Workbook
Name scen_sel: Inputs!$B$4
Name SCEN_TABLE: Inputs!$A$18:$F$23
Name WAL_A: Scenario_Summary!$G$7
Name YIELD_A: Scenario_Summary!$H$7
Name LOSS_A: Scenario_Summary!$E$7
Name PRINPAID_A: Scenario_Summary!$D$7
Name INTPAID_A: Scenario_Summary!$C$7
Name CF_A: CashFlows!$F$5:$F$101
Name FV_A: Retention!$C$6
Name FVLIVE_A: Retention!$D$6
Name FVLOCK_A: Inputs!$B$81
Name WAL_B: Scenario_Summary!$G$8
Name YIELD_B: Scenario_Summary!$H$8
Name LOSS_B: Scenario_Summary!$E$8
Name PRINPAID_B: Scenario_Summary!$D$8
Name INTPAID_B: Scenario_Summary!$C$8
Name CF_B: CashFlows!$K$5:$K$101
Name FV_B: Retention!$C$7
Name FVLIVE_B: Retention!$D$7
Name FVLOCK_B: Inputs!$B$82
Name WAL_C: Scenario_Summary!$G$9
Name YIELD_C: Scenario_Summary!$H$9
Name LOSS_C: Scenario_Summary!$E$9
Name PRINPAID_C: Scenario_Summary!$D$9
Name INTPAID_C: Scenario_Summary!$C$9
Name CF_C: CashFlows!$P$5:$P$101
Name FV_C: Retention!$C$8
Name FVLIVE_C: Retention!$D$8
Name FVLOCK_C: Inputs!$B$83
Name WAL_R: Scenario_Summary!$G$10
Name YIELD_R: Scenario_Summary!$H$10
Name LOSS_R: Scenario_Summary!$E$10
Name PRINPAID_R: Scenario_Summary!$D$10
Name INTPAID_R: Scenario_Summary!$C$10
Name CF_R: CashFlows!$S$5:$S$101
Name FV_R: Retention!$C$9
Name FVLIVE_R: Retention!$D$9
Name FVLOCK_R: Inputs!$B$84
Name ENDBAL_A: CashFlows!$E$5:$E$101
Name ENDBAL_B: CashFlows!$J$5:$J$101
Name ENDBAL_C: CashFlows!$O$5:$O$101
Name CHECK_POOL_RECON: Scenario_Summary!$B$15
Name CHECK_CASH: Scenario_Summary!$B$16
Name CHECK_NOTES_OVER_CASH: Scenario_Summary!$B$17
Name BREACH_MONTHS: Scenario_Summary!$B$21
Name FRAC_TABLE: Retention!$B$15:$E$19
Name RET_AMOUNTS: Retention!$F$15:$H$19
Name RET_OUT: Retention!$B$28:$I$32
Name INPUT_POOL_BAL: Inputs!$B$49
Name INPUT_BAL_R: Inputs!$B$50
Name RETCF_RRV: Retention_CF!$H$5:$H$101
Name RETCF_RRH: Retention_CF!$M$5:$M$101
Name RETCF_RRL: Retention_CF!$R$5:$R$101
Name RETCF_EUV: Retention_CF!$W$5:$W$101
Name RETCF_EUFL: Retention_CF!$AB$5:$AB$101
Name POOL_END: Pool!$BP$5:$BP$101
Name POOL_CASH: Pool!$BW$5:$BW$101
Name ES_BPS: Tests!$O$5:$O$101
Name IN_SCEN_SEL: Inputs!$B$4
Name IN_POOL_BAL: Inputs!$B$49

Sheet Inputs
A1: Inputs (typed values live only on this sheet). Collateral is SYNTHETIC; forward curve is ASSUMED.
A3: Active scenario
A4: Selected scenario number (1-based row of scenario table) | B4: 1
A5: Pool rep lines (name, balance, WAC, remaining term)
A6: RL01 | B6: 60000000 | C6: 0.065 | D6: 60
A7: RL02 | B7: 55000000 | C7: 0.0725 | D7: 72
A8: RL03 | B8: 50000000 | C8: 0.08 | D8: 48
A9: RL04 | B9: 48000000 | C9: 0.0875 | D9: 66
A10: RL05 | B10: 45000000 | C10: 0.095 | D10: 60
A11: RL06 | B11: 40000000 | C11: 0.1025 | D11: 84
A12: RL07 | B12: 35000000 | C12: 0.11 | D12: 54
A13: RL08 | B13: 30000000 | C13: 0.1175 | D13: 72
A14: RL09 | B14: 22000000 | C14: 0.125 | D14: 36
A15: RL10 | B15: 15000000 | C15: 0.135 | D15: 48
A17: Scenario table (name, CPR, CDR, severity, recovery lag months, forward shift bps)
A18: Base | B18: 0.1 | C18: 0.03 | D18: 0.4 | E18: 6 | F18: 0
A19: Mild stress | B19: 0.1 | C19: 0.06 | D19: 0.5 | E19: 6 | F19: 0
A20: Stress | B20: 0.06 | C20: 0.12 | D20: 0.6 | E20: 9 | F20: 0
A21: Severe stress | B21: 0.04 | C21: 0.2 | D21: 0.7 | E21: 12 | F21: 0
A22: Fast prepay | B22: 0.3 | C22: 0.03 | D22: 0.4 | E22: 6 | F22: 0
A23: Rate shock +300bp | B23: 0.1 | C23: 0.06 | D23: 0.5 | E23: 6 | F23: 300
A25: Active scenario values (formulas)
A26: Scenario name | B26: =INDEX($A$18:$A$23,Inputs!$B$4)
A27: CPR | B27: =INDEX($B$18:$B$23,Inputs!$B$4) | C27: annual
A28: CDR | B28: =INDEX($C$18:$C$23,Inputs!$B$4) | C28: annual
A29: Loss severity | B29: =INDEX($D$18:$D$23,Inputs!$B$4) | C29: of defaulted balance
A30: Recovery lag (months) | B30: =INDEX($E$18:$E$23,Inputs!$B$4)
A31: Forward curve shift (bps) | B31: =INDEX($F$18:$F$23,Inputs!$B$4)
A32: SMM | B32: =1-(1-Inputs!$B$27)^(1/12) | C32: monthly
A33: MDR | B33: =1-(1-Inputs!$B$28)^(1/12) | C33: monthly
A35: Curve, notes, fees, reserve
A36: Forward index at t=0 | B36: 0.043
A37: Forward index long-run | B37: 0.0325
A38: Curve time constant (months) | B38: 24
A39: Class A balance | B39: 300000000
A40: Class B balance | B40: 40000000
A41: Class C balance | B41: 30000000
A42: Class A margin over index | B42: 0.011
A43: Class B margin over index | B43: 0.0225
A44: Class C fixed coupon | B44: 0.075
A45: Servicing fee (annual) | B45: 0.006
A46: Trustee fee (annual) | B46: 0.0003
A47: Reserve account initial funding | B47: 3000000
A48: Reserve account target | B48: 3000000
A49: Pool balance | B49: =SUM($B$6:$B$15)
A50: Residual balance (pool + reserve - A - B - C) | B50: =Inputs!$B$49+Inputs!$B$47-Inputs!$B$39-Inputs!$B$40-Inputs!$B$41
A51: Senior fee rate (annual) | B51: =Inputs!$B$45+Inputs!$B$46
A52: Principal mode (sequential or pro_rata) | B52: sequential
A53: Sequential flag | B53: =IF(Inputs!$B$52="sequential",1,0)
A55: Credit enhancement triggers
A56: OC test Class A minimum | B56: 1.25
A57: OC test Class B minimum | B57: 1.12
A58: OC test Class C minimum | B58: 1.045
A59: IC test Class A minimum | B59: 1.5
A60: IC test Class B minimum | B60: 1.3
A61: IC test Class C minimum | B61: 1.15
A63: Retention, fair value margins, financing
A64: FV margin A over forward | B64: 0.011
A65: FV margin B | B65: 0.0275
A66: FV margin C | B66: 0.045
A67: FV margin residual | B67: 0.12
A68: Required retention | B68: 0.05
A69: L-shape vertical share | B69: 0.025
A70: EU vertical: A sold (1/0) | B70: 1
A71: EU vertical: B sold (1/0) | B71: 1
A72: EU vertical: C sold (1/0) | B72: 1
A73: EU vertical: R sold (1/0) | B73: 1
A74: Advance rate A | B74: 0.85
A75: Advance rate B | B75: 0.7
... A78: Financing spread over forward | B78: 0.0275
A80: Optional FV sizing override: leave blank to size retention on the selected scenario, or paste base-case fair values to fix sizing at closing
A81: Locked fair value A
A82: Locked fair value B
A83: Locked fair value C
A84: Locked fair value R

Sheet Pool
A1: Pool
A2: Rep-line amortization. Order: defaults, interest, scheduled principal, prepayment. Period 0 is closing.
A4: Period | B4: Forward index | C4: RL01 beg | D4: RL01 defaults | E4: RL01 interest | F4: RL01 sched prin | G4: RL01 prepay | H4: RL01 end | I4: RL02 beg | J4: RL02 defaults | K4: RL02 interest | L4: RL02 sched prin | M4: RL02 prepay | N4: RL02 end | O4: RL03 beg | P4: RL03 defaults | Q4: RL03 interest | R4: RL03 sched prin | S4: RL03 prepay | T4: RL03 end | U4: RL04 beg | V4: RL04 defaults | W4: RL04 interest | X4: RL04 sched prin | Y4: RL04 prepay | Z4: RL04 end | AA4: RL05 beg | AB4: RL05 defaults | AC4: RL05 interest | AD4: RL05 sched prin | AE4: RL05 prepay | AF4: RL05 end | AG4: RL06 beg | AH4: RL06 defaults | AI4: RL06 interest | AJ4: RL06 sched prin | AK4: RL06 prepay | AL4: RL06 end | AM4: RL07 beg | AN4: RL07 defaults | AO4: RL07 interest | AP4: RL07 sched prin | AQ4: RL07 prepay | AR4: RL07 end | AS4: RL08 beg | AT4: RL08 defaults | AU4: RL08 interest | AV4: RL08 sched prin | AW4: RL08 prepay | AX4: RL08 end | AY4: RL09 beg | AZ4: RL09 defaults | BA4: RL09 interest | BB4: RL09 sched prin | BC4: RL09 prepay | BD4: RL09 end | BE4: RL10 beg | BF4: RL10 defaults | BG4: RL10 interest | BH4: RL10 sched prin | BI4: RL10 prepay | BJ4: RL10 end | BK4: Pool beg balance | BL4: Pool defaults | BM4: Pool interest | BN4: Pool sched principal | BO4: Pool prepayments | BP4: Pool end balance | BQ4: Recoveries | BR4: Cum defaults | BS4: Cum recoveries | BT4: Cum net loss (default x severity) | BU4: Pending recoveries | BV4: Collateral value (end + pending) | BW4: Collateral cash in | BX4: Balance recon (beg-def-sch-pre-end)
A5: 0 | B5: =Inputs!$B$36+(Inputs!$B$37-Inputs!$B$36)*(1-EXP(-A5/Inputs!$B$38))+Inputs!$B$31/10000 | H5: =Inputs!$B$6 | N5: =Inputs!$B$7 | T5: =Inputs!$B$8 | Z5: =Inputs!$B$9 | AF5: =Inputs!$B$10 | AL5: =Inputs!$B$11 | AR5: =Inputs!$B$12 | AX5: =Inputs!$B$13 | BD5: =Inputs!$B$14 | BJ5: =Inputs!$B$15 | BP5: =H5+N5+T5+Z5+AF5+AL5+AR5+AX5+BD5+BJ5 | BR5: 0 | BS5: 0 | BT5: 0 | BU5: 0 | BV5: =BP5+BU5
A6: 1 | B6: =Inputs!$B$36+(Inputs!$B$37-Inputs!$B$36)*(1-EXP(-A6/Inputs!$B$38))+Inputs!$B$31/10000 | C6: =H5 | D6: =C6*Inputs!$B$33 | E6: =(C6-D6)*Inputs!$C$6/12 | F6: =IF(MAX(Inputs!$D$6-(A6-1),0)<=0,0,(C6-D6)*((Inputs!$C$6/12)/(1-(1+Inputs!$C$6/12)^(-MAX(Inputs!$D$6-(A6-1),0)))-Inputs!$C$6/12)) | G6: =(C6-D6-F6)*Inputs!$B$32 | H6: =C6-D6-F6-G6 | I6: =N5 | J6: =I6*Inputs!$B$33 | K6: =(I6-J6)*Inputs!$C$7/12 | L6: =IF(MAX(Inputs!$D$7-(A6-1),0)<=0,0,(I6-J6)*((Inputs!$C$7/12)/(1-(1+Inputs!$C$7/12)^(-MAX(Inputs!$D$7-(A6-1),0)))-Inputs!$C$7/12)) | M6: =(I6-J6-L6)*Inputs!$B$32 | N6: =I6-J6-L6-M6 | O6: =T5 | P6: =O6*Inputs!$B$33 | Q6: =(O6-P6)*Inputs!$C$8/12 | R6: =IF(MAX(Inputs!$D$8-(A6-1),0)<=0,0,(O6-P6)*((Inputs!$C$8/12)/(1-(1+Inputs!$C$8/12)^(-MAX(Inputs!$D$8-(A6-1),0)))-Inputs!$C$8/12)) | S6: =(O6-P6-R6)*Inputs!$B$32 | T6: =O6-P6-R6-S6 | U6: =Z5 | V6: =U6*Inputs!$B$33 | W6: =(U6-V6)*Inputs!$C$9/12 | X6: =IF(MAX(Inputs!$D$9-(A6-1),0)<=0,0,(U6-V6)*((Inputs!$C$9/12)/(1-(1+Inputs!$C$9/12)^(-MAX(Inputs!$D$9-(A6-1),0)))-Inputs!$C$9/12)) | Y6: =(U6-V6-X6)*Inputs!$B$32 | Z6: =U6-V6-X6-Y6 | AA6: =AF5 | AB6: =AA6*Inputs!$B$33 | AC6: =(AA6-AB6)*Inputs!$C$10/12 | AD6: =IF(MAX(Inputs!$D$10-(A6-1),0)<=0,0,(AA6-AB6)*((Inputs!$C$10/12)/(1-(1+Inputs!$C$10/12)^(-MAX(Inputs!$D$10-(A6-1),0)))-Inputs!$C$10/12)) | AE6: =(AA6-AB6-AD6)*Inputs!$B$32 | AF6: =AA6-AB6-AD6-AE6 | AG6: =AL5 | AH6: =AG6*Inputs!$B$33 | AI6: =(AG6-AH6)*Inputs!$C$11/12 | AJ6: =IF(MAX(Inputs!$D$11-(A6-1),0)<=0,0,(AG6-AH6)*((Inputs!$C$11/12)/(1-(1+Inputs!$C$11/12)^(-MAX(Inputs!$D$11-(A6-1),0)))-Inputs!$C$11/12)) | AK6: =(AG6-AH6-AJ6)*Inputs!$B$32 | AL6: =AG6-AH6-AJ6-AK6 | AM6: =AR5 | AN6: =AM6*Inputs!$B$33 | AO6: =(AM6-AN6)*Inputs!$C$12/12 | AP6: =IF(MAX(Inputs!$D$12-(A6-1),0)<=0,0,(AM6-AN6)*((Inputs!$C$12/12)/(1-(1+Inputs!$C$12/12)^(-MAX(Inputs!$D$12-(A6-1),0)))-Inputs!$C$12/12)) | AQ6: =(AM6-AN6-AP6)*Inputs!$B$32 | AR6: =AM6-AN6-AP6-AQ6 | AS6: =AX5 | AT6: =AS6*Inputs!$B$33 | AU6: =(AS6-AT6)*Inputs!$C$13/12 | AV6: =IF(MAX(Inputs!$D$13-(A6-1),0)<=0,0,(AS6-AT6)*((Inputs!$C$13/12)/(1-(1+Inputs!$C$13/12)^(-MAX(Inputs!$D$13-(A6-1),0)))-Inputs!$C$13/12)) | AW6: =(AS6-AT6-AV6)*Inputs!$B$32 | AX6: =AS6-AT6-AV6-AW6 | AY6: =BD5 | AZ6: =AY6*Inputs!$B$33 | BA6: =(AY6-AZ6)*Inputs!$C$14/12 | BB6: =IF(MAX(Inputs!$D$14-(A6-1),0)<=0,0,(AY6-AZ6)*((Inputs!$C$14/12)/(1-(1+Inputs!$C$14/12)^(-MAX(Inputs!$D$14-(A6-1),0)))-Inputs!$C$14/12)) | BC6: =(AY6-AZ6-BB6)*Inputs!$B$32 | BD6: =AY6-AZ6-BB6-BC6 | BE6: =BJ5 | BF6: =BE6*Inputs!$B$33 | BG6: =(BE6-BF6)*Inputs!$C$15/12 | BH6: =IF(MAX(Inputs!$D$15-(A6-1),0)<=0,0,(BE6-BF6)*((Inputs!$C$15/12)/(1-(1+Inputs!$C$15/12)^(-MAX(Inputs!$D$15-(A6-1),0)))-Inputs!$C$15/12)) | BI6: =(BE6-BF6-BH6)*Inputs!$B$32 | BJ6: =BE6-BF6-BH6-BI6 | BK6: =C6+I6+O6+U6+AA6+AG6+AM6+AS6+AY6+BE6 | BL6: =D6+J6+P6+V6+AB6+AH6+AN6+AT6+AZ6+BF6 | BM6: =E6+K6+Q6+W6+AC6+AI6+AO6+AU6+BA6+BG6 | BN6: =F6+L6+R6+X6+AD6+AJ6+AP6+AV6+BB6+BH6 | BO6: =G6+M6+S6+Y6+AE6+AK6+AQ6+AW6+BC6+BI6 | BP6: =H6+N6+T6+Z6+AF6+AL6+AR6+AX6+BD6+BJ6 | BQ6: =IF(A6-Inputs!$B$30>=1,INDEX($BL$5:$BL$101,A6-Inputs!$B$30+1)*(1-Inputs!$B$29),0) | BR6: =BR5+BL6 | BS6: =BS5+BQ6 | BT6: =BR6*Inputs!$B$29 | BU6: =BR6*(1-Inputs!$B$29)-BS6 | BV6: =BP6+BU6 | BW6: =BM6+BN6+BO6+BQ6 | BX6: =BK6-BL6-BN6-BO6-BP6
A7: 2 | B7: =Inputs!$B$36+(Inputs!$B$37-Inputs!$B$36)*(1-EXP(-A7/Inputs!$B$38))+Inputs!$B$31/10000 | C7: =H6 | D7: =C7*Inputs!$B$33 | E7: =(C7-D7)*Inputs!$C$6/12 | F7: =IF(MAX(Inputs!$D$6-(A7-1),0)<=0,0,(C7-D7)*((Inputs!$C$6/12)/(1-(1+Inputs!$C$6/12)^(-MAX(Inputs!$D$6-(A7-1),0)))-Inputs!$C$6/12)) | G7: =(C7-D7-F7)*Inputs!$B$32 | H7: =C7-D7-F7-G7 | I7: =N6 | J7: =I7*Inputs!$B$33 | K7: =(I7-J7)*Inputs!$C$7/12 | L7: =IF(MAX(Inputs!$D$7-(A7-1),0)<=0,0,(I7-J7)*((Inputs!$C$7/12)/(1-(1+Inputs!$C$7/12)^(-MAX(Inputs!$D$7-(A7-1),0)))-Inputs!$C$7/12)) | M7: =(I7-J7-L7)*Inputs!$B$32 | N7: =I7-J7-L7-M7 | O7: =T6 | P7: =O7*Inputs!$B$33 | Q7: =(O7-P7)*Inputs!$C$8/12 | R7: =IF(MAX(Inputs!$D$8-(A7-1),0)<=0,0,(O7-P7)*((Inputs!$C$8/12)/(1-(1+Inputs!$C$8/12)^(-MAX(Inputs!$D$8-(A7-1),0)))-Inputs!$C$8/12)) | S7: =(O7-P7-R7)*Inputs!$B$32 | T7: =O7-P7-R7-S7 | U7: =Z6 | V7: =U7*Inputs!$B$33 | W7: =(U7-V7)*Inputs!$C$9/12 | X7: =IF(MAX(Inputs!$D$9-(A7-1),0)<=0,0,(U7-V7)*((Inputs!$C$9/12)/(1-(1+Inputs!$C$9/12)^(-MAX(Inputs!$D$9-(A7-1),0)))-Inputs!$C$9/12)) | Y7: =(U7-V7-X7)*Inputs!$B$32 | Z7: =U7-V7-X7-Y7 | AA7: =AF6 | AB7: =AA7*Inputs!$B$33 | AC7: =(AA7-AB7)*Inputs!$C$10/12 | AD7: =IF(MAX(Inputs!$D$10-(A7-1),0)<=0,0,(AA7-AB7)*((Inputs!$C$10/12)/(1-(1+Inputs!$C$10/12)^(-MAX(Inputs!$D$10-(A7-1),0)))-Inputs!$C$10/12)) | AE7: =(AA7-AB7-AD7)*Inputs!$B$32 | AF7: =AA7-AB7-AD7-AE7 | AG7: =AL6 | AH7: =AG7*Inputs!$B$33 | AI7: =(AG7-AH7)*Inputs!$C$11/12 | AJ7: =IF(MAX(Inputs!$D$11-(A7-1),0)<=0,0,(AG7-AH7)*((Inputs!$C$11/12)/(1-(1+Inputs!$C$11/12)^(-MAX(Inputs!$D$11-(A7-1),0)))-Inputs!$C$11/12)) | AK7: =(AG7-AH7-AJ7)*Inputs!$B$32 | AL7: =AG7-AH7-AJ7-AK7 | AM7: =AR6 | AN7: =AM7*Inputs!$B$33 | AO7: =(AM7-AN7)*Inputs!$C$12/12 | AP7: =IF(MAX(Inputs!$D$12-(A7-1),0)<=0,0,(AM7-AN7)*((Inputs!$C$12/12)/(1-(1+Inputs!$C$12/12)^(-MAX(Inputs!$D$12-(A7-1),0)))-Inputs!$C$12/12)) | AQ7: =(AM7-AN7-AP7)*Inputs!$B$32 | AR7: =AM7-AN7-AP7-AQ7 | AS7: =AX6 | AT7: =AS7*Inputs!$B$33 | AU7: =(AS7-AT7)*Inputs!$C$13/12 | AV7: =IF(MAX(Inputs!$D$13-(A7-1),0)<=0,0,(AS7-AT7)*((Inputs!$C$13/12)/(1-(1+Inputs!$C$13/12)^(-MAX(Inputs!$D$13-(A7-1),0)))-Inputs!$C$13/12)) | AW7: =(AS7-AT7-AV7)*Inputs!$B$32 | AX7: =AS7-AT7-AV7-AW7 | AY7: =BD6 | AZ7: =AY7*Inputs!$B$33 | BA7: =(AY7-AZ7)*Inputs!$C$14/12 | BB7: =IF(MAX(Inputs!$D$14-(A7-1),0)<=0,0,(AY7-AZ7)*((Inputs!$C$14/12)/(1-(1+Inputs!$C$14/12)^(-MAX(Inputs!$D$14-(A7-1),0)))-Inputs!$C$14/12)) | BC7: =(AY7-AZ7-BB7)*Inputs!$B$32 | BD7: =AY7-AZ7-BB7-BC7 | BE7: =BJ6 | BF7: =BE7*Inputs!$B$33 | BG7: =(BE7-BF7)*Inputs!$C$15/12 | BH7: =IF(MAX(Inputs!$D$15-(A7-1),0)<=0,0,(BE7-BF7)*((Inputs!$C$15/12)/(1-(1+Inputs!$C$15/12)^(-MAX(Inputs!$D$15-(A7-1),0)))-Inputs!$C$15/12)) | BI7: =(BE7-BF7-BH7)*Inputs!$B$32 | BJ7: =BE7-BF7-BH7-BI7 | BK7: =C7+I7+O7+U7+AA7+AG7+AM7+AS7+AY7+BE7 | BL7: =D7+J7+P7+V7+AB7+AH7+AN7+AT7+AZ7+BF7 | BM7: =E7+K7+Q7+W7+AC7+AI7+AO7+AU7+BA7+BG7 | BN7: =F7+L7+R7+X7+AD7+AJ7+AP7+AV7+BB7+BH7 | BO7: =G7+M7+S7+Y7+AE7+AK7+AQ7+AW7+BC7+BI7 | BP7: =H7+N7+T7+Z7+AF7+AL7+AR7+AX7+BD7+BJ7 | BQ7: =IF(A7-Inputs!$B$30>=1,INDEX($BL$5:$BL$101,A7-Inputs!$B$30+1)*(1-Inputs!$B$29),0) | BR7: =BR6+BL7 | BS7: =BS6+BQ7 | BT7: =BR7*Inputs!$B$29 | BU7: =BR7*(1-Inputs!$B$29)-BS7 | BV7: =BP7+BU7 | BW7: =BM7+BN7+BO7+BQ7 | BX7: =BK7-BL7-BN7-BO7-BP7
A8: 3 | B8: =Inputs!$B$36+(Inputs!$B$37-Inputs!$B$36)*(1-EXP(-A8/Inputs!$B$38))+Inputs!$B$31/10000 | C8: =H7 | D8: =C8*Inputs!$B$33 | E8: =(C8-D8)*Inputs!$C$6/12 | F8: =IF(MAX(Inputs!$D$6-(A8-1),0)<=0,0,(C8-D8)*((Inputs!$C$6/12)/(1-(1+Inputs!$C$6/12)^(-MAX(Inputs!$D$6-(A8-1),0)))-Inputs!$C$6/12)) | G8: =(C8-D8-F8)*Inputs!$B$32 | H8: =C8-D8-F8-G8 | I8: =N7 | J8: =I8*Inputs!$B$33 | K8: =(I8-J8)*Inputs!$C$7/12 | L8: =IF(MAX(Inputs!$D$7-(A8-1),0)<=0,0,(I8-J8)*((Inputs!$C$7/12)/(1-(1+Inputs!$C$7/12)^(-MAX(Inputs!$D$7-(A8-1),0)))-Inputs!$C$7/12)) | M8: =(I8-J8-L8)*Inputs!$B$32 | N8: =I8-J8-L8-M8 | O8: =T7 | P8: =O8*Inputs!$B$33 | Q8: =(O8-P8)*Inputs!$C$8/12 | R8: =IF(MAX(Inputs!$D$8-(A8-1),0)<=0,0,(O8-P8)*((Inputs!$C$8/12)/(1-(1+Inputs!$C$8/12)^(-MAX(Inputs!$D$8-(A8-1),0)))-Inputs!$C$8/12)) | S8: =(O8-P8-R8)*Inputs!$B$32 | T8: =O8-P8-R8-S8 | U8: =Z7 | V8: =U8*Inputs!$B$33 | W8: =(U8-V8)*Inputs!$C$9/12 | X8: =IF(MAX(Inputs!$D$9-(A8-1),0)<=0,0,(U8-V8)*((Inputs!$C$9/12)/(1-(1+Inputs!$C$9/12)^(-MAX(Inputs!$D$9-(A8-1),0)))-Inputs!$C$9/12)) | Y8: =(U8-V8-X8)*Inputs!$B$32 | Z8: =U8-V8-X8-Y8 | AA8: =AF7 | AB8: =AA8*Inputs!$B$33 | AC8: =(AA8-AB8)*Inputs!$C$10/12 | AD8: =IF(MAX(Inputs!$D$10-(A8-1),0)<=0,0,(AA8-AB8)*((Inputs!$C$10/12)/(1-(1+Inputs!$C$10/12)^(-MAX(Inputs!$D$10-(A8-1),0)))-Inputs!$C$10/12)) | AE8: =(AA8-AB8-AD8)*Inputs!$B$32 | AF8: =AA8-AB8-AD8-AE8 | AG8: =AL7 | AH8: =AG8*Inputs!$B$33 | AI8: =(AG8-AH8)*Inputs!$C$11/12 | AJ8: =IF(MAX(Inputs!$D$11-(A8-1),0)<=0,0,(AG8-AH8)*((Inputs!$C$11/12)/(1-(1+Inputs!$C$11/12)^(-MAX(Inputs!$D$11-(A8-1),0)))-Inputs!$C$11/12)) | AK8: =(AG8-AH8-AJ8)*Inputs!$B$32 | AL8: =AG8-AH8-AJ8-AK8 | AM8: =AR7 | AN8: =AM8*Inputs!$B$33 | AO8: =(AM8-AN8)*Inputs!$C$12/12 | AP8: =IF(MAX(Inputs!$D$12-(A8-1),0)<=0,0,(AM8-AN8)*((Inputs!$C$12/12)/(1-(1+Inputs!$C$12/12)^(-MAX(Inputs!$D$12-(A8-1),0)))-Inputs!$C$12/12)) | AQ8: =(AM8-AN8-AP8)*Inputs!$B$32 | AR8: =AM8-AN8-AP8-AQ8 | AS8: =AX7 | AT8: =AS8*Inputs!$B$33 | AU8: =(AS8-AT8)*Inputs!$C$13/12 | AV8: =IF(MAX(Inputs!$D$13-(A8-1),0)<=0,0,(AS8-AT8)*((Inputs!$C$13/12)/(1-(1+Inputs!$C$13/12)^(-MAX(Inputs!$D$13-(A8-1),0)))-Inputs!$C$13/12)) | AW8: =(AS8-AT8-AV8)*Inputs!$B$32 | AX8: =AS8-AT8-AV8-AW8 | AY8: =BD7 | AZ8: =AY8*Inputs!$B$33 | BA8: =(AY8-AZ8)*Inputs!$C$14/12 | BB8: =IF(MAX(Inputs!$D$14-(A8-1),0)<=0,0,(AY8-AZ8)*((Inputs!$C$14/12)/(1-(1+Inputs!$C$14/12)^(-MAX(Inputs!$D$14-(A8-1),0)))-Inputs!$C$14/12)) | BC8: =(AY8-AZ8-BB8)*Inputs!$B$32 | BD8: =AY8-AZ8-BB8-BC8 | BE8: =BJ7 | BF8: =BE8*Inputs!$B$33 | BG8: =(BE8-BF8)*Inputs!$C$15/12 | BH8: =IF(MAX(Inputs!$D$15-(A8-1),0)<=0,0,(BE8-BF8)*((Inputs!$C$15/12)/(1-(1+Inputs!$C$15/12)^(-MAX(Inputs!$D$15-(A8-1),0)))-Inputs!$C$15/12)) | BI8: =(BE8-BF8-BH8)*Inputs!$B$32 | BJ8: =BE8-BF8-BH8-BI8 | BK8: =C8+I8+O8+U8+AA8+AG8+AM8+AS8+AY8+BE8 | BL8: =D8+J8+P8+V8+AB8+AH8+AN8+AT8+AZ8+BF8 | BM8: =E8+K8+Q8+W8+AC8+AI8+AO8+AU8+BA8+BG8 | BN8: =F8+L8+R8+X8+AD8+AJ8+AP8+AV8+BB8+BH8 | BO8: =G8+M8+S8+Y8+AE8+AK8+AQ8+AW8+BC8+BI8 | BP8: =H8+N8+T8+Z8+AF8+AL8+AR8+AX8+BD8+BJ8 | BQ8: =IF(A8-Inputs!$B$30>=1,INDEX($BL$5:$BL$101,A8-Inputs!$B$30+1)*(1-Inputs!$B$29),0) | BR8: =BR7+BL8 | BS8: =BS7+BQ8 | BT8: =BR8*Inputs!$B$29 | BU8: =BR8*(1-Inputs!$B$29)-BS8 | BV8: =BP8+BU8 | BW8: =BM8+BN8+BO8+BQ8 | BX8: =BK8-BL8-BN8-BO8-BP8
A9: 4 | B9: =Inputs!$B$36+(Inputs!$B$37-Inputs!$B$36)*(1-EXP(-A9/Inputs!$B$38))+Inputs!$B$31/10000 | C9: =H8 | D9: =C9*Inputs!$B$33 | E9: =(C9-D9)*Inputs!$C$6/12 | F9: =IF(MAX(Inputs!$D$6-(A9-1),0)<=0,0,(C9-D9)*((Inputs!$C$6/12)/(1-(1+Inputs!$C$6/12)^(-MAX(Inputs!$D$6-(A9-1),0)))-Inputs!$C$6/12)) | G9: =(C9-D9-F9)*Inputs!$B$32 | H9: =C9-D9-F9-G9 | I9: =N8 | J9: =I9*Inputs!$B$33 | K9: =(I9-J9)*Inputs!$C$7/12 | L9: =IF(MAX(Inputs!$D$7-(A9-1),0)<=0,0,(I9-J9)*((Inputs!$C$7/12)/(1-(1+Inputs!$C$7/12)^(-MAX(Inputs!$D$7-(A9-1),0)))-Inputs!$C$7/12)) | M9: =(I9-J9-L9)*Inputs!$B$32 | N9: =I9-J9-L9-M9 | O9: =T8 | P9: =O9*Inputs!$B$33 | Q9: =(O9-P9)*Inputs!$C$8/12 | R9: =IF(MAX(Inputs!$D$8-(A9-1),0)<=0,0,(O9-P9)*((Inputs!$C$8/12)/(1-(1+Inputs!$C$8/12)^(-MAX(Inputs!$D$8-(A9-1),0)))-Inputs!$C$8/12)) | S9: =(O9-P9-R9)*Inputs!$B$32 | T9: =O9-P9-R9-S9 | U9: =Z8 | V9: =U9*Inputs!$B$33 | W9: =(U9-V9)*Inputs!$C$9/12 | X9: =IF(MAX(Inputs!$D$9-(A9-1),0)<=0,0,(U9-V9)*((Inputs!$C$9/12)/(1-(1+Inputs!$C$9/12)^(-MAX(Inputs!$D$9-(A9-1),0)))-Inputs!$C$9/12)) | Y9: =(U9-V9-X9)*Inputs!$B$32 | Z9: =U9-V9-X9-Y9 | AA9: =AF8 | AB9: =AA9*Inputs!$B$33 | AC9: =(AA9-AB9)*Inputs!$C$10/12 | AD9: =IF(MAX(Inputs!$D$10-(A9-1),0)<=0,0,(AA9-AB9)*((Inputs!$C$10/12)/(1-(1+Inputs!$C$10/12)^(-MAX(Inputs!$D$10-(A9-1),0)))-Inputs!$C$10/12)) | AE9: =(AA9-AB9-AD9)*Inputs!$B$32 | AF9: =AA9-AB9-AD9-AE9 | AG9: =AL8 | AH9: =AG9*Inputs!$B$33 | AI9: =(AG9-AH9)*Inputs!$C$11/12 | AJ9: =IF(MAX(Inputs!$D$11-(A9-1),0)<=0,0,(AG9-AH9)*((Inputs!$C$11/12)/(1-(1+Inputs!$C$11/12)^(-MAX(Inputs!$D$11-(A9-1),0)))-Inputs!$C$11/12)) | AK9: =(AG9-AH9-AJ9)*Inputs!$B$32 | AL9: =AG9-AH9-AJ9-AK9 | AM9: =AR8 | AN9: =AM9*Inputs!$B$33 | AO9: =(AM9-AN9)*Inputs!$C$12/12 | AP9: =IF(MAX(Inputs!$D$12-(A9-1),0)<=0,0,(AM9-AN9)*((Inputs!$C$12/12)/(1-(1+Inputs!$C$12/12)^(-MAX(Inputs!$D$12-(A9-1),0)))-Inputs!$C$12/12)) | AQ9: =(AM9-AN9-AP9)*Inputs!$B$32 | AR9: =AM9-AN9-AP9-AQ9 | AS9: =AX8 | AT9: =AS9*Inputs!$B$33 | AU9: =(AS9-AT9)*Inputs!$C$13/12 | AV9: =IF(MAX(Inputs!$D$13-(A9-1),0)<=0,0,(AS9-AT9)*((Inputs!$C$13/12)/(1-(1+Inputs!$C$13/12)^(-MAX(Inputs!$D$13-(A9-1),0)))-Inputs!$C$13/12)) | AW9: =(AS9-AT9-AV9)*Inputs!$B$32 | AX9: =AS9-AT9-AV9-AW9 | AY9: =BD8 | AZ9: =AY9*Inputs!$B$33 | BA9: =(AY9-AZ9)*Inputs!$C$14/12 | BB9: =IF(MAX(Inputs!$D$14-(A9-1),0)<=0,0,(AY9-AZ9)*((Inputs!$C$14/12)/(1-(1+Inputs!$C$14/12)^(-MAX(Inputs!$D$14-(A9-1),0)))-Inputs!$C$14/12)) | BC9: =(AY9-AZ9-BB9)*Inputs!$B$32 | BD9: =AY9-AZ9-BB9-BC9 | BE9: =BJ8 | BF9: =BE9*Inputs!$B$33 | BG9: =(BE9-BF9)*Inputs!$C$15/12 | BH9: =IF(MAX(Inputs!$D$15-(A9-1),0)<=0,0,(BE9-BF9)*((Inputs!$C$15/12)/(1-(1+Inputs!$C$15/12)^(-MAX(Inputs!$D$15-(A9-1),0)))-Inputs!$C$15/12)) | BI9: =(BE9-BF9-BH9)*Inputs!$B$32 | BJ9: =BE9-BF9-BH9-BI9 | BK9: =C9+I9+O9+U9+AA9+AG9+AM9+AS9+AY9+BE9 | BL9: =D9+J9+P9+V9+AB9+AH9+AN9+AT9+AZ9+BF9 | BM9: =E9+K9+Q9+W9+AC9+AI9+AO9+AU9+BA9+BG9 | BN9: =F9+L9+R9+X9+AD9+AJ9+AP9+AV9+BB9+BH9 | BO9: =G9+M9+S9+Y9+AE9+AK9+AQ9+AW9+BC9+BI9 | BP9: =H9+N9+T9+Z9+AF9+AL9+AR9+AX9+BD9+BJ9 | BQ9: =IF(A9-Inputs!$B$30>=1,INDEX($BL$5:$BL$101,A9-Inputs!$B$30+1)*(1-Inputs!$B$29),0) | BR9: =BR8+BL9 | BS9: =BS8+BQ9 | BT9: =BR9*Inputs!$B$29 | BU9: =BR9*(1-Inputs!$B$29)-BS9 | BV9: =BP9+BU9 | BW9: =BM9+BN9+BO9+BQ9 | BX9: =BK9-BL9-BN9-BO9-BP9
A10: 5 | B10: =Inputs!$B$36+(Inputs!$B$37-Inputs!$B$36)*(1-EXP(-A10/Inputs!$B$38))+Inputs!$B$31/10000 | C10: =H9 | D10: =C10*Inputs!$B$33 | E10: =(C10-D10)*Inputs!$C$6/12 | F10: =IF(MAX(Inputs!$D$6-(A10-1),0)<=0,0,(C10-D10)*((Inputs!$C$6/12)/(1-(1+Inputs!$C$6/12)^(-MAX(Inputs!$D$6-(A10-1),0)))-Inputs!$C$6/12)) | G10: =(C10-D10-F10)*Inputs!$B$32 | H10: =C10-D10-F10-G10 | I10: =N9 | J10: =I10*Inputs!$B$33 | K10: =(I10-J10)*Inputs!$C$7/12 | L10: =IF(MAX(Inputs!$D$7-(A10-1),0)<=0,0,(I10-J10)*((Inputs!$C$7/12)/(1-(1+Inputs!$C$7/12)^(-MAX(Inputs!$D$7-(A10-1),0)))-Inputs!$C$7/12)) | M10: =(I10-J10-L10)*Inputs!$B$32 | N10: =I10-J10-L10-M10 | O10: =T9 | P10: =O10*Inputs!$B$33 | Q10: =(O10-P10)*Inputs!$C$8/12 | R10: =IF(MAX(Inputs!$D$8-(A10-1),0)<=0,0,(O10-P10)*((Inputs!$C$8/12)/(1-(1+Inputs!$C$8/12)^(-MAX(Inputs!$D$8-(A10-1),0)))-Inputs!$C$8/12)) | S10: =(O10-P10-R10)*Inputs!$B$32 | T10: =O10-P10-R10-S10 | U10: =Z9 | V10: =U10*Inputs!$B$33 | W10: =(U10-V10)*Inputs!$C$9/12 | X10: =IF(MAX(Inputs!$D$9-(A10-1),0)<=0,0,(U10-V10)*((Inputs!$C$9/12)/(1-(1+Inputs!$C$9/12)^(-MAX(Inputs!$D$9-(A10-1),0)))-Inputs!$C$9/12)) | Y10: =(U10-V10-X10)*Inputs!$B$32 | Z10: =U10-V10-X10-Y10 | AA10: =AF9 | AB10: =AA10*Inputs!$B$33 | AC10: =(AA10-AB10)*Inputs!$C$10/12 | AD10: =IF(MAX(Inputs!$D$10-(A10-1),0)<=0,0,(AA10-AB10)*((Inputs!$C$10/12)/(1-(1+Inputs!$C$10/12)^(-MAX(Inputs!$D$10-(A10-1),0)))-Inputs!$C$10/12)) | AE10: =(AA10-AB10-AD10)*Inputs!$B$32 | AF10: =AA10-AB10-AD10-AE10 | AG10: =AL9 | AH10: =AG10*Inputs!$B$33 | AI10: =(AG10-AH10)*Inputs!$C$11/12 | AJ10: =IF(MAX(Inputs!$D$11-(A10-1),0)<=0,0,(AG10-AH10)*((Inputs!$C$11/12)/(1-(1+Inputs!$C$11/12)^(-MAX(Inputs!$D$11-(A10-1),0)))-Inputs!$C$11/12)) | AK10: =(AG10-AH10-AJ10)*Inputs!$B$32 | AL10: =AG10-AH10-AJ10-AK10 | AM10: =AR9 | AN10: =AM10*Inputs!$B$33 | AO10: =(AM10-AN10)*Inputs!$C$12/12 | AP10: =IF(MAX(Inputs!$D$12-(A10-1),0)<=0,0,(AM10-AN10)*((Inputs!$C$12/12)/(1-(1+Inputs!$C$12/12)^(-MAX(Inputs!$D$12-(A10-1),0)))-Inputs!$C$12/12)) | AQ10: =(AM10-AN10-AP10)*Inputs!$B$32 | AR10: =AM10-AN10-AP10-AQ10 | AS10: =AX9 | AT10: =AS10*Inputs!$B$33 | AU10: =(AS10-AT10)*Inputs!$C$13/12 | AV10: =IF(MAX(Inputs!$D$13-(A10-1),0)<=0,0,(AS10-AT10)*((Inputs!$C$13/12)/(1-(1+Inputs!$C$13/12)^(-MAX(Inputs!$D$13-(A10-1),0)))-Inputs!$C$13/12)) | AW10: =(AS10-AT10-AV10)*Inputs!$B$32 | AX10: =AS10-AT10-AV10-AW10 | AY10: =BD9 | AZ10: =AY10*Inputs!$B$33 | BA10: =(AY10-AZ10)*Inputs!$C$14/12 | BB10: =IF(MAX(Inputs!$D$14-(A10-1),0)<=0,0,(AY10-AZ10)*((Inputs!$C$14/12)/(1-(1+Inputs!$C$14/12)^(-MAX(Inputs!$D$14-(A10-1),0)))-Inputs!$C$14/12)) | BC10: =(AY10-AZ10-BB10)*Inputs!$B$32 | BD10: =AY10-AZ10-BB10-BC10 | BE10: =BJ9 | BF10: =BE10*Inputs!$B$33 | BG10: =(BE10-BF10)*Inputs!$C$15/12 | BH10: =IF(MAX(Inputs!$D$15-(A10-1),0)<=0,0,(BE10-BF10)*((Inputs!$C$15/12)/(1-(1+Inputs!$C$15/12)^(-MAX(Inputs!$D$15-(A10-1),0)))-Inputs!$C$15/12)) | BI10: =(BE10-BF10-BH10)*Inputs!$B$32 | BJ10: =BE10-BF10-BH10-BI10 | BK10: =C10+I10+O10+U10+AA10+AG10+AM10+AS10+AY10+BE10 | BL10: =D10+J10+P10+V10+AB10+AH10+AN10+AT10+AZ10+BF10 | BM10: =E10+K10+Q10+W10+AC10+AI10+AO10+AU10+BA10+BG10 | BN10: =F10+L10+R10+X10+AD10+AJ10+AP10+AV10+BB10+BH10 | BO10: =G10+M10+S10+Y10+AE10+AK10+AQ10+AW10+BC10+BI10 | BP10: =H10+N10+T10+Z10+AF10+AL10+AR10+AX10+BD10+BJ10 | BQ10: =IF(A10-Inputs!$B$30>=1,INDEX($BL$5:$BL$101,A10-Inputs!$B$30+1)*(1-Inputs!$B$29),0) | BR10: =BR9+BL10 | BS10: =BS9+BQ10 | BT10: =BR10*Inputs!$B$29 | BU10: =BR10*(1-Inputs!$B$29)-BS10 | BV10: =BP10+BU10 | BW10: =BM10+BN10+BO10+BQ10 | BX10: =BK10-BL10-BN10-BO10-BP10
A11: 6 | B11: =Inputs!$B$36+(Inputs!$B$37-Inputs!$B$36)*(1-EXP(-A11/Inputs!$B$38))+Inputs!$B$31/10000 | C11: =H10 | D11: =C11*Inputs!$B$33 | E11: =(C11-D11)*Inputs!$C$6/12 | F11: =IF(MAX(Inputs!$D$6-(A11-1),0)<=0,0,(C11-D11)*((Inputs!$C$6/12)/(1-(1+Inputs!$C$6/12)^(-MAX(Inputs!$D$6-(A11-1),0)))-Inputs!$C$6/12)) | G11: =(C11-D11-F11)*Inputs!$B$32 | H11: =C11-D11-F11-G11 | I11: =N10 | J11: =I11*Inputs!$B$33 | K11: =(I11-J11)*Inputs!$C$7/12 | L11: =IF(MAX(Inputs!$D$7-(A11-1),0)<=0,0,(I11-J11)*((Inputs!$C$7/12)/(1-(1+Inputs!$C$7/12)^(-MAX(Inputs!$D$7-(A11-1),0)))-Inputs!$C$7/12)) | M11: =(I11-J11-L11)*Inputs!$B$32 | N11: =I11-J11-L11-M11 | O11: =T10 | P11: =O11*Inputs!$B$33 | Q11: =(O11-P11)*Inputs!$C$8/12 | R11: =IF(MAX(Inputs!$D$8-(A11-1),0)<=0,0,(O11-P11)*((Inputs!$C$8/12)/(1-(1+Inputs!$C$8/12)^(-MAX(Inputs!$D$8-(A11-1),0)))-Inputs!$C$8/12)) | S11: =(O11-P11-R11)*Inputs!$B$32 | T11: =O11-P11-R11-S11 | U11: =Z10 | V11: =U11*Inputs!$B$33 | W11: =(U11-V11)*Inputs!$C$9/12 | X11: =IF(MAX(Inputs!$D$9-(A11-1),0)<=0,0,(U11-V11)*((Inputs!$C$9/12)/(1-(1+Inputs!$C$9/12)^(-MAX(Inputs!$D$9-(A11-1),0)))-Inputs!$C$9/12)) | Y11: =(U11-V11-X11)*Inputs!$B$32 | Z11: =U11-V11-X11-Y11 | AA11: =AF10 | AB11: =AA11*Inputs!$B$33 | AC11: =(AA11-AB11)*Inputs!$C$10/12 | AD11: =IF(MAX(Inputs!$D$10-(A11-1),0)<=0,0,(AA11-AB11)*((Inputs!$C$10/12)/(1-(1+Inputs!$C$10/12)^(-MAX(Inputs!$D$10-(A11-1),0)))-Inputs!$C$10/12)) | AE11: =(AA11-AB11-AD11)*Inputs!$B$32 | AF11: =AA11-AB11-AD11-AE11 | AG11: =AL10 | AH11: =AG11*Inputs!$B$33 | AI11: =(AG11-AH11)*Inputs!$C$11/12 | AJ11: =IF(MAX(Inputs!$D$11-(A11-1),0)<=0,0,(AG11-AH11)*((Inputs!$C$11/12)/(1-(1+Inputs!$C$11/12)^(-MAX(Inputs!$D$11-(A11-1),0)))-Inputs!$C$11/12)) | AK11: =(AG11-AH11-AJ11)*Inputs!$B$32 | AL11: =AG11-AH11-AJ11-AK11 | AM11: =AR10 | AN11: =AM11*Inputs!$B$33 | AO11: =(AM11-AN11)*Inputs!$C$12/12 | AP11: =IF(MAX(Inputs!$D$12-(A11-1),0)<=0,0,(AM11-AN11)*((Inputs!$C$12/12)/(1-(1+Inputs!$C$12/12)^(-MAX(Inputs!$D$12-(A11-1),0)))-Inputs!$C$12/12)) | AQ11: =(AM11-AN11-AP11)*Inputs!$B$32 | AR11: =AM11-AN11-AP11-AQ11 | AS11: =AX10 | AT11: =AS11*Inputs!$B$33 | AU11: =(AS11-AT11)*Inputs!$C$13/12 | AV11: =IF(MAX(Inputs!$D$13-(A11-1),0)<=0,0,(AS11-AT11)*((Inputs!$C$13/12)/(1-(1+Inputs!$C$13/12)^(-MAX(Inputs!$D$13-(A11-1),0)))-Inputs!$C$13/12)) | AW11: =(AS11-AT11-AV11)*Inputs!$B$32 | AX11: =AS11-AT11-AV11-AW11 | AY11: =BD10 | AZ11: =AY11*Inputs!$B$33 | BA11: =(AY11-AZ11)*Inputs!$C$14/12 | BB11: =IF(MAX(Inputs!$D$14-(A11-1),0)<=0,0,(AY11-AZ11)*((Inputs!$C$14/12)/(1-(1+Inputs!$C$14/12)^(-MAX(Inputs!$D$14-(A11-1),0)))-Inputs!$C$14/12)) | BC11: =(AY11-AZ11-BB11)*Inputs!$B$32 | BD11: =AY11-AZ11-BB11-BC11 | BE11: =BJ10 | BF11: =BE11*Inputs!$B$33 | BG11: =(BE11-BF11)*Inputs!$C$15/12 | BH11: =IF(MAX(Inputs!$D$15-(A11-1),0)<=0,0,(BE11-BF11)*((Inputs!$C$15/12)/(1-(1+Inputs!$C$15/12)^(-MAX(Inputs!$D$15-(A11-1),0)))-Inputs!$C$15/12)) | BI11: =(BE11-BF11-BH11)*Inputs!$B$32 | BJ11: =BE11-BF11-BH11-BI11 | BK11: =C11+I11+O11+U11+AA11+AG11+AM11+AS11+AY11+BE11 | BL11: =D11+J11+P11+V11+AB11+AH11+AN11+AT11+AZ11+BF11 | BM11: =E11+K11+Q11+W11+AC11+AI11+AO11+AU11+BA11+BG11 | BN11: =F11+L11+R11+X11+AD11+AJ11+AP11+AV11+BB11+BH11 | BO11: =G11+M11+S11+Y11+AE11+AK11+AQ11+AW11+BC11+BI11 | BP11: =H11+N11+T11+Z11+AF11+AL11+AR11+AX11+BD11+BJ11 | BQ11: =IF(A11-Inputs!$B$30>=1,INDEX($BL$5:$BL$101,A11-Inputs!$B$30+1)*(1-Inputs!$B$29),0) | BR11: =BR10+BL11 | BS11: =BS10+BQ11 | BT11: =BR11*Inputs!$B$29 | BU11: =BR11*(1-Inputs!$B$29)-BS11 | BV11: =BP11+BU11 | BW11: =BM11+BN11+BO11+BQ11 | BX11: =BK11-BL11-BN11-BO11-BP11
A12: 7 | B12: =Inputs!$B$36+(Inputs!$B$37-Inputs!$B$36)*(1-EXP(-A12/Inputs!$B$38))+Inputs!$B$31/10000 | C12: =H11 | D12: =C12*Inputs!$B$33 | E12: =(C12-D12)*Inputs!$C$6/12 | F12: =IF(MAX(Inputs!$D$6-(A12-1),0)<=0,0,(C12-D12)*((Inputs!$C$6/12)/(1-(1+Inputs!$C$6/12)^(-MAX(Inputs!$D$6-(A12-1),0)))-Inputs!$C$6/12)) | G12: =(C12-D12-F12)*Inputs!$B$32 | H12: =C12-D12-F12-G12 | I12: =N11 | J12: =I12*Inputs!$B$33 | K12: =(I12-J12)*Inputs!$C$7/12 | L12: =IF(MAX(Inputs!$D$7-(A12-1),0)<=0,0,(I12-J12)*((Inputs!$C$7/12)/(1-(1+Inputs!$C$7/12)^(-MAX(Inputs!$D$7-(A12-1),0)))-Inputs!$C$7/12)) | M12: =(I12-J12-L12)*Inputs!$B$32 | N12: =I12-J12-L12-M12 | O12: =T11 | P12: =O12*Inputs!$B$33 | Q12: =(O12-P12)*Inputs!$C$8/12 | R12: =IF(MAX(Inputs!$D$8-(A12-1),0)<=0,0,(O12-P12)*((Inputs!$C$8/12)/(1-(1+Inputs!$C$8/12)^(-MAX(Inputs!$D$8-(A12-1),0)))-Inputs!$C$8/12)) | S12: =(O12-P12-R12)*Inputs!$B$32 | T12: =O12-P12-R12-S12 | U12: =Z11 | V12: =U12*Inputs!$B$33 | W12: =(U12-V12)*Inputs!$C$9/12 | X12: =IF(MAX(Inputs!$D$9-(A12-1),0)<=0,0,(U12-V12)*((Inputs!$C$9/12)/(1-(1+Inputs!$C$9/12)^(-MAX(Inputs!$D$9-(A12-1),0)))-Inputs!$C$9/12)) | Y12: =(U12-V12-X12)*Inputs!$B$32 | Z12: =U12-V12-X12-Y12 | AA12: =AF11 | AB12: =AA12*Inputs!$B$33 | AC12: =(AA12-AB12)*Inputs!$C$10/12 | AD12: =IF(MAX(Inputs!$D$10-(A12-1),0)<=0,0,(AA12-AB12)*((Inputs!$C$10/12)/(1-(1+Inputs!$C$10/12)^(-MAX(Inputs!$D$10-(A12-1),0)))-Inputs!$C$10/12)) | AE12: =(AA12-AB12-AD12)*Inputs!$B$32 | AF12: =AA12-AB12-AD12-AE12 | AG12: =AL11 | AH12: =AG12*Inputs!$B$33 | AI12: =(AG12-AH12)*Inputs!$C$11/12 | AJ12: =IF(MAX(Inputs!$D$11-(A12-1),0)<=0,0,(AG12-AH12)*((Inputs!$C$11/12)/(1-(1+Inputs!$C$11/12)^(-MAX(Inputs!$D$11-(A12-1),0)))-Inputs!$C$11/12)) | AK12: =(AG12-AH12-AJ12)*Inputs!$B$32 | AL12: =AG12-AH12-AJ12-AK12 | AM12: =AR11 | AN12: =AM12*Inputs!$B$33 | AO12: =(AM12-AN12)*Inputs!$C$12/12 | AP12: =IF(MAX(Inputs!$D$12-(A12-1),0)<=0,0,(AM12-AN12)*((Inputs!$C$12/12)/(1-(1+Inputs!$C$12/12)^(-MAX(Inputs!$D$12-(A12-1),0)))-Inputs!$C$12/12)) | AQ12: =(AM12-AN12-AP12)*Inputs!$B$32 | AR12: =AM12-AN12-AP12-AQ12 | AS12: =AX11 | AT12: =AS12*Inputs!$B$33 | AU12: =(AS12-AT12)*Inputs!$C$13/12 | AV12: =IF(MAX(Inputs!$D$13-(A12-1),0)<=0,0,(AS12-AT12)*((Inputs!$C$13/12)/(1-(1+Inputs!$C$13/12)^(-MAX(Inputs!$D$13-(A12-1),0)))-Inputs!$C$13/12)) | AW12: =(AS12-AT12-AV12)*Inputs!$B$32 | AX12: =AS12-AT12-AV12-AW12 | AY12: =BD11 | AZ12: =AY12*Inputs!$B$33 | BA12: =(AY12-AZ12)*Inputs!$C$14/12 | BB12: =IF(MAX(Inputs!$D$14-(A12-1),0)<=0,0,(AY12-AZ12)*((Inputs!$C$14/12)/(1-(1+Inputs!$C$14/12)^(-MAX(Inputs!$D$14-(A12-1),0)))-Inputs!$C$14/12)) | BC12: =(AY12-AZ12-BB12)*Inputs!$B$32 | BD12: =AY12-AZ12-BB12-BC12 | BE12: =BJ11 | BF12: =BE12*Inputs!$B$33 | BG12: =(BE12-BF12)*Inputs!$C$15/12 | BH12: =IF(MAX(Inputs!$D$15-(A12-1),0)<=0,0,(BE12-BF12)*((Inputs!$C$15/12)/(1-(1+Inputs!$C$15/12)^(-MAX(Inputs!$D$15-(A12-1),0)))-Inputs!$C$15/12)) | BI12: =(BE12-BF12-BH12)*Inputs!$B$32 | BJ12: =BE12-BF12-BH12-BI12 | BK12: =C12+I12+O12+U12+AA12+AG12+AM12+AS12+AY12+BE12 | BL12: =D12+J12+P12+V12+AB12+AH12+AN12+AT12+AZ12+BF12 | BM12: =E12+K12+Q12+W12+AC12+AI12+AO12+AU12+BA12+BG12 | BN12: =F12+L12+R12+X12+AD12+AJ12+AP12+AV12+BB12+BH12 | BO12: =G12+M12+S12+Y12+AE12+AK12+AQ12+AW12+BC12+BI12 | BP12: =H12+N12+T12+Z12+AF12+AL12+AR12+AX12+BD12+BJ12 | BQ12: =IF(A12-Inputs!$B$30>=1,INDEX($BL$5:$BL$101,A12-Inputs!$B$30+1)*(1-Inputs!$B$29),0) | BR12: =BR11+BL12 | BS12: =BS11+BQ12 | BT12: =BR12*Inputs!$B$29 | BU12: =BR12*(1-Inputs!$B$29)-BS12 | BV12: =BP12+BU12 | BW12: =BM12+BN12+BO12+BQ12 | BX12: =BK12-BL12-BN12-BO12-BP12
A13: 8 | B13: =Inputs!$B$36+(Inputs!$B$37-Inputs!$B$36)*(1-EXP(-A13/Inputs!$B$38))+Inputs!$B$31/10000 | C13: =H12 | D13: =C13*Inputs!$B$33 | E13: =(C13-D13)*Inputs!$C$6/12 | F13: =IF(MAX(Inputs!$D$6-(A13-1),0)<=0,0,(C13-D13)*((Inputs!$C$6/12)/(1-(1+Inputs!$C$6/12)^(-MAX(Inputs!$D$6-(A13-1),0)))-Inputs!$C$6/12)) | G13: =(C13-D13-F13)*Inputs!$B$32 | H13: =C13-D13-F13-G13 | I13: =N12 | J13: =I13*Inputs!$B$33 | K13: =(I13-J13)*Inputs!$C$7/12 | L13: =IF(MAX(Inputs!$D$7-(A13-1),0)<=0,0,(I13-J13)*((Inputs!$C$7/12)/(1-(1+Inputs!$C$7/12)^(-MAX(Inputs!$D$7-(A13-1),0)))-Inputs!$C$7/12)) | M13: =(I13-J13-L13)*Inputs!$B$32 | N13: =I13-J13-L13-M13 | O13: =T12 | P13: =O13*Inputs!$B$33 | Q13: =(O13-P13)*Inputs!$C$8/12 | R13: =IF(MAX(Inputs!$D$8-(A13-1),0)<=0,0,(O13-P13)*((Inputs!$C$8/12)/(1-(1+Inputs!$C$8/12)^(-MAX(Inputs!$D$8-(A13-1),0)))-Inputs!$C$8/12)) | S13: =(O13-P13-R13)*Inputs!$B$32 | T13: =O13-P13-R13-S13 | U13: =Z12 | V13: =U13*Inputs!$B$33 | W13: =(U13-V13)*Inputs!$C$9/12 | X13: =IF(MAX(Inputs!$D$9-(A13-1),0)<=0,0,(U13-V13)*((Inputs!$C$9/12)/(1-(1+Inputs!$C$9/12)^(-MAX(Inputs!$D$9-(A13-1),0)))-Inputs!$C$9/12)) | Y13: =(U13-V13-X13)*Inputs!$B$32 | Z13: =U13-V13-X13-Y13 | AA13: =AF12 | AB13: =AA13*Inputs!$B$33 | AC13: =(AA13-AB13)*Inputs!$C$10/12 | AD13: =IF(MAX(Inputs!$D$10-(A13-1),0)<=0,0,(AA13-AB13)*((Inputs!$C$10/12)/(1-(1+Inputs!$C$10/12)^(-MAX(Inputs!$D$10-(A13-1),0)))-Inputs!$C$10/12)) | AE13: =(AA13-AB13-AD13)*Inputs!$B$32 | AF13: =AA13-AB13-AD13-AE13 | AG13: =AL12 | AH13: =AG13*Inputs!$B$33 | AI13: =(AG13-AH13)*Inputs!$C$11/12 | AJ13: =IF(MAX(Inputs!$D$11-(A13-1),0)<=0,0,(AG13-AH13)*((Inputs!$C$11/12)/(1-(1+Inputs!$C$11/12)^(-MAX(Inputs!$D$11-(A13-1),0)))-Inputs!$C$11/12)) | AK13: =(AG13-AH13-AJ13)*Inputs!$B$32 | AL13: =AG13-AH13-AJ13-AK13 | AM13: =AR12 | AN13: =AM13*Inputs!$B$33 | AO13: =(AM13-AN13)*Inputs!$C$12/12 | AP13: =IF(MAX(Inputs!$D$12-(A13-1),0)<=0,0,(AM13-AN13)*((Inputs!$C$12/12)/(1-(1+Inputs!$C$12/12)^(-MAX(Inputs!$D$12-(A13-1),0)))-Inputs!$C$12/12)) | AQ13: =(AM13-AN13-AP13)*Inputs!$B$32 | AR13: =AM13-AN13-AP13-AQ13 | AS13: =AX12 | AT13: =AS13*Inputs!$B$33 | AU13: =(AS13-AT13)*Inputs!$C$13/12 | AV13: =IF(MAX(Inputs!$D$13-(A13-1),0)<=0,0,(AS13-AT13)*((Inputs!$C$13/12)/(1-(1+Inputs!$C$13/12)^(-MAX(Inputs!$D$13-(A13-1),0)))-Inputs!$C$13/12)) | AW13: =(AS13-AT13-AV13)*Inputs!$B$32 | AX13: =AS13-AT13-AV13-AW13 | AY13: =BD12 | AZ13: =AY13*Inputs!$B$33 | BA13: =(AY13-AZ13)*Inputs!$C$14/12 | BB13: =IF(MAX(Inputs!$D$14-(A13-1),0)<=0,0,(AY13-AZ13)*((Inputs!$C$14/12)/(1-(1+Inputs!$C$14/12)^(-MAX(Inputs!$D$14-(A13-1),0)))-Inputs!$C$14/12)) | BC13: =(AY13-AZ13-BB13)*Inputs!$B$32 | BD13: =AY13-AZ13-BB13-BC13 | BE13: =BJ12 | BF13: =BE13*Inputs!$B$33 | BG13: =(BE13-BF13)*Inputs!$C$15/12 | BH13: =IF(MAX(Inputs!$D$15-(A13-1),0)<=0,0,(BE13-BF13)*((Inputs!$C$15/12)/(1-(1+Inputs!$C$15/12)^(-MAX(Inputs!$D$15-(A13-1),0)))-Inputs!$C$15/12)) | BI13: =(BE13-BF13-BH13)*Inputs!$B$32 | BJ13: =BE13-BF13-BH13-BI13 | BK13: =C13+I13+O13+U13+AA13+AG13+AM13+AS13+AY13+BE13 | BL13: =D13+J13+P13+V13+AB13+AH13+AN13+AT13+AZ13+BF13 | BM13: =E13+K13+Q13+W13+AC13+AI13+AO13+AU13+BA13+BG13 | BN13: =F13+L13+R13+X13+AD13+AJ13+AP13+AV13+BB13+BH13 | BO13: =G13+M13+S13+Y13+AE13+AK13+AQ13+AW13+BC13+BI13 | BP13: =H13+N13+T13+Z13+AF13+AL13+AR13+AX13+BD13+BJ13 | BQ13: =IF(A13-Inputs!$B$30>=1,INDEX($BL$5:$BL$101,A13-Inputs!$B$30+1)*(1-Inputs!$B$29),0) | BR13: =BR12+BL13 | BS13: =BS12+BQ13 | BT13: =BR13*Inputs!$B$29 | BU13: =BR13*(1-Inputs!$B$29)-BS13 | BV13: =BP13+BU13 | BW13: =BM13+BN13+BO13+BQ13 | BX13: =BK13-BL13-BN13-BO13-BP13
A14: 9 | B14: =Inputs!$B$36+(Inputs!$B$37-Inputs!$B$36)*(1-EXP(-A14/Inputs!$B$38))+Inputs!$B$31/10000 | C14: =H13 | D14: =C14*Inputs!$B$33 | E14: =(C14-D14)*Inputs!$C$6/12 | F14: =IF(MAX(Inputs!$D$6-(A14-1),0)<=0,0,(C14-D14)*((Inputs!$C$6/12)/(1-(1+Inputs!$C$6/12)^(-MAX(Inputs!$D$6-(A14-1),0)))-Inputs!$C$6/12)) | G14: =(C14-D14-F14)*Inputs!$B$32 | H14: =C14-D14-F14-G14 | I14: =N13 | J14: =I14*Inputs!$B$33 | K14: =(I14-J14)*Inputs!$C$7/12 | L14: =IF(MAX(Inputs!$D$7-(A14-1),0)<=0,0,(I14-J14)*((Inputs!$C$7/12)/(1-(1+Inputs!$C$7/12)^(-MAX(Inputs!$D$7-(A14-1),0)))-Inputs!$C$7/12)) | M14: =(I14-J14-L14)*Inputs!$B$32 | N14: =I14-J14-L14-M14 | O14: =T13 | P14: =O14*Inputs!$B$33 | Q14: =(O14-P14)*Inputs!$C$8/12 | R14: =IF(MAX(Inputs!$D$8-(A14-1),0)<=0,0,(O14-P14)*((Inputs!$C$8/12)/(1-(1+Inputs!$C$8/12)^(-MAX(Inputs!$D$8-(A14-1),0)))-Inputs!$C$8/12)) | S14: =(O14-P14-R14)*Inputs!$B$32 | T14: =O14-P14-R14-S14 | U14: =Z13 | V14: =U14*Inputs!$B$33 | W14: =(U14-V14)*Inputs!$C$9/12 | X14: =IF(MAX(Inputs!$D$9-(A14-1),0)<=0,0,(U14-V14)*((Inputs!$C$9/12)/(1-(1+Inputs!$C$9/12)^(-MAX(Inputs!$D$9-(A14-1),0)))-Inputs!$C$9/12)) | Y14: =(U14-V14-X14)*Inputs!$B$32 | Z14: =U14-V14-X14-Y14 | AA14: =AF13 | AB14: =AA14*Inputs!$B$33 | AC14: =(AA14-AB14)*Inputs!$C$10/12 | AD14: =IF(MAX(Inputs!$D$10-(A14-1),0)<=0,0,(AA14-AB14)*((Inputs!$C$10/12)/(1-(1+Inputs!$C$10/12)^(-MAX(Inputs!$D$10-(A14-1),0)))-Inputs!$C$10/12)) | AE14: =(AA14-AB14-AD14)*Inputs!$B$32 | AF14: =AA14-AB14-AD14-AE14 | AG14: =AL13 | AH14: =AG14*Inputs!$B$33 | AI14: =(AG14-AH14)*Inputs!$C$11/12 | AJ14: =IF(MAX(Inputs!$D$11-(A14-1),0)<=0,0,(AG14-AH14)*((Inputs!$C$11/12)/(1-(1+Inputs!$C$11/12)^(-MAX(Inputs!$D$11-(A14-1),0)))-Inputs!$C$11/12)) | AK14: =(AG14-AH14-AJ14)*Inputs!$B$32 | AL14: =AG14-AH14-AJ14-AK14 | AM14: =AR13 | AN14: =AM14*Inputs!$B$33 | AO14: =(AM14-AN14)*Inputs!$C$12/12 | AP14: =IF(MAX(Inputs!$D$12-(A14-1),0)<=0,0,(AM14-AN14)*((Inputs!$C$12/12)/(1-(1+Inputs!$C$12/12)^(-MAX(Inputs!$D$12-(A14-1),0)))-Inputs!$C$12/12)) | AQ14: =(AM14-AN14-AP14)*Inputs!$B$32 | AR14: =AM14-AN14-AP14-AQ14 | AS14: =AX13 | AT14: =AS14*Inputs!$B$33 | AU14: =(AS14-AT14)*Inputs!$C$13/12 | AV14: =IF(MAX(Inputs!$D$13-(A14-1),0)<=0,0,(AS14-AT14)*((Inputs!$C$13/12)/(1-(1+Inputs!$C$13/12)^(-MAX(Inputs!$D$13-(A14-1),0)))-Inputs!$C$13/12)) | AW14: =(AS14-AT14-AV14)*Inputs!$B$32 | AX14: =AS14-AT14-AV14-AW14 | AY14: =BD13 | AZ14: =AY14*Inputs!$B$33 | BA14: =(AY14-AZ14)*Inputs!$C$14/12 | BB14: =IF(MAX(Inputs!$D$14-(A14-1),0)<=0,0,(AY14-AZ14)*((Inputs!$C$14/12)/(1-(1+Inputs!$C$14/12)^(-MAX(Inputs!$D$14-(A14-1),0)))-Inputs!$C$14/12)) | BC14: =(AY14-AZ14-BB14)*Inputs!$B$32 | BD14: =AY14-AZ14-BB14-BC14 | BE14: =BJ13 | BF14: =BE14*Inputs!$B$33 | BG14: =(BE14-BF14)*Inputs!$C$15/12 | BH14: =IF(MAX(Inputs!$D$15-(A14-1),0)<=0,0,(BE14-BF14)*((Inputs!$C$15/12)/(1-(1+Inputs!$C$15/12)^(-MAX(Inputs!$D$15-(A14-1),0)))-Inputs!$C$15/12)) | BI14: =(BE14-BF14-BH14)*Inputs!$B$32 | BJ14: =BE14-BF14-BH14-BI14 | BK14: =C14+I14+O14+U14+AA14+AG14+AM14+AS14+AY14+BE14 | BL14: =D14+J14+P14+V14+AB14+AH14+AN14+AT14+AZ14+BF14 | BM14: =E14+K14+Q14+W14+AC14+AI14+AO14+AU14+BA14+BG14 | BN14: =F14+L14+R14+X14+AD14+AJ14+AP14+AV14+BB14+BH14 | BO14: =G14+M14+S14+Y14+AE14+AK14+AQ14+AW14+BC14+BI14 | BP14: =H14+N14+T14+Z14+AF14+AL14+AR14+AX14+BD14+BJ14 | BQ14: =IF(A14-Inputs!$B$30>=1,INDEX($BL$5:$BL$101,A14-Inputs!$B$30+1)*(1-Inputs!$B$29),0) | BR14: =BR13+BL14 | BS14: =BS13+BQ14 | BT14: =BR14*Inputs!$B$29 | BU14: =BR14*(1-Inputs!$B$29)-BS14 | BV14: =BP14+BU14 | BW14: =BM14+BN14+BO14+BQ14 | BX14: =BK14-BL14-BN14-BO14-BP14
A15: 10 | B15: =Inputs!$B$36+(Inputs!$B$37-Inputs!$B$36)*(1-EXP(-A15/Inputs!$B$38))+Inputs!$B$31/10000 | C15: =H14 | D15: =C15*Inputs!$B$33 | E15: =(C15-D15)*Inputs!$C$6/12 | F15: =IF(MAX(Inputs!$D$6-(A15-1),0)<=0,0,(C15-D15)*((Inputs!$C$6/12)/(1-(1+Inputs!$C$6/12)^(-MAX(Inputs!$D$6-(A15-1),0)))-Inputs!$C$6/12)) | G15: =(C15-D15-F15)*Inputs!$B$32 | H15: =C15-D15-F15-G15 | I15: =N14 | J15: =I15*Inputs!$B$33 | K15: =(I15-J15)*Inputs!$C$7/12 | L15: =IF(MAX(Inputs!$D$7-(A15-1),0)<=0,0,(I15-J15)*((Inputs!$C$7/12)/(1-(1+Inputs!$C$7/12)^(-MAX(Inputs!$D$7-(A15-1),0)))-Inputs!$C$7/12)) | M15: =(I15-J15-L15)*Inputs!$B$32 | N15: =I15-J15-L15-M15 | O15: =T14 | P15: =O15*Inputs!$B$33 | Q15: =(O15-P15)*Inputs!$C$8/12 | R15: =IF(MAX(Inputs!$D$8-(A15-1),0)<=0,0,(O15-P15)*((Inputs!$C$8/12)/(1-(1+Inputs!$C$8/12)^(-MAX(Inputs!$D$8-(A15-1),0)))-Inputs!$C$8/12)) | S15: =(O15-P15-R15)*Inputs!$B$32 | T15: =O15-P15-R15-S15 | U15: =Z14 | V15: =U15*Inputs!$B$33 | W15: =(U15-V15)*Inputs!$C$9/12 | X15: =IF(MAX(Inputs!$D$9-(A15-1),0)<=0,0,(U15-V15)*((Inputs!$C$9/12)/(1-(1+Inputs!$C$9/12)^(-MAX(Inputs!$D$9-(A15-1),0)))-Inputs!$C$9/12)) | Y15: =(U15-V15-X15)*Inputs!$B$32 | Z15: =U15-V15-X15-Y15 | AA15: =AF14 | AB15: =AA15*Inputs!$B$33 | AC15: =(AA15-AB15)*Inputs!$C$10/12 | AD15: =IF(MAX(Inputs!$D$10-(A15-1),0)<=0,0,(AA15-AB15)*((Inputs!$C$10/12)/(1-(1+Inputs!$C$10/12)^(-MAX(Inputs!$D$10-(A15-1),0)))-Inputs!$C$10/12)) | AE15: =(AA15-AB15-AD15)*Inputs!$B$32 | AF15: =AA15-AB15-AD15-AE15 | AG15: =AL14 | AH15: =AG15*Inputs!$B$33 | AI15: =(AG15-AH15)*Inputs!$C$11/12 | AJ15: =IF(MAX(Inputs!$D$11-(A15-1),0)<=0,0,(AG15-AH15)*((Inputs!$C$11/12)/(1-(1+Inputs!$C$11/12)^(-MAX(Inputs!$D$11-(A15-1),0)))-Inputs!$C$11/12)) | AK15: =(AG15-AH15-AJ15)*Inputs!$B$32 | AL15: =AG15-AH15-AJ15-AK15 | AM15: =AR14 | AN15: =AM15*Inputs!$B$33 | AO15: =(AM15-AN15)*Inputs!$C$12/12 | AP15: =IF(MAX(Inputs!$D$12-(A15-1),0)<=0,0,(AM15-AN15)*((Inputs!$C$12/12)/(1-(1+Inputs!$C$12/12)^(-MAX(Inputs!$D$12-(A15-1),0)))-Inputs!$C$12/12)) | AQ15: =(AM15-AN15-AP15)*Inputs!$B$32 | AR15: =AM15-AN15-AP15-AQ15 | AS15: =AX14 | AT15: =AS15*Inputs!$B$33 | AU15: =(AS15-AT15)*Inputs!$C$13/12 | AV15: =IF(MAX(Inputs!$D$13-(A15-1),0)<=0,0,(AS15-AT15)*((Inputs!$C$13/12)/(1-(1+Inputs!$C$13/12)^(-MAX(Inputs!$D$13-(A15-1),0)))-Inputs!$C$13/12)) | AW15: =(AS15-AT15-AV15)*Inputs!$B$32 | AX15: =AS15-AT15-AV15-AW15 | AY15: =BD14 | AZ15: =AY15*Inputs!$B$33 | BA15: =(AY15-AZ15)*Inputs!$C$14/12 | BB15: =IF(MAX(Inputs!$D$14-(A15-1),0)<=0,0,(AY15-AZ15)*((Inputs!$C$14/12)/(1-(1+Inputs!$C$14/12)^(-MAX(Inputs!$D$14-(A15-1),0)))-Inputs!$C$14/12)) | BC15: =(AY15-AZ15-BB15)*Inputs!$B$32 | BD15: =AY15-AZ15-BB15-BC15 | BE15: =BJ14 | BF15: =BE15*Inputs!$B$33 | BG15: =(BE15-BF15)*Inputs!$C$15/12 | BH15: =IF(MAX(Inputs!$D$15-(A15-1),0)<=0,0,(BE15-BF15)*((Inputs!$C$15/12)/(1-(1+Inputs!$C$15/12)^(-MAX(Inputs!$D$15-(A15-1),0)))-Inputs!$C$15/12)) | BI15: =(BE15-BF15-BH15)*Inputs!$B$32 | BJ15: =BE15-BF15-BH15-BI15 | BK15: =C15+I15+O15+U15+AA15+AG15+AM15+AS15+AY15+BE15 | BL15: =D15+J15+P15+V15+AB15+AH15+AN15+AT15+AZ15+BF15 | BM15: =E15+K15+Q15+W15+AC15+AI15+AO15+AU15+BA15+BG15 | BN15: =F15+L15+R15+X15+AD15+AJ15+AP15+AV15+BB15+BH15 | BO15: =G15+M15+S15+Y15+AE15+AK15+AQ15+AW15+BC15+BI15 | BP15: =H15+N15+T15+Z15+AF15+AL15+AR15+AX15+BD15+BJ15 | BQ15: =IF(A15-Inputs!$B$30>=1,INDEX($BL$5:$BL$101,A15-Inputs!$B$30+1)*(1-Inputs!$B$29),0) | BR15: =BR14+BL15 | BS15: =BS14+BQ15 | BT15: =BR15*Inputs!$B$29 | BU15: =BR15*(1-Inputs!$B$29)-BS15 | BV15: =BP15+BU15 | BW15: =BM15+BN15+BO15+BQ15 | BX15: =BK15-BL15-BN15-BO15-BP15
A16: 11 | B16: =Inputs!$B$36+(Inputs!$B$37-Inputs!$B$36)*(1-EXP(-A16/Inputs!$B$38))+Inputs!$B$31/10000 | C16: =H15 | D16: =C16*Inputs!$B$33 | E16: =(C16-D16)*Inputs!$C$6/12 | F16: =IF(MAX(Inputs!$D$6-(A16-1),0)<=0,0,(C16-D16)*((Inputs!$C$6/12)/(1-(1+Inputs!$C$6/12)^(-MAX(Inputs!$D$6-(A16-1),0)))-Inputs!$C$6/12)) | G16: =(C16-D16-F16)*Inputs!$B$32 | H16: =C16-D16-F16-G16 | I16: =N15 | J16: =I16*Inputs!$B$33 | K16: =(I16-J16)*Inputs!$C$7/12 | L16: =IF(MAX(Inputs!$D$7-(A16-1),0)<=0,0,(I16-J16)*((Inputs!$C$7/12)/(1-(1+Inputs!$C$7/12)^(-MAX(Inputs!$D$7-(A16-1),0)))-Inputs!$C$7/12)) | M16: =(I16-J16-L16)*Inputs!$B$32 | N16: =I16-J16-L16-M16 | O16: =T15 | P16: =O16*Inputs!$B$33 | Q16: =(O16-P16)*Inputs!$C$8/12 | R16: =IF(MAX(Inputs!$D$8-(A16-1),0)<=0,0,(O16-P16)*((Inputs!$C$8/12)/(1-(1+Inputs!$C$8/12)^(-MAX(Inputs!$D$8-(A16-1),0)))-Inputs!$C$8/12)) | S16: =(O16-P16-R16)*Inputs!$B$32 | T16: =O16-P16-R16-S16 | U16: =Z15 | V16: =U16*Inputs!$B$33 | W16: =(U16-V16)*Inputs!$C$9/12 | X16: =IF(MAX(Inputs!$D$9-(A16-1),0)<=0,0,(U16-V16)*((Inputs!$C$9/12)/(1-(1+Inputs!$C$9/12)^(-MAX(Inputs!$D$9-(A16-1),0)))-Inputs!$C$9/12)) | Y16: =(U16-V16-X16)*Inputs!$B$32 | Z16: =U16-V16-X16-Y16 | AA16: =AF15 | AB16: =AA16*Inputs!$B$33 | AC16: =(AA16-AB16)*Inputs!$C$10/12 | AD16: =IF(MAX(Inputs!$D$10-(A16-1),0)<=0,0,(AA16-AB16)*((Inputs!$C$10/12)/(1-(1+Inputs!$C$10/12)^(-MAX(Inputs!$D$10-(A16-1),0)))-Inputs!$C$10/12)) | AE16: =(AA16-AB16-AD16)*Inputs!$B$32 | AF16: =AA16-AB16-AD16-AE16 | AG16: =AL15 | AH16: =AG16*Inputs!$B$33 | AI16: =(AG16-AH16)*Inputs!$C$11/12 | AJ16: =IF(MAX(Inputs!$D$11-(A16-1),0)<=0,0,(AG16-AH16)*((Inputs!$C$11/12)/(1-(1+Inputs!$C$11/12)^(-MAX(Inputs!$D$11-(A16-1),0)))-Inputs!$C$11/12)) | AK16: =(AG16-AH16-AJ16)*Inputs!$B$32 | AL16: =AG16-AH16-AJ16-AK16 | AM16: =AR15 | AN16: =AM16*Inputs!$B$33 | AO16: =(AM16-AN16)*Inputs!$C$12/12 | AP16: =IF(MAX(Inputs!$D$12-(A16-1),0)<=0,0,(AM16-AN16)*((Inputs!$C$12/12)/(1-(1+Inputs!$C$12/12)^(-MAX(Inputs!$D$12-(A16-1),0)))-Inputs!$C$12/12)) | AQ16: =(AM16-AN16-AP16)*Inputs!$B$32 | AR16: =AM16-AN16-AP16-AQ16 | AS16: =AX15 | AT16: =AS16*Inputs!$B$33 | AU16: =(AS16-AT16)*Inputs!$C$13/12 | AV16: =IF(MAX(Inputs!$D$13-(A16-1),0)<=0,0,(AS16-AT16)*((Inputs!$C$13/12)/(1-(1+Inputs!$C$13/12)^(-MAX(Inputs!$D$13-(A16-1),0)))-Inputs!$C$13/12)) | AW16: =(AS16-AT16-AV16)*Inputs!$B$32 | AX16: =AS16-AT16-AV16-AW16 | AY16: =BD15 | AZ16: =AY16*Inputs!$B$33 | BA16: =(AY16-AZ16)*Inputs!$C$14/12 | BB16: =IF(MAX(Inputs!$D$14-(A16-1),0)<=0,0,(AY16-AZ16)*((Inputs!$C$14/12)/(1-(1+Inputs!$C$14/12)^(-MAX(Inputs!$D$14-(A16-1),0)))-Inputs!$C$14/12)) | BC16: =(AY16-AZ16-BB16)*Inputs!$B$32 | BD16: =AY16-AZ16-BB16-BC16 | BE16: =BJ15 | BF16: =BE16*Inputs!$B$33 | BG16: =(BE16-BF16)*Inputs!$C$15/12 | BH16: =IF(MAX(Inputs!$D$15-(A16-1),0)<=0,0,(BE16-BF16)*((Inputs!$C$15/12)/(1-(1+Inputs!$C$15/12)^(-MAX(Inputs!$D$15-(A16-1),0)))-Inputs!$C$15/12)) | BI16: =(BE16-BF16-BH16)*Inputs!$B$32 | BJ16: =BE16-BF16-BH16-BI16 | BK16: =C16+I16+O16+U16+AA16+AG16+AM16+AS16+AY16+BE16 | BL16: =D16+J16+P16+V16+AB16+AH16+AN16+AT16+AZ16+BF16 | BM16: =E16+K16+Q16+W16+AC16+AI16+AO16+AU16+BA16+BG16 | BN16: =F16+L16+R16+X16+AD16+AJ16+AP16+AV16+BB16+BH16 | BO16: =G16+M16+S16+Y16+AE16+AK16+AQ16+AW16+BC16+BI16 | BP16: =H16+N16+T16+Z16+AF16+AL16+AR16+AX16+BD16+BJ16 | BQ16: =IF(A16-Inputs!$B$30>=1,INDEX($BL$5:$BL$101,A16-Inputs!$B$30+1)*(1-Inputs!$B$29),0) | BR16: =BR15+BL16 | BS16: =BS15+BQ16 | BT16: =BR16*Inputs!$B$29 | BU16: =BR16*(1-Inputs!$B$29)-BS16 | BV16: =BP16+BU16 | BW16: =BM16+BN16+BO16+BQ16 | BX16: =BK16-BL16-BN16-BO16-BP16
A17: 12 | B17: =Inputs!$B$36+(Inputs!$B$37-Inputs!$B$36)*(1-EXP(-A17/Inputs!$B$38))+Inputs!$B$31/10000 | C17: =H16 | D17: =C17*Inputs!$B$33 | E17: =(C17-D17)*Inputs!$C$6/12 | F17: =IF(MAX(Inputs!$D$6-(A17-1),0)<=0,0,(C17-D17)*((Inputs!$C$6/12)/(1-(1+Inputs!$C$6/12)^(-MAX(Inputs!$D$6-(A17-1),0)))-Inputs!$C$6/12)) | G17: =(C17-D17-F17)*Inputs!$B$32 | H17: =C17-D17-F17-G17 | I17: =N16 | J17: =I17*Inputs!$B$33 | K17: =(I17-J17)*Inputs!$C$7/12 | L17: =IF(MAX(Inputs!$D$7-(A17-1),0)<=0,0,(I17-J17)*((Inputs!$C$7/12)/(1-(1+Inputs!$C$7/12)^(-MAX(Inputs!$D$7-(A17-1),0)))-Inputs!$C$7/12)) | M17: =(I17-J17-L17)*Inputs!$B$32 | N17: =I17-J17-L17-M17 | O17: =T16 | P17: =O17*Inputs!$B$33 | Q17: =(O17-P17)*Inputs!$C$8/12 | R17: =IF(MAX(Inputs!$D$8-(A17-1),0)<=0,0,(O17-P17)*((Inputs!$C$8/12)/(1-(1+Inputs!$C$8/12)^(-MAX(Inputs!$D$8-(A17-1),0)))-Inputs!$C$8/12)) | S17: =(O17-P17-R17)*Inputs!$B$32 | T17: =O17-P17-R17-S17 | U17: =Z16 | V17: =U17*Inputs!$B$33 | W17: =(U17-V17)*Inputs!$C$9/12 | X17: =IF(MAX(Inputs!$D$9-(A17-1),0)<=0,0,(U17-V17)*((Inputs!$C$9/12)/(1-(1+Inputs!$C$9/12)^(-MAX(Inputs!$D$9-(A17-1),0)))-Inputs!$C$9/12)) | Y17: =(U17-V17-X17)*Inputs!$B$32 | Z17: =U17-V17-X17-Y17 | AA17: =AF16 | AB17: =AA17*Inputs!$B$33 | AC17: =(AA17-AB17)*Inputs!$C$10/12 | AD17: =IF(MAX(Inputs!$D$10-(A17-1),0)<=0,0,(AA17-AB17)*((Inputs!$C$10/12)/(1-(1+Inputs!$C$10/12)^(-MAX(Inputs!$D$10-(A17-1),0)))-Inputs!$C$10/12)) | AE17: =(AA17-AB17-AD17)*Inputs!$B$32 | AF17: =AA17-AB17-AD17-AE17 | AG17: =AL16 | AH17: =AG17*Inputs!$B$33 | AI17: =(AG17-AH17)*Inputs!$C$11/12 | AJ17: =IF(MAX(Inputs!$D$11-(A17-1),0)<=0,0,(AG17-AH17)*((Inputs!$C$11/12)/(1-(1+Inputs!$C$11/12)^(-MAX(Inputs!$D$11-(A17-1),0)))-Inputs!$C$11/12)) | AK17: =(AG17-AH17-AJ17)*Inputs!$B$32 | AL17: =AG17-AH17-AJ17-AK17 | AM17: =AR16 | AN17: =AM17*Inputs!$B$33 | AO17: =(AM17-AN17)*Inputs!$C$12/12 | AP17: =IF(MAX(Inputs!$D$12-(A17-1),0)<=0,0,(AM17-AN17)*((Inputs!$C$12/12)/(1-(1+Inputs!$C$12/12)^(-MAX(Inputs!$D$12-(A17-1),0)))-Inputs!$C$12/12)) | AQ17: =(AM17-AN17-AP17)*Inputs!$B$32 | AR17: =AM17-AN17-AP17-AQ17 | AS17: =AX16 | AT17: =AS17*Inputs!$B$33 | AU17: =(AS17-AT17)*Inputs!$C$13/12 | AV17: =IF(MAX(Inputs!$D$13-(A17-1),0)<=0,0,(AS17-AT17)*((Inputs!$C$13/12)/(1-(1+Inputs!$C$13/12)^(-MAX(Inputs!$D$13-(A17-1),0)))-Inputs!$C$13/12)) | AW17: =(AS17-AT17-AV17)*Inputs!$B$32 | AX17: =AS17-AT17-AV17-AW17 | AY17: =BD16 | AZ17: =AY17*Inputs!$B$33 | BA17: =(AY17-AZ17)*Inputs!$C$14/12 | BB17: =IF(MAX(Inputs!$D$14-(A17-1),0)<=0,0,(AY17-AZ17)*((Inputs!$C$14/12)/(1-(1+Inputs!$C$14/12)^(-MAX(Inputs!$D$14-(A17-1),0)))-Inputs!$C$14/12)) | BC17: =(AY17-AZ17-BB17)*Inputs!$B$32 | BD17: =AY17-AZ17-BB17-BC17 | BE17: =BJ16 | BF17: =BE17*Inputs!$B$33 | BG17: =(BE17-BF17)*Inputs!$C$15/12 | BH17: =IF(MAX(Inputs!$D$15-(A17-1),0)<=0,0,(BE17-BF17)*((Inputs!$C$15/12)/(1-(1+Inputs!$C$15/12)^(-MAX(Inputs!$D$15-(A17-1),0)))-Inputs!$C$15/12)) | BI17: =(BE17-BF17-BH17)*Inputs!$B$32 | BJ17: =BE17-BF17-BH17-BI17 | BK17: =C17+I17+O17+U17+AA17+AG17+AM17+AS17+AY17+BE17 | BL17: =D17+J17+P17+V17+AB17+AH17+AN17+AT17+AZ17+BF17 | BM17: =E17+K17+Q17+W17+AC17+AI17+AO17+AU17+BA17+BG17 | BN17: =F17+L17+R17+X17+AD17+AJ17+AP17+AV17+BB17+BH17 | BO17: =G17+M17+S17+Y17+AE17+AK17+AQ17+AW17+BC17+BI17 | BP17: =H17+N17+T17+Z17+AF17+AL17+AR17+AX17+BD17+BJ17 | BQ17: =IF(A17-Inputs!$B$30>=1,INDEX($BL$5:$BL$101,A17-Inputs!$B$30+1)*(1-Inputs!$B$29),0) | BR17: =BR16+BL17 | BS17: =BS16+BQ17 | BT17: =BR17*Inputs!$B$29 | BU17: =BR17*(1-Inputs!$B$29)-BS17 | BV17: =BP17+BU17 | BW17: =BM17+BN17+BO17+BQ17 | BX17: =BK17-BL17-BN17-BO17-BP17
... A101: 96 | B101: =Inputs!$B$36+(Inputs!$B$37-Inputs!$B$36)*(1-EXP(-A101/Inputs!$B$38))+Inputs!$B$31/10000 | C101: =H100 | D101: =C101*Inputs!$B$33 | E101: =(C101-D101)*Inputs!$C$6/12 | F101: =IF(MAX(Inputs!$D$6-(A101-1),0)<=0,0,(C101-D101)*((Inputs!$C$6/12)/(1-(1+Inputs!$C$6/12)^(-MAX(Inputs!$D$6-(A101-1),0)))-Inputs!$C$6/12)) | G101: =(C101-D101-F101)*Inputs!$B$32 | H101: =C101-D101-F101-G101 | I101: =N100 | J101: =I101*Inputs!$B$33 | K101: =(I101-J101)*Inputs!$C$7/12 | L101: =IF(MAX(Inputs!$D$7-(A101-1),0)<=0,0,(I101-J101)*((Inputs!$C$7/12)/(1-(1+Inputs!$C$7/12)^(-MAX(Inputs!$D$7-(A101-1),0)))-Inputs!$C$7/12)) | M101: =(I101-J101-L101)*Inputs!$B$32 | N101: =I101-J101-L101-M101 | O101: =T100 | P101: =O101*Inputs!$B$33 | Q101: =(O101-P101)*Inputs!$C$8/12 | R101: =IF(MAX(Inputs!$D$8-(A101-1),0)<=0,0,(O101-P101)*((Inputs!$C$8/12)/(1-(1+Inputs!$C$8/12)^(-MAX(Inputs!$D$8-(A101-1),0)))-Inputs!$C$8/12)) | S101: =(O101-P101-R101)*Inputs!$B$32 | T101: =O101-P101-R101-S101 | U101: =Z100 | V101: =U101*Inputs!$B$33 | W101: =(U101-V101)*Inputs!$C$9/12 | X101: =IF(MAX(Inputs!$D$9-(A101-1),0)<=0,0,(U101-V101)*((Inputs!$C$9/12)/(1-(1+Inputs!$C$9/12)^(-MAX(Inputs!$D$9-(A101-1),0)))-Inputs!$C$9/12)) | Y101: =(U101-V101-X101)*Inputs!$B$32 | Z101: =U101-V101-X101-Y101 | AA101: =AF100 | AB101: =AA101*Inputs!$B$33 | AC101: =(AA101-AB101)*Inputs!$C$10/12 | AD101: =IF(MAX(Inputs!$D$10-(A101-1),0)<=0,0,(AA101-AB101)*((Inputs!$C$10/12)/(1-(1+Inputs!$C$10/12)^(-MAX(Inputs!$D$10-(A101-1),0)))-Inputs!$C$10/12)) | AE101: =(AA101-AB101-AD101)*Inputs!$B$32 | AF101: =AA101-AB101-AD101-AE101 | AG101: =AL100 | AH101: =AG101*Inputs!$B$33 | AI101: =(AG101-AH101)*Inputs!$C$11/12 | AJ101: =IF(MAX(Inputs!$D$11-(A101-1),0)<=0,0,(AG101-AH101)*((Inputs!$C$11/12)/(1-(1+Inputs!$C$11/12)^(-MAX(Inputs!$D$11-(A101-1),0)))-Inputs!$C$11/12)) | AK101: =(AG101-AH101-AJ101)*Inputs!$B$32 | AL101: =AG101-AH101-AJ101-AK101 | AM101: =AR100 | AN101: =AM101*Inputs!$B$33 | AO101: =(AM101-AN101)*Inputs!$C$12/12 | AP101: =IF(MAX(Inputs!$D$12-(A101-1),0)<=0,0,(AM101-AN101)*((Inputs!$C$12/12)/(1-(1+Inputs!$C$12/12)^(-MAX(Inputs!$D$12-(A101-1),0)))-Inputs!$C$12/12)) | AQ101: =(AM101-AN101-AP101)*Inputs!$B$32 | AR101: =AM101-AN101-AP101-AQ101 | AS101: =AX100 | AT101: =AS101*Inputs!$B$33 | AU101: =(AS101-AT101)*Inputs!$C$13/12 | AV101: =IF(MAX(Inputs!$D$13-(A101-1),0)<=0,0,(AS101-AT101)*((Inputs!$C$13/12)/(1-(1+Inputs!$C$13/12)^(-MAX(Inputs!$D$13-(A101-1),0)))-Inputs!$C$13/12)) | AW101: =(AS101-AT101-AV101)*Inputs!$B$32 | AX101: =AS101-AT101-AV101-AW101 | AY101: =BD100 | AZ101: =AY101*Inputs!$B$33 | BA101: =(AY101-AZ101)*Inputs!$C$14/12 | BB101: =IF(MAX(Inputs!$D$14-(A101-1),0)<=0,0,(AY101-AZ101)*((Inputs!$C$14/12)/(1-(1+Inputs!$C$14/12)^(-MAX(Inputs!$D$14-(A101-1),0)))-Inputs!$C$14/12)) | BC101: =(AY101-AZ101-BB101)*Inputs!$B$32 | BD101: =AY101-AZ101-BB101-BC101 | BE101: =BJ100 | BF101: =BE101*Inputs!$B$33 | BG101: =(BE101-BF101)*Inputs!$C$15/12 | BH101: =IF(MAX(Inputs!$D$15-(A101-1),0)<=0,0,(BE101-BF101)*((Inputs!$C$15/12)/(1-(1+Inputs!$C$15/12)^(-MAX(Inputs!$D$15-(A101-1),0)))-Inputs!$C$15/12)) | BI101: =(BE101-BF101-BH101)*Inputs!$B$32 | BJ101: =BE101-BF101-BH101-BI101 | BK101: =C101+I101+O101+U101+AA101+AG101+AM101+AS101+AY101+BE101 | BL101: =D101+J101+P101+V101+AB101+AH101+AN101+AT101+AZ101+BF101 | BM101: =E101+K101+Q101+W101+AC101+AI101+AO101+AU101+BA101+BG101 | BN101: =F101+L101+R101+X101+AD101+AJ101+AP101+AV101+BB101+BH101 | BO101: =G101+M101+S101+Y101+AE101+AK101+AQ101+AW101+BC101+BI101 | BP101: =H101+N101+T101+Z101+AF101+AL101+AR101+AX101+BD101+BJ101 | BQ101: =IF(A101-Inputs!$B$30>=1,INDEX($BL$5:$BL$101,A101-Inputs!$B$30+1)*(1-Inputs!$B$29),0) | BR101: =BR100+BL101 | BS101: =BS100+BQ101 | BT101: =BR101*Inputs!$B$29 | BU101: =BR101*(1-Inputs!$B$29)-BS101 | BV101: =BP101+BU101 | BW101: =BM101+BN101+BO101+BQ101 | BX101: =BK101-BL101-BN101-BO101-BP101

Sheet Waterfall
A1: Waterfall
A2: Interest and principal priority of payments, turbo, reserve, write-downs.
A4: Period | B4: Senior fees accrued | C4: Senior fees due | D4: A beg balance | E4: B beg balance | F4: C beg balance | G4: A coupon | H4: B coupon | I4: C coupon | J4: A interest accrued | K4: A interest due (incl carry) | L4: B interest accrued | M4: B interest due (incl carry) | N4: C interest accrued | O4: C interest due (incl carry) | P4: Interest collections | Q4: Reserve beg | R4: Reserve draw | S4: Available interest funds | T4: Available principal funds | U4: Sequential flag | V4: Sum A+B+C beg | W4: A regular principal | X4: B regular principal | Y4: C regular principal | Z4: Principal to residual | AA4: A pro forma balance | AB4: B pro forma balance | AC4: C pro forma balance | AD4: Pro forma A+B+C | AE4: 1 Senior fees paid | AF4: Remaining after fees | AG4: 2 A interest paid | AH4: Remaining after A int | AI4: 3 Turbo (A test breach) | AJ4: Remaining after turbo 1 | AK4: 4 B interest paid | AL4: Remaining after B int | AM4: 5 Turbo (B test breach) | AN4: Remaining after turbo 2 | AO4: 6 C interest paid | AP4: Remaining after C int | AQ4: 7 Turbo (C test breach) | AR4: Remaining after turbo 3 | AS4: Deficiency before turbo 4 | AT4: 8 Turbo (cure deficiency) | AU4: Remaining after turbo 4 | AV4: Turbo total | AW4: Turbo to A | AX4: Turbo to B | AY4: Turbo to C | AZ4: A after turbo | BA4: B after turbo | BB4: C after turbo | BC4: A+B+C after turbo | BD4: Principal deficiency | BE4: C write-down | BF4: B write-down | BG4: A write-down | BH4: A end balance | BI4: B end balance | BJ4: C end balance | BK4: Notes retired flag | BL4: Reserve after draw | BM4: 9 Reserve top-up | BN4: Reserve release | BO4: Reserve end | BP4: 10 Residual interest distribution | BQ4: Residual cash (int + prin + release) | BR4: A principal paid | BS4: B principal paid | BT4: C principal paid | BU4: Notes P+I paid | BV4: A interest shortfall carried | BW4: B interest shortfall carried | BX4: C interest shortfall carried | BY4: Fee shortfall carried | BZ4: Cash conservation check
A5: 0 | BH5: =Inputs!$B$39 | BI5: =Inputs!$B$40 | BJ5: =Inputs!$B$41 | BO5: =Inputs!$B$47 | BV5: 0 | BW5: 0 | BX5: 0 | BY5: 0
A6: 1 | B6: =Inputs!$B$51/12*Pool!BK6 | C6: =B6+BY5 | D6: =BH5 | E6: =BI5 | F6: =BJ5 | G6: =MAX(0,Pool!B6+Inputs!$B$42) | H6: =MAX(0,Pool!B6+Inputs!$B$43) | I6: =Inputs!$B$44 | J6: =D6*G6/12 | K6: =J6+BV5 | L6: =E6*H6/12 | M6: =L6+BW5 | N6: =F6*I6/12 | O6: =N6+BX5 | P6: =Pool!BM6 | Q6: =BO5 | R6: =MIN(Q6,MAX(0,C6+K6+M6-P6)) | S6: =P6+R6 | T6: =Pool!BN6+Pool!BO6+Pool!BQ6 | U6: =IF(OR(Inputs!$B$53=1,Tests!M5=1),1,0) | V6: =D6+E6+F6 | W6: =IF(U6=1,MIN(D6,T6),IF(V6<=0,0,MIN(T6,V6)*D6/V6)) | X6: =IF(U6=1,MIN(E6,T6-W6),IF(V6<=0,0,MIN(T6,V6)*E6/V6)) | Y6: =IF(U6=1,MIN(F6,T6-W6-X6),IF(V6<=0,0,MIN(T6,V6)*F6/V6)) | Z6: =T6-W6-X6-Y6 | AA6: =D6-W6 | AB6: =E6-X6 | AC6: =F6-Y6 | AD6: =AA6+AB6+AC6 | AE6: =MIN(C6,S6) | AF6: =S6-AE6 | AG6: =MIN(K6,AF6) | AH6: =AF6-AG6 | AI6: =IF(Tests!F6=1,MIN(AH6,AD6),0) | AJ6: =AH6-AI6 | AK6: =MIN(M6,AJ6) | AL6: =AJ6-AK6 | AM6: =IF(Tests!I6=1,MIN(AL6,AD6-AI6),0) | AN6: =AL6-AM6 | AO6: =MIN(O6,AN6) | AP6: =AN6-AO6 | AQ6: =IF(Tests!L6=1,MIN(AP6,AD6-AI6-AM6),0) | AR6: =AP6-AQ6 | AS6: =MAX(0,AD6-AI6-AM6-AQ6-Pool!BV6) | AT6: =MIN(AR6,AS6) | AU6: =AR6-AT6 | AV6: =AI6+AM6+AQ6+AT6 | AW6: =MIN(AA6,AV6) | AX6: =MIN(AB6,AV6-AW6) | AY6: =MIN(AC6,AV6-AW6-AX6) | AZ6: =AA6-AW6 | BA6: =AB6-AX6 | BB6: =AC6-AY6 | BC6: =AZ6+BA6+BB6 | BD6: =MAX(0,BC6-Pool!BV6) | BE6: =MIN(BB6,BD6) | BF6: =MIN(BA6,BD6-BE6) | BG6: =MIN(AZ6,BD6-BE6-BF6) | BH6: =AZ6-BG6 | BI6: =BA6-BF6 | BJ6: =BB6-BE6 | BK6: =IF(BH6+BI6+BJ6<0.005,1,0) | BL6: =Q6-R6 | BM6: =IF(BK6=1,0,MIN(AU6,MAX(0,Inputs!$B$48-BL6))) | BN6: =IF(BK6=1,BL6,0) | BO6: =BL6+BM6-BN6 | BP6: =AU6-BM6 | BQ6: =BP6+Z6+BN6 | BR6: =W6+AW6 | BS6: =X6+AX6 | BT6: =Y6+AY6 | BU6: =AG6+AK6+AO6+BR6+BS6+BT6 | BV6: =K6-AG6 | BW6: =M6-AK6 | BX6: =O6-AO6 | BY6: =C6-AE6 | BZ6: =AE6+BU6+BQ6+(BO6-Q6)-Pool!BW6
A7: 2 | B7: =Inputs!$B$51/12*Pool!BK7 | C7: =B7+BY6 | D7: =BH6 | E7: =BI6 | F7: =BJ6 | G7: =MAX(0,Pool!B7+Inputs!$B$42) | H7: =MAX(0,Pool!B7+Inputs!$B$43) | I7: =Inputs!$B$44 | J7: =D7*G7/12 | K7: =J7+BV6 | L7: =E7*H7/12 | M7: =L7+BW6 | N7: =F7*I7/12 | O7: =N7+BX6 | P7: =Pool!BM7 | Q7: =BO6 | R7: =MIN(Q7,MAX(0,C7+K7+M7-P7)) | S7: =P7+R7 | T7: =Pool!BN7+Pool!BO7+Pool!BQ7 | U7: =IF(OR(Inputs!$B$53=1,Tests!M6=1),1,0) | V7: =D7+E7+F7 | W7: =IF(U7=1,MIN(D7,T7),IF(V7<=0,0,MIN(T7,V7)*D7/V7)) | X7: =IF(U7=1,MIN(E7,T7-W7),IF(V7<=0,0,MIN(T7,V7)*E7/V7)) | Y7: =IF(U7=1,MIN(F7,T7-W7-X7),IF(V7<=0,0,MIN(T7,V7)*F7/V7)) | Z7: =T7-W7-X7-Y7 | AA7: =D7-W7 | AB7: =E7-X7 | AC7: =F7-Y7 | AD7: =AA7+AB7+AC7 | AE7: =MIN(C7,S7) | AF7: =S7-AE7 | AG7: =MIN(K7,AF7) | AH7: =AF7-AG7 | AI7: =IF(Tests!F7=1,MIN(AH7,AD7),0) | AJ7: =AH7-AI7 | AK7: =MIN(M7,AJ7) | AL7: =AJ7-AK7 | AM7: =IF(Tests!I7=1,MIN(AL7,AD7-AI7),0) | AN7: =AL7-AM7 | AO7: =MIN(O7,AN7) | AP7: =AN7-AO7 | AQ7: =IF(Tests!L7=1,MIN(AP7,AD7-AI7-AM7),0) | AR7: =AP7-AQ7 | AS7: =MAX(0,AD7-AI7-AM7-AQ7-Pool!BV7) | AT7: =MIN(AR7,AS7) | AU7: =AR7-AT7 | AV7: =AI7+AM7+AQ7+AT7 | AW7: =MIN(AA7,AV7) | AX7: =MIN(AB7,AV7-AW7) | AY7: =MIN(AC7,AV7-AW7-AX7) | AZ7: =AA7-AW7 | BA7: =AB7-AX7 | BB7: =AC7-AY7 | BC7: =AZ7+BA7+BB7 | BD7: =MAX(0,BC7-Pool!BV7) | BE7: =MIN(BB7,BD7) | BF7: =MIN(BA7,BD7-BE7) | BG7: =MIN(AZ7,BD7-BE7-BF7) | BH7: =AZ7-BG7 | BI7: =BA7-BF7 | BJ7: =BB7-BE7 | BK7: =IF(BH7+BI7+BJ7<0.005,1,0) | BL7: =Q7-R7 | BM7: =IF(BK7=1,0,MIN(AU7,MAX(0,Inputs!$B$48-BL7))) | BN7: =IF(BK7=1,BL7,0) | BO7: =BL7+BM7-BN7 | BP7: =AU7-BM7 | BQ7: =BP7+Z7+BN7 | BR7: =W7+AW7 | BS7: =X7+AX7 | BT7: =Y7+AY7 | BU7: =AG7+AK7+AO7+BR7+BS7+BT7 | BV7: =K7-AG7 | BW7: =M7-AK7 | BX7: =O7-AO7 | BY7: =C7-AE7 | BZ7: =AE7+BU7+BQ7+(BO7-Q7)-Pool!BW7
A8: 3 | B8: =Inputs!$B$51/12*Pool!BK8 | C8: =B8+BY7 | D8: =BH7 | E8: =BI7 | F8: =BJ7 | G8: =MAX(0,Pool!B8+Inputs!$B$42) | H8: =MAX(0,Pool!B8+Inputs!$B$43) | I8: =Inputs!$B$44 | J8: =D8*G8/12 | K8: =J8+BV7 | L8: =E8*H8/12 | M8: =L8+BW7 | N8: =F8*I8/12 | O8: =N8+BX7 | P8: =Pool!BM8 | Q8: =BO7 | R8: =MIN(Q8,MAX(0,C8+K8+M8-P8)) | S8: =P8+R8 | T8: =Pool!BN8+Pool!BO8+Pool!BQ8 | U8: =IF(OR(Inputs!$B$53=1,Tests!M7=1),1,0) | V8: =D8+E8+F8 | W8: =IF(U8=1,MIN(D8,T8),IF(V8<=0,0,MIN(T8,V8)*D8/V8)) | X8: =IF(U8=1,MIN(E8,T8-W8),IF(V8<=0,0,MIN(T8,V8)*E8/V8)) | Y8: =IF(U8=1,MIN(F8,T8-W8-X8),IF(V8<=0,0,MIN(T8,V8)*F8/V8)) | Z8: =T8-W8-X8-Y8 | AA8: =D8-W8 | AB8: =E8-X8 | AC8: =F8-Y8 | AD8: =AA8+AB8+AC8 | AE8: =MIN(C8,S8) | AF8: =S8-AE8 | AG8: =MIN(K8,AF8) | AH8: =AF8-AG8 | AI8: =IF(Tests!F8=1,MIN(AH8,AD8),0) | AJ8: =AH8-AI8 | AK8: =MIN(M8,AJ8) | AL8: =AJ8-AK8 | AM8: =IF(Tests!I8=1,MIN(AL8,AD8-AI8),0) | AN8: =AL8-AM8 | AO8: =MIN(O8,AN8) | AP8: =AN8-AO8 | AQ8: =IF(Tests!L8=1,MIN(AP8,AD8-AI8-AM8),0) | AR8: =AP8-AQ8 | AS8: =MAX(0,AD8-AI8-AM8-AQ8-Pool!BV8) | AT8: =MIN(AR8,AS8) | AU8: =AR8-AT8 | AV8: =AI8+AM8+AQ8+AT8 | AW8: =MIN(AA8,AV8) | AX8: =MIN(AB8,AV8-AW8) | AY8: =MIN(AC8,AV8-AW8-AX8) | AZ8: =AA8-AW8 | BA8: =AB8-AX8 | BB8: =AC8-AY8 | BC8: =AZ8+BA8+BB8 | BD8: =MAX(0,BC8-Pool!BV8) | BE8: =MIN(BB8,BD8) | BF8: =MIN(BA8,BD8-BE8) | BG8: =MIN(AZ8,BD8-BE8-BF8) | BH8: =AZ8-BG8 | BI8: =BA8-BF8 | BJ8: =BB8-BE8 | BK8: =IF(BH8+BI8+BJ8<0.005,1,0) | BL8: =Q8-R8 | BM8: =IF(BK8=1,0,MIN(AU8,MAX(0,Inputs!$B$48-BL8))) | BN8: =IF(BK8=1,BL8,0) | BO8: =BL8+BM8-BN8 | BP8: =AU8-BM8 | BQ8: =BP8+Z8+BN8 | BR8: =W8+AW8 | BS8: =X8+AX8 | BT8: =Y8+AY8 | BU8: =AG8+AK8+AO8+BR8+BS8+BT8 | BV8: =K8-AG8 | BW8: =M8-AK8 | BX8: =O8-AO8 | BY8: =C8-AE8 | BZ8: =AE8+BU8+BQ8+(BO8-Q8)-Pool!BW8
A9: 4 | B9: =Inputs!$B$51/12*Pool!BK9 | C9: =B9+BY8 | D9: =BH8 | E9: =BI8 | F9: =BJ8 | G9: =MAX(0,Pool!B9+Inputs!$B$42) | H9: =MAX(0,Pool!B9+Inputs!$B$43) | I9: =Inputs!$B$44 | J9: =D9*G9/12 | K9: =J9+BV8 | L9: =E9*H9/12 | M9: =L9+BW8 | N9: =F9*I9/12 | O9: =N9+BX8 | P9: =Pool!BM9 | Q9: =BO8 | R9: =MIN(Q9,MAX(0,C9+K9+M9-P9)) | S9: =P9+R9 | T9: =Pool!BN9+Pool!BO9+Pool!BQ9 | U9: =IF(OR(Inputs!$B$53=1,Tests!M8=1),1,0) | V9: =D9+E9+F9 | W9: =IF(U9=1,MIN(D9,T9),IF(V9<=0,0,MIN(T9,V9)*D9/V9)) | X9: =IF(U9=1,MIN(E9,T9-W9),IF(V9<=0,0,MIN(T9,V9)*E9/V9)) | Y9: =IF(U9=1,MIN(F9,T9-W9-X9),IF(V9<=0,0,MIN(T9,V9)*F9/V9)) | Z9: =T9-W9-X9-Y9 | AA9: =D9-W9 | AB9: =E9-X9 | AC9: =F9-Y9 | AD9: =AA9+AB9+AC9 | AE9: =MIN(C9,S9) | AF9: =S9-AE9 | AG9: =MIN(K9,AF9) | AH9: =AF9-AG9 | AI9: =IF(Tests!F9=1,MIN(AH9,AD9),0) | AJ9: =AH9-AI9 | AK9: =MIN(M9,AJ9) | AL9: =AJ9-AK9 | AM9: =IF(Tests!I9=1,MIN(AL9,AD9-AI9),0) | AN9: =AL9-AM9 | AO9: =MIN(O9,AN9) | AP9: =AN9-AO9 | AQ9: =IF(Tests!L9=1,MIN(AP9,AD9-AI9-AM9),0) | AR9: =AP9-AQ9 | AS9: =MAX(0,AD9-AI9-AM9-AQ9-Pool!BV9) | AT9: =MIN(AR9,AS9) | AU9: =AR9-AT9 | AV9: =AI9+AM9+AQ9+AT9 | AW9: =MIN(AA9,AV9) | AX9: =MIN(AB9,AV9-AW9) | AY9: =MIN(AC9,AV9-AW9-AX9) | AZ9: =AA9-AW9 | BA9: =AB9-AX9 | BB9: =AC9-AY9 | BC9: =AZ9+BA9+BB9 | BD9: =MAX(0,BC9-Pool!BV9) | BE9: =MIN(BB9,BD9) | BF9: =MIN(BA9,BD9-BE9) | BG9: =MIN(AZ9,BD9-BE9-BF9) | BH9: =AZ9-BG9 | BI9: =BA9-BF9 | BJ9: =BB9-BE9 | BK9: =IF(BH9+BI9+BJ9<0.005,1,0) | BL9: =Q9-R9 | BM9: =IF(BK9=1,0,MIN(AU9,MAX(0,Inputs!$B$48-BL9))) | BN9: =IF(BK9=1,BL9,0) | BO9: =BL9+BM9-BN9 | BP9: =AU9-BM9 | BQ9: =BP9+Z9+BN9 | BR9: =W9+AW9 | BS9: =X9+AX9 | BT9: =Y9+AY9 | BU9: =AG9+AK9+AO9+BR9+BS9+BT9 | BV9: =K9-AG9 | BW9: =M9-AK9 | BX9: =O9-AO9 | BY9: =C9-AE9 | BZ9: =AE9+BU9+BQ9+(BO9-Q9)-Pool!BW9
A10: 5 | B10: =Inputs!$B$51/12*Pool!BK10 | C10: =B10+BY9 | D10: =BH9 | E10: =BI9 | F10: =BJ9 | G10: =MAX(0,Pool!B10+Inputs!$B$42) | H10: =MAX(0,Pool!B10+Inputs!$B$43) | I10: =Inputs!$B$44 | J10: =D10*G10/12 | K10: =J10+BV9 | L10: =E10*H10/12 | M10: =L10+BW9 | N10: =F10*I10/12 | O10: =N10+BX9 | P10: =Pool!BM10 | Q10: =BO9 | R10: =MIN(Q10,MAX(0,C10+K10+M10-P10)) | S10: =P10+R10 | T10: =Pool!BN10+Pool!BO10+Pool!BQ10 | U10: =IF(OR(Inputs!$B$53=1,Tests!M9=1),1,0) | V10: =D10+E10+F10 | W10: =IF(U10=1,MIN(D10,T10),IF(V10<=0,0,MIN(T10,V10)*D10/V10)) | X10: =IF(U10=1,MIN(E10,T10-W10),IF(V10<=0,0,MIN(T10,V10)*E10/V10)) | Y10: =IF(U10=1,MIN(F10,T10-W10-X10),IF(V10<=0,0,MIN(T10,V10)*F10/V10)) | Z10: =T10-W10-X10-Y10 | AA10: =D10-W10 | AB10: =E10-X10 | AC10: =F10-Y10 | AD10: =AA10+AB10+AC10 | AE10: =MIN(C10,S10) | AF10: =S10-AE10 | AG10: =MIN(K10,AF10) | AH10: =AF10-AG10 | AI10: =IF(Tests!F10=1,MIN(AH10,AD10),0) | AJ10: =AH10-AI10 | AK10: =MIN(M10,AJ10) | AL10: =AJ10-AK10 | AM10: =IF(Tests!I10=1,MIN(AL10,AD10-AI10),0) | AN10: =AL10-AM10 | AO10: =MIN(O10,AN10) | AP10: =AN10-AO10 | AQ10: =IF(Tests!L10=1,MIN(AP10,AD10-AI10-AM10),0) | AR10: =AP10-AQ10 | AS10: =MAX(0,AD10-AI10-AM10-AQ10-Pool!BV10) | AT10: =MIN(AR10,AS10) | AU10: =AR10-AT10 | AV10: =AI10+AM10+AQ10+AT10 | AW10: =MIN(AA10,AV10) | AX10: =MIN(AB10,AV10-AW10) | AY10: =MIN(AC10,AV10-AW10-AX10) | AZ10: =AA10-AW10 | BA10: =AB10-AX10 | BB10: =AC10-AY10 | BC10: =AZ10+BA10+BB10 | BD10: =MAX(0,BC10-Pool!BV10) | BE10: =MIN(BB10,BD10) | BF10: =MIN(BA10,BD10-BE10) | BG10: =MIN(AZ10,BD10-BE10-BF10) | BH10: =AZ10-BG10 | BI10: =BA10-BF10 | BJ10: =BB10-BE10 | BK10: =IF(BH10+BI10+BJ10<0.005,1,0) | BL10: =Q10-R10 | BM10: =IF(BK10=1,0,MIN(AU10,MAX(0,Inputs!$B$48-BL10))) | BN10: =IF(BK10=1,BL10,0) | BO10: =BL10+BM10-BN10 | BP10: =AU10-BM10 | BQ10: =BP10+Z10+BN10 | BR10: =W10+AW10 | BS10: =X10+AX10 | BT10: =Y10+AY10 | BU10: =AG10+AK10+AO10+BR10+BS10+BT10 | BV10: =K10-AG10 | BW10: =M10-AK10 | BX10: =O10-AO10 | BY10: =C10-AE10 | BZ10: =AE10+BU10+BQ10+(BO10-Q10)-Pool!BW10
A11: 6 | B11: =Inputs!$B$51/12*Pool!BK11 | C11: =B11+BY10 | D11: =BH10 | E11: =BI10 | F11: =BJ10 | G11: =MAX(0,Pool!B11+Inputs!$B$42) | H11: =MAX(0,Pool!B11+Inputs!$B$43) | I11: =Inputs!$B$44 | J11: =D11*G11/12 | K11: =J11+BV10 | L11: =E11*H11/12 | M11: =L11+BW10 | N11: =F11*I11/12 | O11: =N11+BX10 | P11: =Pool!BM11 | Q11: =BO10 | R11: =MIN(Q11,MAX(0,C11+K11+M11-P11)) | S11: =P11+R11 | T11: =Pool!BN11+Pool!BO11+Pool!BQ11 | U11: =IF(OR(Inputs!$B$53=1,Tests!M10=1),1,0) | V11: =D11+E11+F11 | W11: =IF(U11=1,MIN(D11,T11),IF(V11<=0,0,MIN(T11,V11)*D11/V11)) | X11: =IF(U11=1,MIN(E11,T11-W11),IF(V11<=0,0,MIN(T11,V11)*E11/V11)) | Y11: =IF(U11=1,MIN(F11,T11-W11-X11),IF(V11<=0,0,MIN(T11,V11)*F11/V11)) | Z11: =T11-W11-X11-Y11 | AA11: =D11-W11 | AB11: =E11-X11 | AC11: =F11-Y11 | AD11: =AA11+AB11+AC11 | AE11: =MIN(C11,S11) | AF11: =S11-AE11 | AG11: =MIN(K11,AF11) | AH11: =AF11-AG11 | AI11: =IF(Tests!F11=1,MIN(AH11,AD11),0) | AJ11: =AH11-AI11 | AK11: =MIN(M11,AJ11) | AL11: =AJ11-AK11 | AM11: =IF(Tests!I11=1,MIN(AL11,AD11-AI11),0) | AN11: =AL11-AM11 | AO11: =MIN(O11,AN11) | AP11: =AN11-AO11 | AQ11: =IF(Tests!L11=1,MIN(AP11,AD11-AI11-AM11),0) | AR11: =AP11-AQ11 | AS11: =MAX(0,AD11-AI11-AM11-AQ11-Pool!BV11) | AT11: =MIN(AR11,AS11) | AU11: =AR11-AT11 | AV11: =AI11+AM11+AQ11+AT11 | AW11: =MIN(AA11,AV11) | AX11: =MIN(AB11,AV11-AW11) | AY11: =MIN(AC11,AV11-AW11-AX11) | AZ11: =AA11-AW11 | BA11: =AB11-AX11 | BB11: =AC11-AY11 | BC11: =AZ11+BA11+BB11 | BD11: =MAX(0,BC11-Pool!BV11) | BE11: =MIN(BB11,BD11) | BF11: =MIN(BA11,BD11-BE11) | BG11: =MIN(AZ11,BD11-BE11-BF11) | BH11: =AZ11-BG11 | BI11: =BA11-BF11 | BJ11: =BB11-BE11 | BK11: =IF(BH11+BI11+BJ11<0.005,1,0) | BL11: =Q11-R11 | BM11: =IF(BK11=1,0,MIN(AU11,MAX(0,Inputs!$B$48-BL11))) | BN11: =IF(BK11=1,BL11,0) | BO11: =BL11+BM11-BN11 | BP11: =AU11-BM11 | BQ11: =BP11+Z11+BN11 | BR11: =W11+AW11 | BS11: =X11+AX11 | BT11: =Y11+AY11 | BU11: =AG11+AK11+AO11+BR11+BS11+BT11 | BV11: =K11-AG11 | BW11: =M11-AK11 | BX11: =O11-AO11 | BY11: =C11-AE11 | BZ11: =AE11+BU11+BQ11+(BO11-Q11)-Pool!BW11
A12: 7 | B12: =Inputs!$B$51/12*Pool!BK12 | C12: =B12+BY11 | D12: =BH11 | E12: =BI11 | F12: =BJ11 | G12: =MAX(0,Pool!B12+Inputs!$B$42) | H12: =MAX(0,Pool!B12+Inputs!$B$43) | I12: =Inputs!$B$44 | J12: =D12*G12/12 | K12: =J12+BV11 | L12: =E12*H12/12 | M12: =L12+BW11 | N12: =F12*I12/12 | O12: =N12+BX11 | P12: =Pool!BM12 | Q12: =BO11 | R12: =MIN(Q12,MAX(0,C12+K12+M12-P12)) | S12: =P12+R12 | T12: =Pool!BN12+Pool!BO12+Pool!BQ12 | U12: =IF(OR(Inputs!$B$53=1,Tests!M11=1),1,0) | V12: =D12+E12+F12 | W12: =IF(U12=1,MIN(D12,T12),IF(V12<=0,0,MIN(T12,V12)*D12/V12)) | X12: =IF(U12=1,MIN(E12,T12-W12),IF(V12<=0,0,MIN(T12,V12)*E12/V12)) | Y12: =IF(U12=1,MIN(F12,T12-W12-X12),IF(V12<=0,0,MIN(T12,V12)*F12/V12)) | Z12: =T12-W12-X12-Y12 | AA12: =D12-W12 | AB12: =E12-X12 | AC12: =F12-Y12 | AD12: =AA12+AB12+AC12 | AE12: =MIN(C12,S12) | AF12: =S12-AE12 | AG12: =MIN(K12,AF12) | AH12: =AF12-AG12 | AI12: =IF(Tests!F12=1,MIN(AH12,AD12),0) | AJ12: =AH12-AI12 | AK12: =MIN(M12,AJ12) | AL12: =AJ12-AK12 | AM12: =IF(Tests!I12=1,MIN(AL12,AD12-AI12),0) | AN12: =AL12-AM12 | AO12: =MIN(O12,AN12) | AP12: =AN12-AO12 | AQ12: =IF(Tests!L12=1,MIN(AP12,AD12-AI12-AM12),0) | AR12: =AP12-AQ12 | AS12: =MAX(0,AD12-AI12-AM12-AQ12-Pool!BV12) | AT12: =MIN(AR12,AS12) | AU12: =AR12-AT12 | AV12: =AI12+AM12+AQ12+AT12 | AW12: =MIN(AA12,AV12) | AX12: =MIN(AB12,AV12-AW12) | AY12: =MIN(AC12,AV12-AW12-AX12) | AZ12: =AA12-AW12 | BA12: =AB12-AX12 | BB12: =AC12-AY12 | BC12: =AZ12+BA12+BB12 | BD12: =MAX(0,BC12-Pool!BV12) | BE12: =MIN(BB12,BD12) | BF12: =MIN(BA12,BD12-BE12) | BG12: =MIN(AZ12,BD12-BE12-BF12) | BH12: =AZ12-BG12 | BI12: =BA12-BF12 | BJ12: =BB12-BE12 | BK12: =IF(BH12+BI12+BJ12<0.005,1,0) | BL12: =Q12-R12 | BM12: =IF(BK12=1,0,MIN(AU12,MAX(0,Inputs!$B$48-BL12))) | BN12: =IF(BK12=1,BL12,0) | BO12: =BL12+BM12-BN12 | BP12: =AU12-BM12 | BQ12: =BP12+Z12+BN12 | BR12: =W12+AW12 | BS12: =X12+AX12 | BT12: =Y12+AY12 | BU12: =AG12+AK12+AO12+BR12+BS12+BT12 | BV12: =K12-AG12 | BW12: =M12-AK12 | BX12: =O12-AO12 | BY12: =C12-AE12 | BZ12: =AE12+BU12+BQ12+(BO12-Q12)-Pool!BW12
A13: 8 | B13: =Inputs!$B$51/12*Pool!BK13 | C13: =B13+BY12 | D13: =BH12 | E13: =BI12 | F13: =BJ12 | G13: =MAX(0,Pool!B13+Inputs!$B$42) | H13: =MAX(0,Pool!B13+Inputs!$B$43) | I13: =Inputs!$B$44 | J13: =D13*G13/12 | K13: =J13+BV12 | L13: =E13*H13/12 | M13: =L13+BW12 | N13: =F13*I13/12 | O13: =N13+BX12 | P13: =Pool!BM13 | Q13: =BO12 | R13: =MIN(Q13,MAX(0,C13+K13+M13-P13)) | S13: =P13+R13 | T13: =Pool!BN13+Pool!BO13+Pool!BQ13 | U13: =IF(OR(Inputs!$B$53=1,Tests!M12=1),1,0) | V13: =D13+E13+F13 | W13: =IF(U13=1,MIN(D13,T13),IF(V13<=0,0,MIN(T13,V13)*D13/V13)) | X13: =IF(U13=1,MIN(E13,T13-W13),IF(V13<=0,0,MIN(T13,V13)*E13/V13)) | Y13: =IF(U13=1,MIN(F13,T13-W13-X13),IF(V13<=0,0,MIN(T13,V13)*F13/V13)) | Z13: =T13-W13-X13-Y13 | AA13: =D13-W13 | AB13: =E13-X13 | AC13: =F13-Y13 | AD13: =AA13+AB13+AC13 | AE13: =MIN(C13,S13) | AF13: =S13-AE13 | AG13: =MIN(K13,AF13) | AH13: =AF13-AG13 | AI13: =IF(Tests!F13=1,MIN(AH13,AD13),0) | AJ13: =AH13-AI13 | AK13: =MIN(M13,AJ13) | AL13: =AJ13-AK13 | AM13: =IF(Tests!I13=1,MIN(AL13,AD13-AI13),0) | AN13: =AL13-AM13 | AO13: =MIN(O13,AN13) | AP13: =AN13-AO13 | AQ13: =IF(Tests!L13=1,MIN(AP13,AD13-AI13-AM13),0) | AR13: =AP13-AQ13 | AS13: =MAX(0,AD13-AI13-AM13-AQ13-Pool!BV13) | AT13: =MIN(AR13,AS13) | AU13: =AR13-AT13 | AV13: =AI13+AM13+AQ13+AT13 | AW13: =MIN(AA13,AV13) | AX13: =MIN(AB13,AV13-AW13) | AY13: =MIN(AC13,AV13-AW13-AX13) | AZ13: =AA13-AW13 | BA13: =AB13-AX13 | BB13: =AC13-AY13 | BC13: =AZ13+BA13+BB13 | BD13: =MAX(0,BC13-Pool!BV13) | BE13: =MIN(BB13,BD13) | BF13: =MIN(BA13,BD13-BE13) | BG13: =MIN(AZ13,BD13-BE13-BF13) | BH13: =AZ13-BG13 | BI13: =BA13-BF13 | BJ13: =BB13-BE13 | BK13: =IF(BH13+BI13+BJ13<0.005,1,0) | BL13: =Q13-R13 | BM13: =IF(BK13=1,0,MIN(AU13,MAX(0,Inputs!$B$48-BL13))) | BN13: =IF(BK13=1,BL13,0) | BO13: =BL13+BM13-BN13 | BP13: =AU13-BM13 | BQ13: =BP13+Z13+BN13 | BR13: =W13+AW13 | BS13: =X13+AX13 | BT13: =Y13+AY13 | BU13: =AG13+AK13+AO13+BR13+BS13+BT13 | BV13: =K13-AG13 | BW13: =M13-AK13 | BX13: =O13-AO13 | BY13: =C13-AE13 | BZ13: =AE13+BU13+BQ13+(BO13-Q13)-Pool!BW13
A14: 9 | B14: =Inputs!$B$51/12*Pool!BK14 | C14: =B14+BY13 | D14: =BH13 | E14: =BI13 | F14: =BJ13 | G14: =MAX(0,Pool!B14+Inputs!$B$42) | H14: =MAX(0,Pool!B14+Inputs!$B$43) | I14: =Inputs!$B$44 | J14: =D14*G14/12 | K14: =J14+BV13 | L14: =E14*H14/12 | M14: =L14+BW13 | N14: =F14*I14/12 | O14: =N14+BX13 | P14: =Pool!BM14 | Q14: =BO13 | R14: =MIN(Q14,MAX(0,C14+K14+M14-P14)) | S14: =P14+R14 | T14: =Pool!BN14+Pool!BO14+Pool!BQ14 | U14: =IF(OR(Inputs!$B$53=1,Tests!M13=1),1,0) | V14: =D14+E14+F14 | W14: =IF(U14=1,MIN(D14,T14),IF(V14<=0,0,MIN(T14,V14)*D14/V14)) | X14: =IF(U14=1,MIN(E14,T14-W14),IF(V14<=0,0,MIN(T14,V14)*E14/V14)) | Y14: =IF(U14=1,MIN(F14,T14-W14-X14),IF(V14<=0,0,MIN(T14,V14)*F14/V14)) | Z14: =T14-W14-X14-Y14 | AA14: =D14-W14 | AB14: =E14-X14 | AC14: =F14-Y14 | AD14: =AA14+AB14+AC14 | AE14: =MIN(C14,S14) | AF14: =S14-AE14 | AG14: =MIN(K14,AF14) | AH14: =AF14-AG14 | AI14: =IF(Tests!F14=1,MIN(AH14,AD14),0) | AJ14: =AH14-AI14 | AK14: =MIN(M14,AJ14) | AL14: =AJ14-AK14 | AM14: =IF(Tests!I14=1,MIN(AL14,AD14-AI14),0) | AN14: =AL14-AM14 | AO14: =MIN(O14,AN14) | AP14: =AN14-AO14 | AQ14: =IF(Tests!L14=1,MIN(AP14,AD14-AI14-AM14),0) | AR14: =AP14-AQ14 | AS14: =MAX(0,AD14-AI14-AM14-AQ14-Pool!BV14) | AT14: =MIN(AR14,AS14) | AU14: =AR14-AT14 | AV14: =AI14+AM14+AQ14+AT14 | AW14: =MIN(AA14,AV14) | AX14: =MIN(AB14,AV14-AW14) | AY14: =MIN(AC14,AV14-AW14-AX14) | AZ14: =AA14-AW14 | BA14: =AB14-AX14 | BB14: =AC14-AY14 | BC14: =AZ14+BA14+BB14 | BD14: =MAX(0,BC14-Pool!BV14) | BE14: =MIN(BB14,BD14) | BF14: =MIN(BA14,BD14-BE14) | BG14: =MIN(AZ14,BD14-BE14-BF14) | BH14: =AZ14-BG14 | BI14: =BA14-BF14 | BJ14: =BB14-BE14 | BK14: =IF(BH14+BI14+BJ14<0.005,1,0) | BL14: =Q14-R14 | BM14: =IF(BK14=1,0,MIN(AU14,MAX(0,Inputs!$B$48-BL14))) | BN14: =IF(BK14=1,BL14,0) | BO14: =BL14+BM14-BN14 | BP14: =AU14-BM14 | BQ14: =BP14+Z14+BN14 | BR14: =W14+AW14 | BS14: =X14+AX14 | BT14: =Y14+AY14 | BU14: =AG14+AK14+AO14+BR14+BS14+BT14 | BV14: =K14-AG14 | BW14: =M14-AK14 | BX14: =O14-AO14 | BY14: =C14-AE14 | BZ14: =AE14+BU14+BQ14+(BO14-Q14)-Pool!BW14
A15: 10 | B15: =Inputs!$B$51/12*Pool!BK15 | C15: =B15+BY14 | D15: =BH14 | E15: =BI14 | F15: =BJ14 | G15: =MAX(0,Pool!B15+Inputs!$B$42) | H15: =MAX(0,Pool!B15+Inputs!$B$43) | I15: =Inputs!$B$44 | J15: =D15*G15/12 | K15: =J15+BV14 | L15: =E15*H15/12 | M15: =L15+BW14 | N15: =F15*I15/12 | O15: =N15+BX14 | P15: =Pool!BM15 | Q15: =BO14 | R15: =MIN(Q15,MAX(0,C15+K15+M15-P15)) | S15: =P15+R15 | T15: =Pool!BN15+Pool!BO15+Pool!BQ15 | U15: =IF(OR(Inputs!$B$53=1,Tests!M14=1),1,0) | V15: =D15+E15+F15 | W15: =IF(U15=1,MIN(D15,T15),IF(V15<=0,0,MIN(T15,V15)*D15/V15)) | X15: =IF(U15=1,MIN(E15,T15-W15),IF(V15<=0,0,MIN(T15,V15)*E15/V15)) | Y15: =IF(U15=1,MIN(F15,T15-W15-X15),IF(V15<=0,0,MIN(T15,V15)*F15/V15)) | Z15: =T15-W15-X15-Y15 | AA15: =D15-W15 | AB15: =E15-X15 | AC15: =F15-Y15 | AD15: =AA15+AB15+AC15 | AE15: =MIN(C15,S15) | AF15: =S15-AE15 | AG15: =MIN(K15,AF15) | AH15: =AF15-AG15 | AI15: =IF(Tests!F15=1,MIN(AH15,AD15),0) | AJ15: =AH15-AI15 | AK15: =MIN(M15,AJ15) | AL15: =AJ15-AK15 | AM15: =IF(Tests!I15=1,MIN(AL15,AD15-AI15),0) | AN15: =AL15-AM15 | AO15: =MIN(O15,AN15) | AP15: =AN15-AO15 | AQ15: =IF(Tests!L15=1,MIN(AP15,AD15-AI15-AM15),0) | AR15: =AP15-AQ15 | AS15: =MAX(0,AD15-AI15-AM15-AQ15-Pool!BV15) | AT15: =MIN(AR15,AS15) | AU15: =AR15-AT15 | AV15: =AI15+AM15+AQ15+AT15 | AW15: =MIN(AA15,AV15) | AX15: =MIN(AB15,AV15-AW15) | AY15: =MIN(AC15,AV15-AW15-AX15) | AZ15: =AA15-AW15 | BA15: =AB15-AX15 | BB15: =AC15-AY15 | BC15: =AZ15+BA15+BB15 | BD15: =MAX(0,BC15-Pool!BV15) | BE15: =MIN(BB15,BD15) | BF15: =MIN(BA15,BD15-BE15) | BG15: =MIN(AZ15,BD15-BE15-BF15) | BH15: =AZ15-BG15 | BI15: =BA15-BF15 | BJ15: =BB15-BE15 | BK15: =IF(BH15+BI15+BJ15<0.005,1,0) | BL15: =Q15-R15 | BM15: =IF(BK15=1,0,MIN(AU15,MAX(0,Inputs!$B$48-BL15))) | BN15: =IF(BK15=1,BL15,0) | BO15: =BL15+BM15-BN15 | BP15: =AU15-BM15 | BQ15: =BP15+Z15+BN15 | BR15: =W15+AW15 | BS15: =X15+AX15 | BT15: =Y15+AY15 | BU15: =AG15+AK15+AO15+BR15+BS15+BT15 | BV15: =K15-AG15 | BW15: =M15-AK15 | BX15: =O15-AO15 | BY15: =C15-AE15 | BZ15: =AE15+BU15+BQ15+(BO15-Q15)-Pool!BW15
A16: 11 | B16: =Inputs!$B$51/12*Pool!BK16 | C16: =B16+BY15 | D16: =BH15 | E16: =BI15 | F16: =BJ15 | G16: =MAX(0,Pool!B16+Inputs!$B$42) | H16: =MAX(0,Pool!B16+Inputs!$B$43) | I16: =Inputs!$B$44 | J16: =D16*G16/12 | K16: =J16+BV15 | L16: =E16*H16/12 | M16: =L16+BW15 | N16: =F16*I16/12 | O16: =N16+BX15 | P16: =Pool!BM16 | Q16: =BO15 | R16: =MIN(Q16,MAX(0,C16+K16+M16-P16)) | S16: =P16+R16 | T16: =Pool!BN16+Pool!BO16+Pool!BQ16 | U16: =IF(OR(Inputs!$B$53=1,Tests!M15=1),1,0) | V16: =D16+E16+F16 | W16: =IF(U16=1,MIN(D16,T16),IF(V16<=0,0,MIN(T16,V16)*D16/V16)) | X16: =IF(U16=1,MIN(E16,T16-W16),IF(V16<=0,0,MIN(T16,V16)*E16/V16)) | Y16: =IF(U16=1,MIN(F16,T16-W16-X16),IF(V16<=0,0,MIN(T16,V16)*F16/V16)) | Z16: =T16-W16-X16-Y16 | AA16: =D16-W16 | AB16: =E16-X16 | AC16: =F16-Y16 | AD16: =AA16+AB16+AC16 | AE16: =MIN(C16,S16) | AF16: =S16-AE16 | AG16: =MIN(K16,AF16) | AH16: =AF16-AG16 | AI16: =IF(Tests!F16=1,MIN(AH16,AD16),0) | AJ16: =AH16-AI16 | AK16: =MIN(M16,AJ16) | AL16: =AJ16-AK16 | AM16: =IF(Tests!I16=1,MIN(AL16,AD16-AI16),0) | AN16: =AL16-AM16 | AO16: =MIN(O16,AN16) | AP16: =AN16-AO16 | AQ16: =IF(Tests!L16=1,MIN(AP16,AD16-AI16-AM16),0) | AR16: =AP16-AQ16 | AS16: =MAX(0,AD16-AI16-AM16-AQ16-Pool!BV16) | AT16: =MIN(AR16,AS16) | AU16: =AR16-AT16 | AV16: =AI16+AM16+AQ16+AT16 | AW16: =MIN(AA16,AV16) | AX16: =MIN(AB16,AV16-AW16) | AY16: =MIN(AC16,AV16-AW16-AX16) | AZ16: =AA16-AW16 | BA16: =AB16-AX16 | BB16: =AC16-AY16 | BC16: =AZ16+BA16+BB16 | BD16: =MAX(0,BC16-Pool!BV16) | BE16: =MIN(BB16,BD16) | BF16: =MIN(BA16,BD16-BE16) | BG16: =MIN(AZ16,BD16-BE16-BF16) | BH16: =AZ16-BG16 | BI16: =BA16-BF16 | BJ16: =BB16-BE16 | BK16: =IF(BH16+BI16+BJ16<0.005,1,0) | BL16: =Q16-R16 | BM16: =IF(BK16=1,0,MIN(AU16,MAX(0,Inputs!$B$48-BL16))) | BN16: =IF(BK16=1,BL16,0) | BO16: =BL16+BM16-BN16 | BP16: =AU16-BM16 | BQ16: =BP16+Z16+BN16 | BR16: =W16+AW16 | BS16: =X16+AX16 | BT16: =Y16+AY16 | BU16: =AG16+AK16+AO16+BR16+BS16+BT16 | BV16: =K16-AG16 | BW16: =M16-AK16 | BX16: =O16-AO16 | BY16: =C16-AE16 | BZ16: =AE16+BU16+BQ16+(BO16-Q16)-Pool!BW16
A17: 12 | B17: =Inputs!$B$51/12*Pool!BK17 | C17: =B17+BY16 | D17: =BH16 | E17: =BI16 | F17: =BJ16 | G17: =MAX(0,Pool!B17+Inputs!$B$42) | H17: =MAX(0,Pool!B17+Inputs!$B$43) | I17: =Inputs!$B$44 | J17: =D17*G17/12 | K17: =J17+BV16 | L17: =E17*H17/12 | M17: =L17+BW16 | N17: =F17*I17/12 | O17: =N17+BX16 | P17: =Pool!BM17 | Q17: =BO16 | R17: =MIN(Q17,MAX(0,C17+K17+M17-P17)) | S17: =P17+R17 | T17: =Pool!BN17+Pool!BO17+Pool!BQ17 | U17: =IF(OR(Inputs!$B$53=1,Tests!M16=1),1,0) | V17: =D17+E17+F17 | W17: =IF(U17=1,MIN(D17,T17),IF(V17<=0,0,MIN(T17,V17)*D17/V17)) | X17: =IF(U17=1,MIN(E17,T17-W17),IF(V17<=0,0,MIN(T17,V17)*E17/V17)) | Y17: =IF(U17=1,MIN(F17,T17-W17-X17),IF(V17<=0,0,MIN(T17,V17)*F17/V17)) | Z17: =T17-W17-X17-Y17 | AA17: =D17-W17 | AB17: =E17-X17 | AC17: =F17-Y17 | AD17: =AA17+AB17+AC17 | AE17: =MIN(C17,S17) | AF17: =S17-AE17 | AG17: =MIN(K17,AF17) | AH17: =AF17-AG17 | AI17: =IF(Tests!F17=1,MIN(AH17,AD17),0) | AJ17: =AH17-AI17 | AK17: =MIN(M17,AJ17) | AL17: =AJ17-AK17 | AM17: =IF(Tests!I17=1,MIN(AL17,AD17-AI17),0) | AN17: =AL17-AM17 | AO17: =MIN(O17,AN17) | AP17: =AN17-AO17 | AQ17: =IF(Tests!L17=1,MIN(AP17,AD17-AI17-AM17),0) | AR17: =AP17-AQ17 | AS17: =MAX(0,AD17-AI17-AM17-AQ17-Pool!BV17) | AT17: =MIN(AR17,AS17) | AU17: =AR17-AT17 | AV17: =AI17+AM17+AQ17+AT17 | AW17: =MIN(AA17,AV17) | AX17: =MIN(AB17,AV17-AW17) | AY17: =MIN(AC17,AV17-AW17-AX17) | AZ17: =AA17-AW17 | BA17: =AB17-AX17 | BB17: =AC17-AY17 | BC17: =AZ17+BA17+BB17 | BD17: =MAX(0,BC17-Pool!BV17) | BE17: =MIN(BB17,BD17) | BF17: =MIN(BA17,BD17-BE17) | BG17: =MIN(AZ17,BD17-BE17-BF17) | BH17: =AZ17-BG17 | BI17: =BA17-BF17 | BJ17: =BB17-BE17 | BK17: =IF(BH17+BI17+BJ17<0.005,1,0) | BL17: =Q17-R17 | BM17: =IF(BK17=1,0,MIN(AU17,MAX(0,Inputs!$B$48-BL17))) | BN17: =IF(BK17=1,BL17,0) | BO17: =BL17+BM17-BN17 | BP17: =AU17-BM17 | BQ17: =BP17+Z17+BN17 | BR17: =W17+AW17 | BS17: =X17+AX17 | BT17: =Y17+AY17 | BU17: =AG17+AK17+AO17+BR17+BS17+BT17 | BV17: =K17-AG17 | BW17: =M17-AK17 | BX17: =O17-AO17 | BY17: =C17-AE17 | BZ17: =AE17+BU17+BQ17+(BO17-Q17)-Pool!BW17
... A101: 96 | B101: =Inputs!$B$51/12*Pool!BK101 | C101: =B101+BY100 | D101: =BH100 | E101: =BI100 | F101: =BJ100 | G101: =MAX(0,Pool!B101+Inputs!$B$42) | H101: =MAX(0,Pool!B101+Inputs!$B$43) | I101: =Inputs!$B$44 | J101: =D101*G101/12 | K101: =J101+BV100 | L101: =E101*H101/12 | M101: =L101+BW100 | N101: =F101*I101/12 | O101: =N101+BX100 | P101: =Pool!BM101 | Q101: =BO100 | R101: =MIN(Q101,MAX(0,C101+K101+M101-P101)) | S101: =P101+R101 | T101: =Pool!BN101+Pool!BO101+Pool!BQ101 | U101: =IF(OR(Inputs!$B$53=1,Tests!M100=1),1,0) | V101: =D101+E101+F101 | W101: =IF(U101=1,MIN(D101,T101),IF(V101<=0,0,MIN(T101,V101)*D101/V101)) | X101: =IF(U101=1,MIN(E101,T101-W101),IF(V101<=0,0,MIN(T101,V101)*E101/V101)) | Y101: =IF(U101=1,MIN(F101,T101-W101-X101),IF(V101<=0,0,MIN(T101,V101)*F101/V101)) | Z101: =T101-W101-X101-Y101 | AA101: =D101-W101 | AB101: =E101-X101 | AC101: =F101-Y101 | AD101: =AA101+AB101+AC101 | AE101: =MIN(C101,S101) | AF101: =S101-AE101 | AG101: =MIN(K101,AF101) | AH101: =AF101-AG101 | AI101: =IF(Tests!F101=1,MIN(AH101,AD101),0) | AJ101: =AH101-AI101 | AK101: =MIN(M101,AJ101) | AL101: =AJ101-AK101 | AM101: =IF(Tests!I101=1,MIN(AL101,AD101-AI101),0) | AN101: =AL101-AM101 | AO101: =MIN(O101,AN101) | AP101: =AN101-AO101 | AQ101: =IF(Tests!L101=1,MIN(AP101,AD101-AI101-AM101),0) | AR101: =AP101-AQ101 | AS101: =MAX(0,AD101-AI101-AM101-AQ101-Pool!BV101) | AT101: =MIN(AR101,AS101) | AU101: =AR101-AT101 | AV101: =AI101+AM101+AQ101+AT101 | AW101: =MIN(AA101,AV101) | AX101: =MIN(AB101,AV101-AW101) | AY101: =MIN(AC101,AV101-AW101-AX101) | AZ101: =AA101-AW101 | BA101: =AB101-AX101 | BB101: =AC101-AY101 | BC101: =AZ101+BA101+BB101 | BD101: =MAX(0,BC101-Pool!BV101) | BE101: =MIN(BB101,BD101) | BF101: =MIN(BA101,BD101-BE101) | BG101: =MIN(AZ101,BD101-BE101-BF101) | BH101: =AZ101-BG101 | BI101: =BA101-BF101 | BJ101: =BB101-BE101 | BK101: =IF(BH101+BI101+BJ101<0.005,1,0) | BL101: =Q101-R101 | BM101: =IF(BK101=1,0,MIN(AU101,MAX(0,Inputs!$B$48-BL101))) | BN101: =IF(BK101=1,BL101,0) | BO101: =BL101+BM101-BN101 | BP101: =AU101-BM101 | BQ101: =BP101+Z101+BN101 | BR101: =W101+AW101 | BS101: =X101+AX101 | BT101: =Y101+AY101 | BU101: =AG101+AK101+AO101+BR101+BS101+BT101 | BV101: =K101-AG101 | BW101: =M101-AK101 | BX101: =O101-AO101 | BY101: =C101-AE101 | BZ101: =AE101+BU101+BQ101+(BO101-Q101)-Pool!BW101

Sheet Tests
A1: Tests
A2: OC and IC tests on pro forma balances, breach flags, excess spread.
A4: Period | B4: Collateral value | C4: IC numerator (interest less fees) | D4: OC ratio A | E4: IC ratio A | F4: Breach A (1=yes) | G4: OC ratio B | H4: IC ratio B | I4: Breach B (1=yes) | J4: OC ratio C | K4: IC ratio C | L4: Breach C (1=yes) | M4: Any breach | N4: Excess spread ($) | O4: Excess spread (annualized bps of pool) | P4: Cum net loss % of pool | Q4: Excess spread diverted (turbo) | R4: Reserve balance
A5: 0 | M5: 0 | P5: 0 | R5: =Waterfall!BO5
A6: 1 | B6: =Pool!BV6 | C6: =MAX(0,Waterfall!P6-Waterfall!B6) | D6: =IF(Waterfall!AA6<=0.005,999,B6/Waterfall!AA6) | E6: =IF(Waterfall!J6<=0.005,999,C6/Waterfall!J6) | F6: =IF(OR(D6<Inputs!$B$56,E6<Inputs!$B$59),1,0) | G6: =IF((Waterfall!AA6+Waterfall!AB6)<=0.005,999,B6/(Waterfall!AA6+Waterfall!AB6)) | H6: =IF((Waterfall!J6+Waterfall!L6)<=0.005,999,C6/(Waterfall!J6+Waterfall!L6)) | I6: =IF(OR(G6<Inputs!$B$57,H6<Inputs!$B$60),1,0) | J6: =IF((Waterfall!AA6+Waterfall!AB6+Waterfall!AC6)<=0.005,999,B6/(Waterfall!AA6+Waterfall!AB6+Waterfall!AC6)) | K6: =IF((Waterfall!J6+Waterfall!L6+Waterfall!N6)<=0.005,999,C6/(Waterfall!J6+Waterfall!L6+Waterfall!N6)) | L6: =IF(OR(J6<Inputs!$B$58,K6<Inputs!$B$61),1,0) | M6: =IF(F6+I6+L6>0,1,0) | N6: =Waterfall!P6-Waterfall!B6-Waterfall!J6-Waterfall!L6-Waterfall!N6 | O6: =IF(Pool!BK6<=0,0,N6*12/Pool!BK6*10000) | P6: =Pool!BT6/Inputs!$B$49 | Q6: =Waterfall!AV6 | R6: =Waterfall!BO6
A7: 2 | B7: =Pool!BV7 | C7: =MAX(0,Waterfall!P7-Waterfall!B7) | D7: =IF(Waterfall!AA7<=0.005,999,B7/Waterfall!AA7) | E7: =IF(Waterfall!J7<=0.005,999,C7/Waterfall!J7) | F7: =IF(OR(D7<Inputs!$B$56,E7<Inputs!$B$59),1,0) | G7: =IF((Waterfall!AA7+Waterfall!AB7)<=0.005,999,B7/(Waterfall!AA7+Waterfall!AB7)) | H7: =IF((Waterfall!J7+Waterfall!L7)<=0.005,999,C7/(Waterfall!J7+Waterfall!L7)) | I7: =IF(OR(G7<Inputs!$B$57,H7<Inputs!$B$60),1,0) | J7: =IF((Waterfall!AA7+Waterfall!AB7+Waterfall!AC7)<=0.005,999,B7/(Waterfall!AA7+Waterfall!AB7+Waterfall!AC7)) | K7: =IF((Waterfall!J7+Waterfall!L7+Waterfall!N7)<=0.005,999,C7/(Waterfall!J7+Waterfall!L7+Waterfall!N7)) | L7: =IF(OR(J7<Inputs!$B$58,K7<Inputs!$B$61),1,0) | M7: =IF(F7+I7+L7>0,1,0) | N7: =Waterfall!P7-Waterfall!B7-Waterfall!J7-Waterfall!L7-Waterfall!N7 | O7: =IF(Pool!BK7<=0,0,N7*12/Pool!BK7*10000) | P7: =Pool!BT7/Inputs!$B$49 | Q7: =Waterfall!AV7 | R7: =Waterfall!BO7
A8: 3 | B8: =Pool!BV8 | C8: =MAX(0,Waterfall!P8-Waterfall!B8) | D8: =IF(Waterfall!AA8<=0.005,999,B8/Waterfall!AA8) | E8: =IF(Waterfall!J8<=0.005,999,C8/Waterfall!J8) | F8: =IF(OR(D8<Inputs!$B$56,E8<Inputs!$B$59),1,0) | G8: =IF((Waterfall!AA8+Waterfall!AB8)<=0.005,999,B8/(Waterfall!AA8+Waterfall!AB8)) | H8: =IF((Waterfall!J8+Waterfall!L8)<=0.005,999,C8/(Waterfall!J8+Waterfall!L8)) | I8: =IF(OR(G8<Inputs!$B$57,H8<Inputs!$B$60),1,0) | J8: =IF((Waterfall!AA8+Waterfall!AB8+Waterfall!AC8)<=0.005,999,B8/(Waterfall!AA8+Waterfall!AB8+Waterfall!AC8)) | K8: =IF((Waterfall!J8+Waterfall!L8+Waterfall!N8)<=0.005,999,C8/(Waterfall!J8+Waterfall!L8+Waterfall!N8)) | L8: =IF(OR(J8<Inputs!$B$58,K8<Inputs!$B$61),1,0) | M8: =IF(F8+I8+L8>0,1,0) | N8: =Waterfall!P8-Waterfall!B8-Waterfall!J8-Waterfall!L8-Waterfall!N8 | O8: =IF(Pool!BK8<=0,0,N8*12/Pool!BK8*10000) | P8: =Pool!BT8/Inputs!$B$49 | Q8: =Waterfall!AV8 | R8: =Waterfall!BO8
A9: 4 | B9: =Pool!BV9 | C9: =MAX(0,Waterfall!P9-Waterfall!B9) | D9: =IF(Waterfall!AA9<=0.005,999,B9/Waterfall!AA9) | E9: =IF(Waterfall!J9<=0.005,999,C9/Waterfall!J9) | F9: =IF(OR(D9<Inputs!$B$56,E9<Inputs!$B$59),1,0) | G9: =IF((Waterfall!AA9+Waterfall!AB9)<=0.005,999,B9/(Waterfall!AA9+Waterfall!AB9)) | H9: =IF((Waterfall!J9+Waterfall!L9)<=0.005,999,C9/(Waterfall!J9+Waterfall!L9)) | I9: =IF(OR(G9<Inputs!$B$57,H9<Inputs!$B$60),1,0) | J9: =IF((Waterfall!AA9+Waterfall!AB9+Waterfall!AC9)<=0.005,999,B9/(Waterfall!AA9+Waterfall!AB9+Waterfall!AC9)) | K9: =IF((Waterfall!J9+Waterfall!L9+Waterfall!N9)<=0.005,999,C9/(Waterfall!J9+Waterfall!L9+Waterfall!N9)) | L9: =IF(OR(J9<Inputs!$B$58,K9<Inputs!$B$61),1,0) | M9: =IF(F9+I9+L9>0,1,0) | N9: =Waterfall!P9-Waterfall!B9-Waterfall!J9-Waterfall!L9-Waterfall!N9 | O9: =IF(Pool!BK9<=0,0,N9*12/Pool!BK9*10000) | P9: =Pool!BT9/Inputs!$B$49 | Q9: =Waterfall!AV9 | R9: =Waterfall!BO9
A10: 5 | B10: =Pool!BV10 | C10: =MAX(0,Waterfall!P10-Waterfall!B10) | D10: =IF(Waterfall!AA10<=0.005,999,B10/Waterfall!AA10) | E10: =IF(Waterfall!J10<=0.005,999,C10/Waterfall!J10) | F10: =IF(OR(D10<Inputs!$B$56,E10<Inputs!$B$59),1,0) | G10: =IF((Waterfall!AA10+Waterfall!AB10)<=0.005,999,B10/(Waterfall!AA10+Waterfall!AB10)) | H10: =IF((Waterfall!J10+Waterfall!L10)<=0.005,999,C10/(Waterfall!J10+Waterfall!L10)) | I10: =IF(OR(G10<Inputs!$B$57,H10<Inputs!$B$60),1,0) | J10: =IF((Waterfall!AA10+Waterfall!AB10+Waterfall!AC10)<=0.005,999,B10/(Waterfall!AA10+Waterfall!AB10+Waterfall!AC10)) | K10: =IF((Waterfall!J10+Waterfall!L10+Waterfall!N10)<=0.005,999,C10/(Waterfall!J10+Waterfall!L10+Waterfall!N10)) | L10: =IF(OR(J10<Inputs!$B$58,K10<Inputs!$B$61),1,0) | M10: =IF(F10+I10+L10>0,1,0) | N10: =Waterfall!P10-Waterfall!B10-Waterfall!J10-Waterfall!L10-Waterfall!N10 | O10: =IF(Pool!BK10<=0,0,N10*12/Pool!BK10*10000) | P10: =Pool!BT10/Inputs!$B$49 | Q10: =Waterfall!AV10 | R10: =Waterfall!BO10
A11: 6 | B11: =Pool!BV11 | C11: =MAX(0,Waterfall!P11-Waterfall!B11) | D11: =IF(Waterfall!AA11<=0.005,999,B11/Waterfall!AA11) | E11: =IF(Waterfall!J11<=0.005,999,C11/Waterfall!J11) | F11: =IF(OR(D11<Inputs!$B$56,E11<Inputs!$B$59),1,0) | G11: =IF((Waterfall!AA11+Waterfall!AB11)<=0.005,999,B11/(Waterfall!AA11+Waterfall!AB11)) | H11: =IF((Waterfall!J11+Waterfall!L11)<=0.005,999,C11/(Waterfall!J11+Waterfall!L11)) | I11: =IF(OR(G11<Inputs!$B$57,H11<Inputs!$B$60),1,0) | J11: =IF((Waterfall!AA11+Waterfall!AB11+Waterfall!AC11)<=0.005,999,B11/(Waterfall!AA11+Waterfall!AB11+Waterfall!AC11)) | K11: =IF((Waterfall!J11+Waterfall!L11+Waterfall!N11)<=0.005,999,C11/(Waterfall!J11+Waterfall!L11+Waterfall!N11)) | L11: =IF(OR(J11<Inputs!$B$58,K11<Inputs!$B$61),1,0) | M11: =IF(F11+I11+L11>0,1,0) | N11: =Waterfall!P11-Waterfall!B11-Waterfall!J11-Waterfall!L11-Waterfall!N11 | O11: =IF(Pool!BK11<=0,0,N11*12/Pool!BK11*10000) | P11: =Pool!BT11/Inputs!$B$49 | Q11: =Waterfall!AV11 | R11: =Waterfall!BO11
A12: 7 | B12: =Pool!BV12 | C12: =MAX(0,Waterfall!P12-Waterfall!B12) | D12: =IF(Waterfall!AA12<=0.005,999,B12/Waterfall!AA12) | E12: =IF(Waterfall!J12<=0.005,999,C12/Waterfall!J12) | F12: =IF(OR(D12<Inputs!$B$56,E12<Inputs!$B$59),1,0) | G12: =IF((Waterfall!AA12+Waterfall!AB12)<=0.005,999,B12/(Waterfall!AA12+Waterfall!AB12)) | H12: =IF((Waterfall!J12+Waterfall!L12)<=0.005,999,C12/(Waterfall!J12+Waterfall!L12)) | I12: =IF(OR(G12<Inputs!$B$57,H12<Inputs!$B$60),1,0) | J12: =IF((Waterfall!AA12+Waterfall!AB12+Waterfall!AC12)<=0.005,999,B12/(Waterfall!AA12+Waterfall!AB12+Waterfall!AC12)) | K12: =IF((Waterfall!J12+Waterfall!L12+Waterfall!N12)<=0.005,999,C12/(Waterfall!J12+Waterfall!L12+Waterfall!N12)) | L12: =IF(OR(J12<Inputs!$B$58,K12<Inputs!$B$61),1,0) | M12: =IF(F12+I12+L12>0,1,0) | N12: =Waterfall!P12-Waterfall!B12-Waterfall!J12-Waterfall!L12-Waterfall!N12 | O12: =IF(Pool!BK12<=0,0,N12*12/Pool!BK12*10000) | P12: =Pool!BT12/Inputs!$B$49 | Q12: =Waterfall!AV12 | R12: =Waterfall!BO12
A13: 8 | B13: =Pool!BV13 | C13: =MAX(0,Waterfall!P13-Waterfall!B13) | D13: =IF(Waterfall!AA13<=0.005,999,B13/Waterfall!AA13) | E13: =IF(Waterfall!J13<=0.005,999,C13/Waterfall!J13) | F13: =IF(OR(D13<Inputs!$B$56,E13<Inputs!$B$59),1,0) | G13: =IF((Waterfall!AA13+Waterfall!AB13)<=0.005,999,B13/(Waterfall!AA13+Waterfall!AB13)) | H13: =IF((Waterfall!J13+Waterfall!L13)<=0.005,999,C13/(Waterfall!J13+Waterfall!L13)) | I13: =IF(OR(G13<Inputs!$B$57,H13<Inputs!$B$60),1,0) | J13: =IF((Waterfall!AA13+Waterfall!AB13+Waterfall!AC13)<=0.005,999,B13/(Waterfall!AA13+Waterfall!AB13+Waterfall!AC13)) | K13: =IF((Waterfall!J13+Waterfall!L13+Waterfall!N13)<=0.005,999,C13/(Waterfall!J13+Waterfall!L13+Waterfall!N13)) | L13: =IF(OR(J13<Inputs!$B$58,K13<Inputs!$B$61),1,0) | M13: =IF(F13+I13+L13>0,1,0) | N13: =Waterfall!P13-Waterfall!B13-Waterfall!J13-Waterfall!L13-Waterfall!N13 | O13: =IF(Pool!BK13<=0,0,N13*12/Pool!BK13*10000) | P13: =Pool!BT13/Inputs!$B$49 | Q13: =Waterfall!AV13 | R13: =Waterfall!BO13
A14: 9 | B14: =Pool!BV14 | C14: =MAX(0,Waterfall!P14-Waterfall!B14) | D14: =IF(Waterfall!AA14<=0.005,999,B14/Waterfall!AA14) | E14: =IF(Waterfall!J14<=0.005,999,C14/Waterfall!J14) | F14: =IF(OR(D14<Inputs!$B$56,E14<Inputs!$B$59),1,0) | G14: =IF((Waterfall!AA14+Waterfall!AB14)<=0.005,999,B14/(Waterfall!AA14+Waterfall!AB14)) | H14: =IF((Waterfall!J14+Waterfall!L14)<=0.005,999,C14/(Waterfall!J14+Waterfall!L14)) | I14: =IF(OR(G14<Inputs!$B$57,H14<Inputs!$B$60),1,0) | J14: =IF((Waterfall!AA14+Waterfall!AB14+Waterfall!AC14)<=0.005,999,B14/(Waterfall!AA14+Waterfall!AB14+Waterfall!AC14)) | K14: =IF((Waterfall!J14+Waterfall!L14+Waterfall!N14)<=0.005,999,C14/(Waterfall!J14+Waterfall!L14+Waterfall!N14)) | L14: =IF(OR(J14<Inputs!$B$58,K14<Inputs!$B$61),1,0) | M14: =IF(F14+I14+L14>0,1,0) | N14: =Waterfall!P14-Waterfall!B14-Waterfall!J14-Waterfall!L14-Waterfall!N14 | O14: =IF(Pool!BK14<=0,0,N14*12/Pool!BK14*10000) | P14: =Pool!BT14/Inputs!$B$49 | Q14: =Waterfall!AV14 | R14: =Waterfall!BO14
A15: 10 | B15: =Pool!BV15 | C15: =MAX(0,Waterfall!P15-Waterfall!B15) | D15: =IF(Waterfall!AA15<=0.005,999,B15/Waterfall!AA15) | E15: =IF(Waterfall!J15<=0.005,999,C15/Waterfall!J15) | F15: =IF(OR(D15<Inputs!$B$56,E15<Inputs!$B$59),1,0) | G15: =IF((Waterfall!AA15+Waterfall!AB15)<=0.005,999,B15/(Waterfall!AA15+Waterfall!AB15)) | H15: =IF((Waterfall!J15+Waterfall!L15)<=0.005,999,C15/(Waterfall!J15+Waterfall!L15)) | I15: =IF(OR(G15<Inputs!$B$57,H15<Inputs!$B$60),1,0) | J15: =IF((Waterfall!AA15+Waterfall!AB15+Waterfall!AC15)<=0.005,999,B15/(Waterfall!AA15+Waterfall!AB15+Waterfall!AC15)) | K15: =IF((Waterfall!J15+Waterfall!L15+Waterfall!N15)<=0.005,999,C15/(Waterfall!J15+Waterfall!L15+Waterfall!N15)) | L15: =IF(OR(J15<Inputs!$B$58,K15<Inputs!$B$61),1,0) | M15: =IF(F15+I15+L15>0,1,0) | N15: =Waterfall!P15-Waterfall!B15-Waterfall!J15-Waterfall!L15-Waterfall!N15 | O15: =IF(Pool!BK15<=0,0,N15*12/Pool!BK15*10000) | P15: =Pool!BT15/Inputs!$B$49 | Q15: =Waterfall!AV15 | R15: =Waterfall!BO15
A16: 11 | B16: =Pool!BV16 | C16: =MAX(0,Waterfall!P16-Waterfall!B16) | D16: =IF(Waterfall!AA16<=0.005,999,B16/Waterfall!AA16) | E16: =IF(Waterfall!J16<=0.005,999,C16/Waterfall!J16) | F16: =IF(OR(D16<Inputs!$B$56,E16<Inputs!$B$59),1,0) | G16: =IF((Waterfall!AA16+Waterfall!AB16)<=0.005,999,B16/(Waterfall!AA16+Waterfall!AB16)) | H16: =IF((Waterfall!J16+Waterfall!L16)<=0.005,999,C16/(Waterfall!J16+Waterfall!L16)) | I16: =IF(OR(G16<Inputs!$B$57,H16<Inputs!$B$60),1,0) | J16: =IF((Waterfall!AA16+Waterfall!AB16+Waterfall!AC16)<=0.005,999,B16/(Waterfall!AA16+Waterfall!AB16+Waterfall!AC16)) | K16: =IF((Waterfall!J16+Waterfall!L16+Waterfall!N16)<=0.005,999,C16/(Waterfall!J16+Waterfall!L16+Waterfall!N16)) | L16: =IF(OR(J16<Inputs!$B$58,K16<Inputs!$B$61),1,0) | M16: =IF(F16+I16+L16>0,1,0) | N16: =Waterfall!P16-Waterfall!B16-Waterfall!J16-Waterfall!L16-Waterfall!N16 | O16: =IF(Pool!BK16<=0,0,N16*12/Pool!BK16*10000) | P16: =Pool!BT16/Inputs!$B$49 | Q16: =Waterfall!AV16 | R16: =Waterfall!BO16
A17: 12 | B17: =Pool!BV17 | C17: =MAX(0,Waterfall!P17-Waterfall!B17) | D17: =IF(Waterfall!AA17<=0.005,999,B17/Waterfall!AA17) | E17: =IF(Waterfall!J17<=0.005,999,C17/Waterfall!J17) | F17: =IF(OR(D17<Inputs!$B$56,E17<Inputs!$B$59),1,0) | G17: =IF((Waterfall!AA17+Waterfall!AB17)<=0.005,999,B17/(Waterfall!AA17+Waterfall!AB17)) | H17: =IF((Waterfall!J17+Waterfall!L17)<=0.005,999,C17/(Waterfall!J17+Waterfall!L17)) | I17: =IF(OR(G17<Inputs!$B$57,H17<Inputs!$B$60),1,0) | J17: =IF((Waterfall!AA17+Waterfall!AB17+Waterfall!AC17)<=0.005,999,B17/(Waterfall!AA17+Waterfall!AB17+Waterfall!AC17)) | K17: =IF((Waterfall!J17+Waterfall!L17+Waterfall!N17)<=0.005,999,C17/(Waterfall!J17+Waterfall!L17+Waterfall!N17)) | L17: =IF(OR(J17<Inputs!$B$58,K17<Inputs!$B$61),1,0) | M17: =IF(F17+I17+L17>0,1,0) | N17: =Waterfall!P17-Waterfall!B17-Waterfall!J17-Waterfall!L17-Waterfall!N17 | O17: =IF(Pool!BK17<=0,0,N17*12/Pool!BK17*10000) | P17: =Pool!BT17/Inputs!$B$49 | Q17: =Waterfall!AV17 | R17: =Waterfall!BO17
... A101: 96 | B101: =Pool!BV101 | C101: =MAX(0,Waterfall!P101-Waterfall!B101) | D101: =IF(Waterfall!AA101<=0.005,999,B101/Waterfall!AA101) | E101: =IF(Waterfall!J101<=0.005,999,C101/Waterfall!J101) | F101: =IF(OR(D101<Inputs!$B$56,E101<Inputs!$B$59),1,0) | G101: =IF((Waterfall!AA101+Waterfall!AB101)<=0.005,999,B101/(Waterfall!AA101+Waterfall!AB101)) | H101: =IF((Waterfall!J101+Waterfall!L101)<=0.005,999,C101/(Waterfall!J101+Waterfall!L101)) | I101: =IF(OR(G101<Inputs!$B$57,H101<Inputs!$B$60),1,0) | J101: =IF((Waterfall!AA101+Waterfall!AB101+Waterfall!AC101)<=0.005,999,B101/(Waterfall!AA101+Waterfall!AB101+Waterfall!AC101)) | K101: =IF((Waterfall!J101+Waterfall!L101+Waterfall!N101)<=0.005,999,C101/(Waterfall!J101+Waterfall!L101+Waterfall!N101)) | L101: =IF(OR(J101<Inputs!$B$58,K101<Inputs!$B$61),1,0) | M101: =IF(F101+I101+L101>0,1,0) | N101: =Waterfall!P101-Waterfall!B101-Waterfall!J101-Waterfall!L101-Waterfall!N101 | O101: =IF(Pool!BK101<=0,0,N101*12/Pool!BK101*10000) | P101: =Pool!BT101/Inputs!$B$49 | Q101: =Waterfall!AV101 | R101: =Waterfall!BO101

Sheet CashFlows
A1: CashFlows
A2: Per-tranche cash flows. Period 0 is the purchase at par (negative).
A4: Period | B4: A interest | C4: A principal | D4: A write-down | E4: A end balance | F4: A cash flow | G4: B interest | H4: B principal | I4: B write-down | J4: B end balance | K4: B cash flow | L4: C interest | M4: C principal | N4: C write-down | O4: C end balance | P4: C cash flow | Q4: R interest distribution | R4: R principal + reserve release | S4: R cash flow | T4: Forward index
A5: 0 | E5: =Waterfall!BH5 | F5: =-Inputs!$B$39 | J5: =Waterfall!BI5 | K5: =-Inputs!$B$40 | O5: =Waterfall!BJ5 | P5: =-Inputs!$B$41 | S5: =-Inputs!$B$50 | T5: =Pool!B5
A6: 1 | B6: =Waterfall!AG6 | C6: =Waterfall!BR6 | D6: =Waterfall!BG6 | E6: =Waterfall!BH6 | F6: =B6+C6 | G6: =Waterfall!AK6 | H6: =Waterfall!BS6 | I6: =Waterfall!BF6 | J6: =Waterfall!BI6 | K6: =G6+H6 | L6: =Waterfall!AO6 | M6: =Waterfall!BT6 | N6: =Waterfall!BE6 | O6: =Waterfall!BJ6 | P6: =L6+M6 | Q6: =Waterfall!BP6 | R6: =Waterfall!Z6+Waterfall!BN6 | S6: =Q6+R6 | T6: =Pool!B6
A7: 2 | B7: =Waterfall!AG7 | C7: =Waterfall!BR7 | D7: =Waterfall!BG7 | E7: =Waterfall!BH7 | F7: =B7+C7 | G7: =Waterfall!AK7 | H7: =Waterfall!BS7 | I7: =Waterfall!BF7 | J7: =Waterfall!BI7 | K7: =G7+H7 | L7: =Waterfall!AO7 | M7: =Waterfall!BT7 | N7: =Waterfall!BE7 | O7: =Waterfall!BJ7 | P7: =L7+M7 | Q7: =Waterfall!BP7 | R7: =Waterfall!Z7+Waterfall!BN7 | S7: =Q7+R7 | T7: =Pool!B7
A8: 3 | B8: =Waterfall!AG8 | C8: =Waterfall!BR8 | D8: =Waterfall!BG8 | E8: =Waterfall!BH8 | F8: =B8+C8 | G8: =Waterfall!AK8 | H8: =Waterfall!BS8 | I8: =Waterfall!BF8 | J8: =Waterfall!BI8 | K8: =G8+H8 | L8: =Waterfall!AO8 | M8: =Waterfall!BT8 | N8: =Waterfall!BE8 | O8: =Waterfall!BJ8 | P8: =L8+M8 | Q8: =Waterfall!BP8 | R8: =Waterfall!Z8+Waterfall!BN8 | S8: =Q8+R8 | T8: =Pool!B8
A9: 4 | B9: =Waterfall!AG9 | C9: =Waterfall!BR9 | D9: =Waterfall!BG9 | E9: =Waterfall!BH9 | F9: =B9+C9 | G9: =Waterfall!AK9 | H9: =Waterfall!BS9 | I9: =Waterfall!BF9 | J9: =Waterfall!BI9 | K9: =G9+H9 | L9: =Waterfall!AO9 | M9: =Waterfall!BT9 | N9: =Waterfall!BE9 | O9: =Waterfall!BJ9 | P9: =L9+M9 | Q9: =Waterfall!BP9 | R9: =Waterfall!Z9+Waterfall!BN9 | S9: =Q9+R9 | T9: =Pool!B9
A10: 5 | B10: =Waterfall!AG10 | C10: =Waterfall!BR10 | D10: =Waterfall!BG10 | E10: =Waterfall!BH10 | F10: =B10+C10 | G10: =Waterfall!AK10 | H10: =Waterfall!BS10 | I10: =Waterfall!BF10 | J10: =Waterfall!BI10 | K10: =G10+H10 | L10: =Waterfall!AO10 | M10: =Waterfall!BT10 | N10: =Waterfall!BE10 | O10: =Waterfall!BJ10 | P10: =L10+M10 | Q10: =Waterfall!BP10 | R10: =Waterfall!Z10+Waterfall!BN10 | S10: =Q10+R10 | T10: =Pool!B10
A11: 6 | B11: =Waterfall!AG11 | C11: =Waterfall!BR11 | D11: =Waterfall!BG11 | E11: =Waterfall!BH11 | F11: =B11+C11 | G11: =Waterfall!AK11 | H11: =Waterfall!BS11 | I11: =Waterfall!BF11 | J11: =Waterfall!BI11 | K11: =G11+H11 | L11: =Waterfall!AO11 | M11: =Waterfall!BT11 | N11: =Waterfall!BE11 | O11: =Waterfall!BJ11 | P11: =L11+M11 | Q11: =Waterfall!BP11 | R11: =Waterfall!Z11+Waterfall!BN11 | S11: =Q11+R11 | T11: =Pool!B11
A12: 7 | B12: =Waterfall!AG12 | C12: =Waterfall!BR12 | D12: =Waterfall!BG12 | E12: =Waterfall!BH12 | F12: =B12+C12 | G12: =Waterfall!AK12 | H12: =Waterfall!BS12 | I12: =Waterfall!BF12 | J12: =Waterfall!BI12 | K12: =G12+H12 | L12: =Waterfall!AO12 | M12: =Waterfall!BT12 | N12: =Waterfall!BE12 | O12: =Waterfall!BJ12 | P12: =L12+M12 | Q12: =Waterfall!BP12 | R12: =Waterfall!Z12+Waterfall!BN12 | S12: =Q12+R12 | T12: =Pool!B12
A13: 8 | B13: =Waterfall!AG13 | C13: =Waterfall!BR13 | D13: =Waterfall!BG13 | E13: =Waterfall!BH13 | F13: =B13+C13 | G13: =Waterfall!AK13 | H13: =Waterfall!BS13 | I13: =Waterfall!BF13 | J13: =Waterfall!BI13 | K13: =G13+H13 | L13: =Waterfall!AO13 | M13: =Waterfall!BT13 | N13: =Waterfall!BE13 | O13: =Waterfall!BJ13 | P13: =L13+M13 | Q13: =Waterfall!BP13 | R13: =Waterfall!Z13+Waterfall!BN13 | S13: =Q13+R13 | T13: =Pool!B13
A14: 9 | B14: =Waterfall!AG14 | C14: =Waterfall!BR14 | D14: =Waterfall!BG14 | E14: =Waterfall!BH14 | F14: =B14+C14 | G14: =Waterfall!AK14 | H14: =Waterfall!BS14 | I14: =Waterfall!BF14 | J14: =Waterfall!BI14 | K14: =G14+H14 | L14: =Waterfall!AO14 | M14: =Waterfall!BT14 | N14: =Waterfall!BE14 | O14: =Waterfall!BJ14 | P14: =L14+M14 | Q14: =Waterfall!BP14 | R14: =Waterfall!Z14+Waterfall!BN14 | S14: =Q14+R14 | T14: =Pool!B14
A15: 10 | B15: =Waterfall!AG15 | C15: =Waterfall!BR15 | D15: =Waterfall!BG15 | E15: =Waterfall!BH15 | F15: =B15+C15 | G15: =Waterfall!AK15 | H15: =Waterfall!BS15 | I15: =Waterfall!BF15 | J15: =Waterfall!BI15 | K15: =G15+H15 | L15: =Waterfall!AO15 | M15: =Waterfall!BT15 | N15: =Waterfall!BE15 | O15: =Waterfall!BJ15 | P15: =L15+M15 | Q15: =Waterfall!BP15 | R15: =Waterfall!Z15+Waterfall!BN15 | S15: =Q15+R15 | T15: =Pool!B15
A16: 11 | B16: =Waterfall!AG16 | C16: =Waterfall!BR16 | D16: =Waterfall!BG16 | E16: =Waterfall!BH16 | F16: =B16+C16 | G16: =Waterfall!AK16 | H16: =Waterfall!BS16 | I16: =Waterfall!BF16 | J16: =Waterfall!BI16 | K16: =G16+H16 | L16: =Waterfall!AO16 | M16: =Waterfall!BT16 | N16: =Waterfall!BE16 | O16: =Waterfall!BJ16 | P16: =L16+M16 | Q16: =Waterfall!BP16 | R16: =Waterfall!Z16+Waterfall!BN16 | S16: =Q16+R16 | T16: =Pool!B16
A17: 12 | B17: =Waterfall!AG17 | C17: =Waterfall!BR17 | D17: =Waterfall!BG17 | E17: =Waterfall!BH17 | F17: =B17+C17 | G17: =Waterfall!AK17 | H17: =Waterfall!BS17 | I17: =Waterfall!BF17 | J17: =Waterfall!BI17 | K17: =G17+H17 | L17: =Waterfall!AO17 | M17: =Waterfall!BT17 | N17: =Waterfall!BE17 | O17: =Waterfall!BJ17 | P17: =L17+M17 | Q17: =Waterfall!BP17 | R17: =Waterfall!Z17+Waterfall!BN17 | S17: =Q17+R17 | T17: =Pool!B17
... A101: 96 | B101: =Waterfall!AG101 | C101: =Waterfall!BR101 | D101: =Waterfall!BG101 | E101: =Waterfall!BH101 | F101: =B101+C101 | G101: =Waterfall!AK101 | H101: =Waterfall!BS101 | I101: =Waterfall!BF101 | J101: =Waterfall!BI101 | K101: =G101+H101 | L101: =Waterfall!AO101 | M101: =Waterfall!BT101 | N101: =Waterfall!BE101 | O101: =Waterfall!BJ101 | P101: =L101+M101 | Q101: =Waterfall!BP101 | R101: =Waterfall!Z101+Waterfall!BN101 | S101: =Q101+R101 | T101: =Pool!B101

Sheet Retention_CF
A1: Retention_CF
A2: Retained-position cash flows and financing sweep by retention option.
A4: Period | B4: Forward index | C4: DF A (fwd + FV margin) | D4: DF B (fwd + FV margin) | E4: DF C (fwd + FV margin) | F4: DF R (fwd + FV margin) | G4: DF financing (fwd + spread) | H4: US RR vertical 246.4(a)(1) retained cash flow | I4: rrv loan balance | J4: rrv loan interest | K4: rrv loan payment (sweep) | L4: rrv sponsor cash flow after loan | M4: US RR horizontal 246.4(a)(2) retained cash flow | N4: rrh loan balance | O4: rrh loan interest | P4: rrh loan payment (sweep) | Q4: rrh sponsor cash flow after loan | R4: US RR L-shaped 246.4(a)(3) retained cash flow | S4: rrl loan balance | T4: rrl loan interest | U4: rrl loan payment (sweep) | V4: rrl sponsor cash flow after loan | W4: EU Art 6(3)(a) vertical retained cash flow | X4: euv loan balance | Y4: euv loan interest | Z4: euv loan payment (sweep) | AA4: euv sponsor cash flow after loan | AB4: EU Art 6(3)(d) first loss retained cash flow | AC4: eufl loan balance | AD4: eufl loan interest | AE4: eufl loan payment (sweep) | AF4: eufl sponsor cash flow after loan
A5: 0 | B5: =Pool!B5 | C5: 1 | D5: 1 | E5: 1 | F5: 1 | G5: 1 | H5: =-Retention!$F$15 | I5: =Retention!$H$15 | L5: =-(Retention!$F$15-Retention!$H$15) | M5: =-Retention!$F$16 | N5: =Retention!$H$16 | Q5: =-(Retention!$F$16-Retention!$H$16) | R5: =-Retention!$F$17 | S5: =Retention!$H$17 | V5: =-(Retention!$F$17-Retention!$H$17) | W5: =-Retention!$F$18 | X5: =Retention!$H$18 | AA5: =-(Retention!$F$18-Retention!$H$18) | AB5: =-Retention!$F$19 | AC5: =Retention!$H$19 | AF5: =-(Retention!$F$19-Retention!$H$19)
A6: 1 | B6: =Pool!B6 | C6: =C5/(1+(B6+Inputs!$B$64)/12) | D6: =D5/(1+(B6+Inputs!$B$65)/12) | E6: =E5/(1+(B6+Inputs!$B$66)/12) | F6: =F5/(1+(B6+Inputs!$B$67)/12) | G6: =G5/(1+(B6+Inputs!$B$78)/12) | H6: =Retention!$B$15*CashFlows!F6+Retention!$C$15*CashFlows!K6+Retention!$D$15*CashFlows!P6+Retention!$E$15*CashFlows!S6 | I6: =I5+J6-K6 | J6: =I5*(B6+Inputs!$B$78)/12 | K6: =MIN(H6,I5+J6) | L6: =H6-K6 | M6: =Retention!$B$16*CashFlows!F6+Retention!$C$16*CashFlows!K6+Retention!$D$16*CashFlows!P6+Retention!$E$16*CashFlows!S6 | N6: =N5+O6-P6 | O6: =N5*(B6+Inputs!$B$78)/12 | P6: =MIN(M6,N5+O6) | Q6: =M6-P6 | R6: =Retention!$B$17*CashFlows!F6+Retention!$C$17*CashFlows!K6+Retention!$D$17*CashFlows!P6+Retention!$E$17*CashFlows!S6 | S6: =S5+T6-U6 | T6: =S5*(B6+Inputs!$B$78)/12 | U6: =MIN(R6,S5+T6) | V6: =R6-U6 | W6: =Retention!$B$18*CashFlows!F6+Retention!$C$18*CashFlows!K6+Retention!$D$18*CashFlows!P6+Retention!$E$18*CashFlows!S6 | X6: =X5+Y6-Z6 | Y6: =X5*(B6+Inputs!$B$78)/12 | Z6: =MIN(W6,X5+Y6) | AA6: =W6-Z6 | AB6: =Retention!$B$19*CashFlows!F6+Retention!$C$19*CashFlows!K6+Retention!$D$19*CashFlows!P6+Retention!$E$19*CashFlows!S6 | AC6: =AC5+AD6-AE6 | AD6: =AC5*(B6+Inputs!$B$78)/12 | AE6: =MIN(AB6,AC5+AD6) | AF6: =AB6-AE6
A7: 2 | B7: =Pool!B7 | C7: =C6/(1+(B7+Inputs!$B$64)/12) | D7: =D6/(1+(B7+Inputs!$B$65)/12) | E7: =E6/(1+(B7+Inputs!$B$66)/12) | F7: =F6/(1+(B7+Inputs!$B$67)/12) | G7: =G6/(1+(B7+Inputs!$B$78)/12) | H7: =Retention!$B$15*CashFlows!F7+Retention!$C$15*CashFlows!K7+Retention!$D$15*CashFlows!P7+Retention!$E$15*CashFlows!S7 | I7: =I6+J7-K7 | J7: =I6*(B7+Inputs!$B$78)/12 | K7: =MIN(H7,I6+J7) | L7: =H7-K7 | M7: =Retention!$B$16*CashFlows!F7+Retention!$C$16*CashFlows!K7+Retention!$D$16*CashFlows!P7+Retention!$E$16*CashFlows!S7 | N7: =N6+O7-P7 | O7: =N6*(B7+Inputs!$B$78)/12 | P7: =MIN(M7,N6+O7) | Q7: =M7-P7 | R7: =Retention!$B$17*CashFlows!F7+Retention!$C$17*CashFlows!K7+Retention!$D$17*CashFlows!P7+Retention!$E$17*CashFlows!S7 | S7: =S6+T7-U7 | T7: =S6*(B7+Inputs!$B$78)/12 | U7: =MIN(R7,S6+T7) | V7: =R7-U7 | W7: =Retention!$B$18*CashFlows!F7+Retention!$C$18*CashFlows!K7+Retention!$D$18*CashFlows!P7+Retention!$E$18*CashFlows!S7 | X7: =X6+Y7-Z7 | Y7: =X6*(B7+Inputs!$B$78)/12 | Z7: =MIN(W7,X6+Y7) | AA7: =W7-Z7 | AB7: =Retention!$B$19*CashFlows!F7+Retention!$C$19*CashFlows!K7+Retention!$D$19*CashFlows!P7+Retention!$E$19*CashFlows!S7 | AC7: =AC6+AD7-AE7 | AD7: =AC6*(B7+Inputs!$B$78)/12 | AE7: =MIN(AB7,AC6+AD7) | AF7: =AB7-AE7
A8: 3 | B8: =Pool!B8 | C8: =C7/(1+(B8+Inputs!$B$64)/12) | D8: =D7/(1+(B8+Inputs!$B$65)/12) | E8: =E7/(1+(B8+Inputs!$B$66)/12) | F8: =F7/(1+(B8+Inputs!$B$67)/12) | G8: =G7/(1+(B8+Inputs!$B$78)/12) | H8: =Retention!$B$15*CashFlows!F8+Retention!$C$15*CashFlows!K8+Retention!$D$15*CashFlows!P8+Retention!$E$15*CashFlows!S8 | I8: =I7+J8-K8 | J8: =I7*(B8+Inputs!$B$78)/12 | K8: =MIN(H8,I7+J8) | L8: =H8-K8 | M8: =Retention!$B$16*CashFlows!F8+Retention!$C$16*CashFlows!K8+Retention!$D$16*CashFlows!P8+Retention!$E$16*CashFlows!S8 | N8: =N7+O8-P8 | O8: =N7*(B8+Inputs!$B$78)/12 | P8: =MIN(M8,N7+O8) | Q8: =M8-P8 | R8: =Retention!$B$17*CashFlows!F8+Retention!$C$17*CashFlows!K8+Retention!$D$17*CashFlows!P8+Retention!$E$17*CashFlows!S8 | S8: =S7+T8-U8 | T8: =S7*(B8+Inputs!$B$78)/12 | U8: =MIN(R8,S7+T8) | V8: =R8-U8 | W8: =Retention!$B$18*CashFlows!F8+Retention!$C$18*CashFlows!K8+Retention!$D$18*CashFlows!P8+Retention!$E$18*CashFlows!S8 | X8: =X7+Y8-Z8 | Y8: =X7*(B8+Inputs!$B$78)/12 | Z8: =MIN(W8,X7+Y8) | AA8: =W8-Z8 | AB8: =Retention!$B$19*CashFlows!F8+Retention!$C$19*CashFlows!K8+Retention!$D$19*CashFlows!P8+Retention!$E$19*CashFlows!S8 | AC8: =AC7+AD8-AE8 | AD8: =AC7*(B8+Inputs!$B$78)/12 | AE8: =MIN(AB8,AC7+AD8) | AF8: =AB8-AE8
A9: 4 | B9: =Pool!B9 | C9: =C8/(1+(B9+Inputs!$B$64)/12) | D9: =D8/(1+(B9+Inputs!$B$65)/12) | E9: =E8/(1+(B9+Inputs!$B$66)/12) | F9: =F8/(1+(B9+Inputs!$B$67)/12) | G9: =G8/(1+(B9+Inputs!$B$78)/12) | H9: =Retention!$B$15*CashFlows!F9+Retention!$C$15*CashFlows!K9+Retention!$D$15*CashFlows!P9+Retention!$E$15*CashFlows!S9 | I9: =I8+J9-K9 | J9: =I8*(B9+Inputs!$B$78)/12 | K9: =MIN(H9,I8+J9) | L9: =H9-K9 | M9: =Retention!$B$16*CashFlows!F9+Retention!$C$16*CashFlows!K9+Retention!$D$16*CashFlows!P9+Retention!$E$16*CashFlows!S9 | N9: =N8+O9-P9 | O9: =N8*(B9+Inputs!$B$78)/12 | P9: =MIN(M9,N8+O9) | Q9: =M9-P9 | R9: =Retention!$B$17*CashFlows!F9+Retention!$C$17*CashFlows!K9+Retention!$D$17*CashFlows!P9+Retention!$E$17*CashFlows!S9 | S9: =S8+T9-U9 | T9: =S8*(B9+Inputs!$B$78)/12 | U9: =MIN(R9,S8+T9) | V9: =R9-U9 | W9: =Retention!$B$18*CashFlows!F9+Retention!$C$18*CashFlows!K9+Retention!$D$18*CashFlows!P9+Retention!$E$18*CashFlows!S9 | X9: =X8+Y9-Z9 | Y9: =X8*(B9+Inputs!$B$78)/12 | Z9: =MIN(W9,X8+Y9) | AA9: =W9-Z9 | AB9: =Retention!$B$19*CashFlows!F9+Retention!$C$19*CashFlows!K9+Retention!$D$19*CashFlows!P9+Retention!$E$19*CashFlows!S9 | AC9: =AC8+AD9-AE9 | AD9: =AC8*(B9+Inputs!$B$78)/12 | AE9: =MIN(AB9,AC8+AD9) | AF9: =AB9-AE9
A10: 5 | B10: =Pool!B10 | C10: =C9/(1+(B10+Inputs!$B$64)/12) | D10: =D9/(1+(B10+Inputs!$B$65)/12) | E10: =E9/(1+(B10+Inputs!$B$66)/12) | F10: =F9/(1+(B10+Inputs!$B$67)/12) | G10: =G9/(1+(B10+Inputs!$B$78)/12) | H10: =Retention!$B$15*CashFlows!F10+Retention!$C$15*CashFlows!K10+Retention!$D$15*CashFlows!P10+Retention!$E$15*CashFlows!S10 | I10: =I9+J10-K10 | J10: =I9*(B10+Inputs!$B$78)/12 | K10: =MIN(H10,I9+J10) | L10: =H10-K10 | M10: =Retention!$B$16*CashFlows!F10+Retention!$C$16*CashFlows!K10+Retention!$D$16*CashFlows!P10+Retention!$E$16*CashFlows!S10 | N10: =N9+O10-P10 | O10: =N9*(B10+Inputs!$B$78)/12 | P10: =MIN(M10,N9+O10) | Q10: =M10-P10 | R10: =Retention!$B$17*CashFlows!F10+Retention!$C$17*CashFlows!K10+Retention!$D$17*CashFlows!P10+Retention!$E$17*CashFlows!S10 | S10: =S9+T10-U10 | T10: =S9*(B10+Inputs!$B$78)/12 | U10: =MIN(R10,S9+T10) | V10: =R10-U10 | W10: =Retention!$B$18*CashFlows!F10+Retention!$C$18*CashFlows!K10+Retention!$D$18*CashFlows!P10+Retention!$E$18*CashFlows!S10 | X10: =X9+Y10-Z10 | Y10: =X9*(B10+Inputs!$B$78)/12 | Z10: =MIN(W10,X9+Y10) | AA10: =W10-Z10 | AB10: =Retention!$B$19*CashFlows!F10+Retention!$C$19*CashFlows!K10+Retention!$D$19*CashFlows!P10+Retention!$E$19*CashFlows!S10 | AC10: =AC9+AD10-AE10 | AD10: =AC9*(B10+Inputs!$B$78)/12 | AE10: =MIN(AB10,AC9+AD10) | AF10: =AB10-AE10
A11: 6 | B11: =Pool!B11 | C11: =C10/(1+(B11+Inputs!$B$64)/12) | D11: =D10/(1+(B11+Inputs!$B$65)/12) | E11: =E10/(1+(B11+Inputs!$B$66)/12) | F11: =F10/(1+(B11+Inputs!$B$67)/12) | G11: =G10/(1+(B11+Inputs!$B$78)/12) | H11: =Retention!$B$15*CashFlows!F11+Retention!$C$15*CashFlows!K11+Retention!$D$15*CashFlows!P11+Retention!$E$15*CashFlows!S11 | I11: =I10+J11-K11 | J11: =I10*(B11+Inputs!$B$78)/12 | K11: =MIN(H11,I10+J11) | L11: =H11-K11 | M11: =Retention!$B$16*CashFlows!F11+Retention!$C$16*CashFlows!K11+Retention!$D$16*CashFlows!P11+Retention!$E$16*CashFlows!S11 | N11: =N10+O11-P11 | O11: =N10*(B11+Inputs!$B$78)/12 | P11: =MIN(M11,N10+O11) | Q11: =M11-P11 | R11: =Retention!$B$17*CashFlows!F11+Retention!$C$17*CashFlows!K11+Retention!$D$17*CashFlows!P11+Retention!$E$17*CashFlows!S11 | S11: =S10+T11-U11 | T11: =S10*(B11+Inputs!$B$78)/12 | U11: =MIN(R11,S10+T11) | V11: =R11-U11 | W11: =Retention!$B$18*CashFlows!F11+Retention!$C$18*CashFlows!K11+Retention!$D$18*CashFlows!P11+Retention!$E$18*CashFlows!S11 | X11: =X10+Y11-Z11 | Y11: =X10*(B11+Inputs!$B$78)/12 | Z11: =MIN(W11,X10+Y11) | AA11: =W11-Z11 | AB11: =Retention!$B$19*CashFlows!F11+Retention!$C$19*CashFlows!K11+Retention!$D$19*CashFlows!P11+Retention!$E$19*CashFlows!S11 | AC11: =AC10+AD11-AE11 | AD11: =AC10*(B11+Inputs!$B$78)/12 | AE11: =MIN(AB11,AC10+AD11) | AF11: =AB11-AE11
A12: 7 | B12: =Pool!B12 | C12: =C11/(1+(B12+Inputs!$B$64)/12) | D12: =D11/(1+(B12+Inputs!$B$65)/12) | E12: =E11/(1+(B12+Inputs!$B$66)/12) | F12: =F11/(1+(B12+Inputs!$B$67)/12) | G12: =G11/(1+(B12+Inputs!$B$78)/12) | H12: =Retention!$B$15*CashFlows!F12+Retention!$C$15*CashFlows!K12+Retention!$D$15*CashFlows!P12+Retention!$E$15*CashFlows!S12 | I12: =I11+J12-K12 | J12: =I11*(B12+Inputs!$B$78)/12 | K12: =MIN(H12,I11+J12) | L12: =H12-K12 | M12: =Retention!$B$16*CashFlows!F12+Retention!$C$16*CashFlows!K12+Retention!$D$16*CashFlows!P12+Retention!$E$16*CashFlows!S12 | N12: =N11+O12-P12 | O12: =N11*(B12+Inputs!$B$78)/12 | P12: =MIN(M12,N11+O12) | Q12: =M12-P12 | R12: =Retention!$B$17*CashFlows!F12+Retention!$C$17*CashFlows!K12+Retention!$D$17*CashFlows!P12+Retention!$E$17*CashFlows!S12 | S12: =S11+T12-U12 | T12: =S11*(B12+Inputs!$B$78)/12 | U12: =MIN(R12,S11+T12) | V12: =R12-U12 | W12: =Retention!$B$18*CashFlows!F12+Retention!$C$18*CashFlows!K12+Retention!$D$18*CashFlows!P12+Retention!$E$18*CashFlows!S12 | X12: =X11+Y12-Z12 | Y12: =X11*(B12+Inputs!$B$78)/12 | Z12: =MIN(W12,X11+Y12) | AA12: =W12-Z12 | AB12: =Retention!$B$19*CashFlows!F12+Retention!$C$19*CashFlows!K12+Retention!$D$19*CashFlows!P12+Retention!$E$19*CashFlows!S12 | AC12: =AC11+AD12-AE12 | AD12: =AC11*(B12+Inputs!$B$78)/12 | AE12: =MIN(AB12,AC11+AD12) | AF12: =AB12-AE12
A13: 8 | B13: =Pool!B13 | C13: =C12/(1+(B13+Inputs!$B$64)/12) | D13: =D12/(1+(B13+Inputs!$B$65)/12) | E13: =E12/(1+(B13+Inputs!$B$66)/12) | F13: =F12/(1+(B13+Inputs!$B$67)/12) | G13: =G12/(1+(B13+Inputs!$B$78)/12) | H13: =Retention!$B$15*CashFlows!F13+Retention!$C$15*CashFlows!K13+Retention!$D$15*CashFlows!P13+Retention!$E$15*CashFlows!S13 | I13: =I12+J13-K13 | J13: =I12*(B13+Inputs!$B$78)/12 | K13: =MIN(H13,I12+J13) | L13: =H13-K13 | M13: =Retention!$B$16*CashFlows!F13+Retention!$C$16*CashFlows!K13+Retention!$D$16*CashFlows!P13+Retention!$E$16*CashFlows!S13 | N13: =N12+O13-P13 | O13: =N12*(B13+Inputs!$B$78)/12 | P13: =MIN(M13,N12+O13) | Q13: =M13-P13 | R13: =Retention!$B$17*CashFlows!F13+Retention!$C$17*CashFlows!K13+Retention!$D$17*CashFlows!P13+Retention!$E$17*CashFlows!S13 | S13: =S12+T13-U13 | T13: =S12*(B13+Inputs!$B$78)/12 | U13: =MIN(R13,S12+T13) | V13: =R13-U13 | W13: =Retention!$B$18*CashFlows!F13+Retention!$C$18*CashFlows!K13+Retention!$D$18*CashFlows!P13+Retention!$E$18*CashFlows!S13 | X13: =X12+Y13-Z13 | Y13: =X12*(B13+Inputs!$B$78)/12 | Z13: =MIN(W13,X12+Y13) | AA13: =W13-Z13 | AB13: =Retention!$B$19*CashFlows!F13+Retention!$C$19*CashFlows!K13+Retention!$D$19*CashFlows!P13+Retention!$E$19*CashFlows!S13 | AC13: =AC12+AD13-AE13 | AD13: =AC12*(B13+Inputs!$B$78)/12 | AE13: =MIN(AB13,AC12+AD13) | AF13: =AB13-AE13
A14: 9 | B14: =Pool!B14 | C14: =C13/(1+(B14+Inputs!$B$64)/12) | D14: =D13/(1+(B14+Inputs!$B$65)/12) | E14: =E13/(1+(B14+Inputs!$B$66)/12) | F14: =F13/(1+(B14+Inputs!$B$67)/12) | G14: =G13/(1+(B14+Inputs!$B$78)/12) | H14: =Retention!$B$15*CashFlows!F14+Retention!$C$15*CashFlows!K14+Retention!$D$15*CashFlows!P14+Retention!$E$15*CashFlows!S14 | I14: =I13+J14-K14 | J14: =I13*(B14+Inputs!$B$78)/12 | K14: =MIN(H14,I13+J14) | L14: =H14-K14 | M14: =Retention!$B$16*CashFlows!F14+Retention!$C$16*CashFlows!K14+Retention!$D$16*CashFlows!P14+Retention!$E$16*CashFlows!S14 | N14: =N13+O14-P14 | O14: =N13*(B14+Inputs!$B$78)/12 | P14: =MIN(M14,N13+O14) | Q14: =M14-P14 | R14: =Retention!$B$17*CashFlows!F14+Retention!$C$17*CashFlows!K14+Retention!$D$17*CashFlows!P14+Retention!$E$17*CashFlows!S14 | S14: =S13+T14-U14 | T14: =S13*(B14+Inputs!$B$78)/12 | U14: =MIN(R14,S13+T14) | V14: =R14-U14 | W14: =Retention!$B$18*CashFlows!F14+Retention!$C$18*CashFlows!K14+Retention!$D$18*CashFlows!P14+Retention!$E$18*CashFlows!S14 | X14: =X13+Y14-Z14 | Y14: =X13*(B14+Inputs!$B$78)/12 | Z14: =MIN(W14,X13+Y14) | AA14: =W14-Z14 | AB14: =Retention!$B$19*CashFlows!F14+Retention!$C$19*CashFlows!K14+Retention!$D$19*CashFlows!P14+Retention!$E$19*CashFlows!S14 | AC14: =AC13+AD14-AE14 | AD14: =AC13*(B14+Inputs!$B$78)/12 | AE14: =MIN(AB14,AC13+AD14) | AF14: =AB14-AE14
A15: 10 | B15: =Pool!B15 | C15: =C14/(1+(B15+Inputs!$B$64)/12) | D15: =D14/(1+(B15+Inputs!$B$65)/12) | E15: =E14/(1+(B15+Inputs!$B$66)/12) | F15: =F14/(1+(B15+Inputs!$B$67)/12) | G15: =G14/(1+(B15+Inputs!$B$78)/12) | H15: =Retention!$B$15*CashFlows!F15+Retention!$C$15*CashFlows!K15+Retention!$D$15*CashFlows!P15+Retention!$E$15*CashFlows!S15 | I15: =I14+J15-K15 | J15: =I14*(B15+Inputs!$B$78)/12 | K15: =MIN(H15,I14+J15) | L15: =H15-K15 | M15: =Retention!$B$16*CashFlows!F15+Retention!$C$16*CashFlows!K15+Retention!$D$16*CashFlows!P15+Retention!$E$16*CashFlows!S15 | N15: =N14+O15-P15 | O15: =N14*(B15+Inputs!$B$78)/12 | P15: =MIN(M15,N14+O15) | Q15: =M15-P15 | R15: =Retention!$B$17*CashFlows!F15+Retention!$C$17*CashFlows!K15+Retention!$D$17*CashFlows!P15+Retention!$E$17*CashFlows!S15 | S15: =S14+T15-U15 | T15: =S14*(B15+Inputs!$B$78)/12 | U15: =MIN(R15,S14+T15) | V15: =R15-U15 | W15: =Retention!$B$18*CashFlows!F15+Retention!$C$18*CashFlows!K15+Retention!$D$18*CashFlows!P15+Retention!$E$18*CashFlows!S15 | X15: =X14+Y15-Z15 | Y15: =X14*(B15+Inputs!$B$78)/12 | Z15: =MIN(W15,X14+Y15) | AA15: =W15-Z15 | AB15: =Retention!$B$19*CashFlows!F15+Retention!$C$19*CashFlows!K15+Retention!$D$19*CashFlows!P15+Retention!$E$19*CashFlows!S15 | AC15: =AC14+AD15-AE15 | AD15: =AC14*(B15+Inputs!$B$78)/12 | AE15: =MIN(AB15,AC14+AD15) | AF15: =AB15-AE15
A16: 11 | B16: =Pool!B16 | C16: =C15/(1+(B16+Inputs!$B$64)/12) | D16: =D15/(1+(B16+Inputs!$B$65)/12) | E16: =E15/(1+(B16+Inputs!$B$66)/12) | F16: =F15/(1+(B16+Inputs!$B$67)/12) | G16: =G15/(1+(B16+Inputs!$B$78)/12) | H16: =Retention!$B$15*CashFlows!F16+Retention!$C$15*CashFlows!K16+Retention!$D$15*CashFlows!P16+Retention!$E$15*CashFlows!S16 | I16: =I15+J16-K16 | J16: =I15*(B16+Inputs!$B$78)/12 | K16: =MIN(H16,I15+J16) | L16: =H16-K16 | M16: =Retention!$B$16*CashFlows!F16+Retention!$C$16*CashFlows!K16+Retention!$D$16*CashFlows!P16+Retention!$E$16*CashFlows!S16 | N16: =N15+O16-P16 | O16: =N15*(B16+Inputs!$B$78)/12 | P16: =MIN(M16,N15+O16) | Q16: =M16-P16 | R16: =Retention!$B$17*CashFlows!F16+Retention!$C$17*CashFlows!K16+Retention!$D$17*CashFlows!P16+Retention!$E$17*CashFlows!S16 | S16: =S15+T16-U16 | T16: =S15*(B16+Inputs!$B$78)/12 | U16: =MIN(R16,S15+T16) | V16: =R16-U16 | W16: =Retention!$B$18*CashFlows!F16+Retention!$C$18*CashFlows!K16+Retention!$D$18*CashFlows!P16+Retention!$E$18*CashFlows!S16 | X16: =X15+Y16-Z16 | Y16: =X15*(B16+Inputs!$B$78)/12 | Z16: =MIN(W16,X15+Y16) | AA16: =W16-Z16 | AB16: =Retention!$B$19*CashFlows!F16+Retention!$C$19*CashFlows!K16+Retention!$D$19*CashFlows!P16+Retention!$E$19*CashFlows!S16 | AC16: =AC15+AD16-AE16 | AD16: =AC15*(B16+Inputs!$B$78)/12 | AE16: =MIN(AB16,AC15+AD16) | AF16: =AB16-AE16
A17: 12 | B17: =Pool!B17 | C17: =C16/(1+(B17+Inputs!$B$64)/12) | D17: =D16/(1+(B17+Inputs!$B$65)/12) | E17: =E16/(1+(B17+Inputs!$B$66)/12) | F17: =F16/(1+(B17+Inputs!$B$67)/12) | G17: =G16/(1+(B17+Inputs!$B$78)/12) | H17: =Retention!$B$15*CashFlows!F17+Retention!$C$15*CashFlows!K17+Retention!$D$15*CashFlows!P17+Retention!$E$15*CashFlows!S17 | I17: =I16+J17-K17 | J17: =I16*(B17+Inputs!$B$78)/12 | K17: =MIN(H17,I16+J17) | L17: =H17-K17 | M17: =Retention!$B$16*CashFlows!F17+Retention!$C$16*CashFlows!K17+Retention!$D$16*CashFlows!P17+Retention!$E$16*CashFlows!S17 | N17: =N16+O17-P17 | O17: =N16*(B17+Inputs!$B$78)/12 | P17: =MIN(M17,N16+O17) | Q17: =M17-P17 | R17: =Retention!$B$17*CashFlows!F17+Retention!$C$17*CashFlows!K17+Retention!$D$17*CashFlows!P17+Retention!$E$17*CashFlows!S17 | S17: =S16+T17-U17 | T17: =S16*(B17+Inputs!$B$78)/12 | U17: =MIN(R17,S16+T17) | V17: =R17-U17 | W17: =Retention!$B$18*CashFlows!F17+Retention!$C$18*CashFlows!K17+Retention!$D$18*CashFlows!P17+Retention!$E$18*CashFlows!S17 | X17: =X16+Y17-Z17 | Y17: =X16*(B17+Inputs!$B$78)/12 | Z17: =MIN(W17,X16+Y17) | AA17: =W17-Z17 | AB17: =Retention!$B$19*CashFlows!F17+Retention!$C$19*CashFlows!K17+Retention!$D$19*CashFlows!P17+Retention!$E$19*CashFlows!S17 | AC17: =AC16+AD17-AE17 | AD17: =AC16*(B17+Inputs!$B$78)/12 | AE17: =MIN(AB17,AC16+AD17) | AF17: =AB17-AE17
... A101: 96 | B101: =Pool!B101 | C101: =C100/(1+(B101+Inputs!$B$64)/12) | D101: =D100/(1+(B101+Inputs!$B$65)/12) | E101: =E100/(1+(B101+Inputs!$B$66)/12) | F101: =F100/(1+(B101+Inputs!$B$67)/12) | G101: =G100/(1+(B101+Inputs!$B$78)/12) | H101: =Retention!$B$15*CashFlows!F101+Retention!$C$15*CashFlows!K101+Retention!$D$15*CashFlows!P101+Retention!$E$15*CashFlows!S101 | I101: =I100+J101-K101 | J101: =I100*(B101+Inputs!$B$78)/12 | K101: =MIN(H101,I100+J101) | L101: =H101-K101 | M101: =Retention!$B$16*CashFlows!F101+Retention!$C$16*CashFlows!K101+Retention!$D$16*CashFlows!P101+Retention!$E$16*CashFlows!S101 | N101: =N100+O101-P101 | O101: =N100*(B101+Inputs!$B$78)/12 | P101: =MIN(M101,N100+O101) | Q101: =M101-P101 | R101: =Retention!$B$17*CashFlows!F101+Retention!$C$17*CashFlows!K101+Retention!$D$17*CashFlows!P101+Retention!$E$17*CashFlows!S101 | S101: =S100+T101-U101 | T101: =S100*(B101+Inputs!$B$78)/12 | U101: =MIN(R101,S100+T101) | V101: =R101-U101 | W101: =Retention!$B$18*CashFlows!F101+Retention!$C$18*CashFlows!K101+Retention!$D$18*CashFlows!P101+Retention!$E$18*CashFlows!S101 | X101: =X100+Y101-Z101 | Y101: =X100*(B101+Inputs!$B$78)/12 | Z101: =MIN(W101,X100+Y101) | AA101: =W101-Z101 | AB101: =Retention!$B$19*CashFlows!F101+Retention!$C$19*CashFlows!K101+Retention!$D$19*CashFlows!P101+Retention!$E$19*CashFlows!S101 | AC101: =AC100+AD101-AE101 | AD101: =AC100*(B101+Inputs!$B$78)/12 | AE101: =MIN(AB101,AC100+AD101) | AF101: =AB101-AE101

Sheet Retention
A1: Risk retention sizing (US Regulation RR, 17 CFR Part 246; EU Regulation 2017/2402 Article 6)
A2: Fair values are PV of the selected scenario's tranche cash flows at forward + assumed margin (illustrative). Retained cost basis for yield is par.
A4: Fair value of each ABS interest
A5: Tranche | B5: Par | C5: Fair value used for sizing | D5: Live PV fair value (selected scenario) | E5: FV used % of par
A6: A | B6: =Inputs!$B$39 | C6: =IF(ISNUMBER(Inputs!$B$81),Inputs!$B$81,D6) | D6: =SUMPRODUCT(CashFlows!$F$6:$F$101,Retention_CF!$C$6:$C$101) | E6: =C6/B6
A7: B | B7: =Inputs!$B$40 | C7: =IF(ISNUMBER(Inputs!$B$82),Inputs!$B$82,D7) | D7: =SUMPRODUCT(CashFlows!$K$6:$K$101,Retention_CF!$D$6:$D$101) | E7: =C7/B7
A8: C | B8: =Inputs!$B$41 | C8: =IF(ISNUMBER(Inputs!$B$83),Inputs!$B$83,D8) | D8: =SUMPRODUCT(CashFlows!$P$6:$P$101,Retention_CF!$E$6:$E$101) | E8: =C8/B8
A9: R | B9: =Inputs!$B$50 | C9: =IF(ISNUMBER(Inputs!$B$84),Inputs!$B$84,D9) | D9: =SUMPRODUCT(CashFlows!$S$6:$S$101,Retention_CF!$F$6:$F$101) | E9: =C9/B9
A10: Total | B10: =SUM(B6:B9) | C10: =SUM(C6:C9) | D10: =SUM(D6:D9)
A12: US minimum horizontal fair value (5% of FV of all ABS interests), also the 246.4(b) cash reserve alternative | C12: =Inputs!$B$68*C10
A13: EU 6(3)(d) required nominal (5% of pool at origination); same amount for 6(3)(c) and 6(3)(e) | C13: =Inputs!$B$68*Inputs!$B$49
A14: Option (fraction of each class retained) | B14: A | C14: B | D14: C | E14: R | F14: Retained par (cost) | G14: Retained fair value | H14: Advance | I14: Par % of pool | J14: FV % of all FV
A15: US RR vertical 246.4(a)(1) | B15: =Inputs!$B$68 | C15: =Inputs!$B$68 | D15: =Inputs!$B$68 | E15: =Inputs!$B$68 | F15: =B15*Inputs!$B$39+C15*Inputs!$B$40+D15*Inputs!$B$41+E15*Inputs!$B$50 | G15: =B15*$C$6+C15*$C$7+D15*$C$8+E15*$C$9 | H15: =B15*Inputs!$B$39*Inputs!$B$74+C15*Inputs!$B$40*Inputs!$B$75+D15*Inputs!$B$41*Inputs!$B$76+E15*Inputs!$B$50*Inputs!$B$77 | I15: =F15/Inputs!$B$49 | J15: =G15/$C$10
A16: US RR horizontal 246.4(a)(2) | B16: =IF(Retention!$C$6<=0,0,MIN(1,MAX(0,Inputs!$B$68*$C$10-E16*Retention!$C$9-D16*Retention!$C$8-C16*Retention!$C$7)/Retention!$C$6)) | C16: =IF(Retention!$C$7<=0,0,MIN(1,MAX(0,Inputs!$B$68*$C$10-E16*Retention!$C$9-D16*Retention!$C$8)/Retention!$C$7)) | D16: =IF(Retention!$C$8<=0,0,MIN(1,MAX(0,Inputs!$B$68*$C$10-E16*Retention!$C$9)/Retention!$C$8)) | E16: =IF(Retention!$C$9<=0,0,MIN(1,MAX(0,Inputs!$B$68*$C$10)/Retention!$C$9)) | F16: =B16*Inputs!$B$39+C16*Inputs!$B$40+D16*Inputs!$B$41+E16*Inputs!$B$50 | G16: =B16*$C$6+C16*$C$7+D16*$C$8+E16*$C$9 | H16: =B16*Inputs!$B$39*Inputs!$B$74+C16*Inputs!$B$40*Inputs!$B$75+D16*Inputs!$B$41*Inputs!$B$76+E16*Inputs!$B$50*Inputs!$B$77 | I16: =F16/Inputs!$B$49 | J16: =G16/$C$10
A17: US RR L-shaped 246.4(a)(3) | B17: =MIN(1,Inputs!$B$69+B23) | C17: =MIN(1,Inputs!$B$69+C23) | D17: =MIN(1,Inputs!$B$69+D23) | E17: =MIN(1,Inputs!$B$69+E23) | F17: =B17*Inputs!$B$39+C17*Inputs!$B$40+D17*Inputs!$B$41+E17*Inputs!$B$50 | G17: =B17*$C$6+C17*$C$7+D17*$C$8+E17*$C$9 | H17: =B17*Inputs!$B$39*Inputs!$B$74+C17*Inputs!$B$40*Inputs!$B$75+D17*Inputs!$B$41*Inputs!$B$76+E17*Inputs!$B$50*Inputs!$B$77 | I17: =F17/Inputs!$B$49 | J17: =G17/$C$10
A18: EU Art 6(3)(a) vertical | B18: =Inputs!$B$68*Inputs!$B$70 | C18: =Inputs!$B$68*Inputs!$B$71 | D18: =Inputs!$B$68*Inputs!$B$72 | E18: =Inputs!$B$68*Inputs!$B$73 | F18: =B18*Inputs!$B$39+C18*Inputs!$B$40+D18*Inputs!$B$41+E18*Inputs!$B$50 | G18: =B18*$C$6+C18*$C$7+D18*$C$8+E18*$C$9 | H18: =B18*Inputs!$B$39*Inputs!$B$74+C18*Inputs!$B$40*Inputs!$B$75+D18*Inputs!$B$41*Inputs!$B$76+E18*Inputs!$B$50*Inputs!$B$77 | I18: =F18/Inputs!$B$49 | J18: =G18/$C$10
A19: EU Art 6(3)(d) first loss | B19: =IF(E19*Inputs!$B$50+D19*Inputs!$B$41+C19*Inputs!$B$40<Inputs!$B$68*Inputs!$B$49,1,0) | C19: =IF(E19*Inputs!$B$50+D19*Inputs!$B$41<Inputs!$B$68*Inputs!$B$49,1,0) | D19: =IF(E19*Inputs!$B$50<Inputs!$B$68*Inputs!$B$49,1,0) | E19: =IF(0<Inputs!$B$68*Inputs!$B$49,1,0) | F19: =B19*Inputs!$B$39+C19*Inputs!$B$40+D19*Inputs!$B$41+E19*Inputs!$B$50 | G19: =B19*$C$6+C19*$C$7+D19*$C$8+E19*$C$9 | H19: =B19*Inputs!$B$39*Inputs!$B$74+C19*Inputs!$B$40*Inputs!$B$75+D19*Inputs!$B$41*Inputs!$B$76+E19*Inputs!$B$50*Inputs!$B$77 | I19: =F19/Inputs!$B$49 | J19: =G19/$C$10
A22: Helper: horizontal component of the L-shaped option
A23: L-shape horizontal component | B23: =IF(Retention!$C$6<=0,0,MIN(1,MAX(0,(Inputs!$B$68-Inputs!$B$69)*$C$10-E23*Retention!$C$9-D23*Retention!$C$8-C23*Retention!$C$7)/Retention!$C$6)) | C23: =IF(Retention!$C$7<=0,0,MIN(1,MAX(0,(Inputs!$B$68-Inputs!$B$69)*$C$10-E23*Retention!$C$9-D23*Retention!$C$8)/Retention!$C$7)) | D23: =IF(Retention!$C$8<=0,0,MIN(1,MAX(0,(Inputs!$B$68-Inputs!$B$69)*$C$10-E23*Retention!$C$9)/Retention!$C$8)) | E23: =IF(Retention!$C$9<=0,0,MIN(1,MAX(0,(Inputs!$B$68-Inputs!$B$69)*$C$10)/Retention!$C$9))
A26: Retained position and financing view (selected scenario)
A27: Option | B27: Total cash received | C27: Yield at cost (monthly IRR x 12) | D27: Advance | E27: Advance / cost | F27: PV coverage (retained CF PV at financing rate / advance) | G27: Loan repaid in month | H27: Unpaid loan at horizon | I27: Levered IRR
A28: US RR vertical 246.4(a)(1) | B28: =SUM(Retention_CF!$H$6:$H$101) | C28: =IFERROR(12*IRR(Retention_CF!$H$5:$H$101,0.005),IFERROR(12*IRR(Retention_CF!$H$5:$H$101,-0.03),IFERROR(12*IRR(Retention_CF!$H$5:$H$101,-0.1),"n/a"))) | D28: =Retention!$H$15 | E28: =D28/Retention!$F$15 | F28: =SUMPRODUCT(Retention_CF!$H$6:$H$101,Retention_CF!$G$6:$G$101)/D28 | G28: =IF(Retention_CF!I101<=0.005,COUNTIF(Retention_CF!$I$6:$I$101,">0.005")+1,"not repaid") | H28: =Retention_CF!I101 | I28: =IFERROR(12*IRR(Retention_CF!$L$5:$L$101,0.005),IFERROR(12*IRR(Retention_CF!$L$5:$L$101,-0.03),IFERROR(12*IRR(Retention_CF!$L$5:$L$101,-0.1),"n/a")))
A29: US RR horizontal 246.4(a)(2) | B29: =SUM(Retention_CF!$M$6:$M$101) | C29: =IFERROR(12*IRR(Retention_CF!$M$5:$M$101,0.005),IFERROR(12*IRR(Retention_CF!$M$5:$M$101,-0.03),IFERROR(12*IRR(Retention_CF!$M$5:$M$101,-0.1),"n/a"))) | D29: =Retention!$H$16 | E29: =D29/Retention!$F$16 | F29: =SUMPRODUCT(Retention_CF!$M$6:$M$101,Retention_CF!$G$6:$G$101)/D29 | G29: =IF(Retention_CF!N101<=0.005,COUNTIF(Retention_CF!$N$6:$N$101,">0.005")+1,"not repaid") | H29: =Retention_CF!N101 | I29: =IFERROR(12*IRR(Retention_CF!$Q$5:$Q$101,0.005),IFERROR(12*IRR(Retention_CF!$Q$5:$Q$101,-0.03),IFERROR(12*IRR(Retention_CF!$Q$5:$Q$101,-0.1),"n/a")))
A30: US RR L-shaped 246.4(a)(3) | B30: =SUM(Retention_CF!$R$6:$R$101) | C30: =IFERROR(12*IRR(Retention_CF!$R$5:$R$101,0.005),IFERROR(12*IRR(Retention_CF!$R$5:$R$101,-0.03),IFERROR(12*IRR(Retention_CF!$R$5:$R$101,-0.1),"n/a"))) | D30: =Retention!$H$17 | E30: =D30/Retention!$F$17 | F30: =SUMPRODUCT(Retention_CF!$R$6:$R$101,Retention_CF!$G$6:$G$101)/D30 | G30: =IF(Retention_CF!S101<=0.005,COUNTIF(Retention_CF!$S$6:$S$101,">0.005")+1,"not repaid") | H30: =Retention_CF!S101 | I30: =IFERROR(12*IRR(Retention_CF!$V$5:$V$101,0.005),IFERROR(12*IRR(Retention_CF!$V$5:$V$101,-0.03),IFERROR(12*IRR(Retention_CF!$V$5:$V$101,-0.1),"n/a")))
A31: EU Art 6(3)(a) vertical | B31: =SUM(Retention_CF!$W$6:$W$101) | C31: =IFERROR(12*IRR(Retention_CF!$W$5:$W$101,0.005),IFERROR(12*IRR(Retention_CF!$W$5:$W$101,-0.03),IFERROR(12*IRR(Retention_CF!$W$5:$W$101,-0.1),"n/a"))) | D31: =Retention!$H$18 | E31: =D31/Retention!$F$18 | F31: =SUMPRODUCT(Retention_CF!$W$6:$W$101,Retention_CF!$G$6:$G$101)/D31 | G31: =IF(Retention_CF!X101<=0.005,COUNTIF(Retention_CF!$X$6:$X$101,">0.005")+1,"not repaid") | H31: =Retention_CF!X101 | I31: =IFERROR(12*IRR(Retention_CF!$AA$5:$AA$101,0.005),IFERROR(12*IRR(Retention_CF!$AA$5:$AA$101,-0.03),IFERROR(12*IRR(Retention_CF!$AA$5:$AA$101,-0.1),"n/a")))
A32: EU Art 6(3)(d) first loss | B32: =SUM(Retention_CF!$AB$6:$AB$101) | C32: =IFERROR(12*IRR(Retention_CF!$AB$5:$AB$101,0.005),IFERROR(12*IRR(Retention_CF!$AB$5:$AB$101,-0.03),IFERROR(12*IRR(Retention_CF!$AB$5:$AB$101,-0.1),"n/a"))) | D32: =Retention!$H$19 | E32: =D32/Retention!$F$19 | F32: =SUMPRODUCT(Retention_CF!$AB$6:$AB$101,Retention_CF!$G$6:$G$101)/D32 | G32: =IF(Retention_CF!AC101<=0.005,COUNTIF(Retention_CF!$AC$6:$AC$101,">0.005")+1,"not repaid") | H32: =Retention_CF!AC101 | I32: =IFERROR(12*IRR(Retention_CF!$AF$5:$AF$101,0.005),IFERROR(12*IRR(Retention_CF!$AF$5:$AF$101,-0.03),IFERROR(12*IRR(Retention_CF!$AF$5:$AF$101,-0.1),"n/a")))

Sheet Scenario_Summary
A1: Scenario summary and integrity checks (live for the scenario selected on Inputs)
A2: Active scenario | B2: =Inputs!$B$26
A3: CPR | B3: CDR | C3: Severity | D3: Lag (months) | E3: Forward shift bps
A4: =Inputs!$B$27 | B4: =Inputs!$B$28 | C4: =Inputs!$B$29 | D4: =Inputs!$B$30 | E4: =Inputs!$B$31
A6: Tranche | B6: Original balance | C6: Interest paid | D6: Principal paid | E6: Write-down / capital shortfall | F6: Ending balance | G6: WAL (years) | H6: Yield at par (monthly IRR x 12) | I6: Principal window first | J6: Principal window last | K6: Conservation check (orig - paid - writedown - end) | L6: Takes loss (1/0)
A7: A | B7: =Inputs!$B$39 | C7: =SUM(CashFlows!$B$6:$B$101) | D7: =SUM(CashFlows!$C$6:$C$101) | E7: =SUM(CashFlows!$D$6:$D$101) | F7: =CashFlows!E101 | G7: =IF(D7<=0.005,"n/a",SUMPRODUCT(CashFlows!$A$6:$A$101,CashFlows!$C$6:$C$101)/12/D7) | H7: =IFERROR(12*IRR(CashFlows!$F$5:$F$101,0.005),IFERROR(12*IRR(CashFlows!$F$5:$F$101,-0.03),IFERROR(12*IRR(CashFlows!$F$5:$F$101,-0.1),"n/a"))) | I7: =IF(D7<=0.005,"n/a",_xlfn.MINIFS(CashFlows!$A$6:$A$101,CashFlows!$C$6:$C$101,">0.005")) | J7: =IF(D7<=0.005,"n/a",_xlfn.MAXIFS(CashFlows!$A$6:$A$101,CashFlows!$C$6:$C$101,">0.005")) | K7: =B7-D7-E7-F7 | L7: =IF(E7>1,1,0)
A8: B | B8: =Inputs!$B$40 | C8: =SUM(CashFlows!$G$6:$G$101) | D8: =SUM(CashFlows!$H$6:$H$101) | E8: =SUM(CashFlows!$I$6:$I$101) | F8: =CashFlows!J101 | G8: =IF(D8<=0.005,"n/a",SUMPRODUCT(CashFlows!$A$6:$A$101,CashFlows!$H$6:$H$101)/12/D8) | H8: =IFERROR(12*IRR(CashFlows!$K$5:$K$101,0.005),IFERROR(12*IRR(CashFlows!$K$5:$K$101,-0.03),IFERROR(12*IRR(CashFlows!$K$5:$K$101,-0.1),"n/a"))) | I8: =IF(D8<=0.005,"n/a",_xlfn.MINIFS(CashFlows!$A$6:$A$101,CashFlows!$H$6:$H$101,">0.005")) | J8: =IF(D8<=0.005,"n/a",_xlfn.MAXIFS(CashFlows!$A$6:$A$101,CashFlows!$H$6:$H$101,">0.005")) | K8: =B8-D8-E8-F8 | L8: =IF(E8>1,1,0)
A9: C | B9: =Inputs!$B$41 | C9: =SUM(CashFlows!$L$6:$L$101) | D9: =SUM(CashFlows!$M$6:$M$101) | E9: =SUM(CashFlows!$N$6:$N$101) | F9: =CashFlows!O101 | G9: =IF(D9<=0.005,"n/a",SUMPRODUCT(CashFlows!$A$6:$A$101,CashFlows!$M$6:$M$101)/12/D9) | H9: =IFERROR(12*IRR(CashFlows!$P$5:$P$101,0.005),IFERROR(12*IRR(CashFlows!$P$5:$P$101,-0.03),IFERROR(12*IRR(CashFlows!$P$5:$P$101,-0.1),"n/a"))) | I9: =IF(D9<=0.005,"n/a",_xlfn.MINIFS(CashFlows!$A$6:$A$101,CashFlows!$M$6:$M$101,">0.005")) | J9: =IF(D9<=0.005,"n/a",_xlfn.MAXIFS(CashFlows!$A$6:$A$101,CashFlows!$M$6:$M$101,">0.005")) | K9: =B9-D9-E9-F9 | L9: =IF(E9>1,1,0)
A10: R | B10: =Inputs!$B$50 | C10: =SUM(CashFlows!$Q$6:$Q$101) | D10: =SUM(CashFlows!$R$6:$R$101) | E10: =MAX(0,B10-C10-D10) | F10: 0 | G10: =IF(D10<=0.005,"n/a",SUMPRODUCT(CashFlows!$A$6:$A$101,CashFlows!$R$6:$R$101)/12/D10) | H10: =IFERROR(12*IRR(CashFlows!$S$5:$S$101,0.005),IFERROR(12*IRR(CashFlows!$S$5:$S$101,-0.03),IFERROR(12*IRR(CashFlows!$S$5:$S$101,-0.1),"n/a"))) | I10: =IF(D10<=0.005,"n/a",_xlfn.MINIFS(CashFlows!$A$6:$A$101,CashFlows!$R$6:$R$101,">0.005")) | J10: =IF(D10<=0.005,"n/a",_xlfn.MAXIFS(CashFlows!$A$6:$A$101,CashFlows!$R$6:$R$101,">0.005")) | K10: n/a | L10: =IF(E10>1,1,0)
A12: For R: column C is residual interest distributions, D is principal distributions plus reserve release, E is the capital shortfall (par less cash received, floored at 0).
A14: Integrity checks (sum of absolute differences, should be 0)
A15: Pool balance reconciliation | B15: =SUMPRODUCT(ABS(Pool!$BX$6:$BX$101))
A16: Cash conservation | B16: =SUMPRODUCT(ABS(Waterfall!$BZ$6:$BZ$101))
A17: Notes P+I plus fees paid above collateral cash plus reserve draw (sum of excesses) | B17: =SUMPRODUCT(((Waterfall!$BU$6:$BU$101+Waterfall!$AE$6:$AE$101-Pool!$BW$6:$BW$101-Waterfall!$R$6:$R$101)>0.005)*(Waterfall!$BU$6:$BU$101+Waterfall!$AE$6:$AE$101-Pool!$BW$6:$BW$101-Waterfall!$R$6:$R$101))
A18: Tranche conservation A | B18: =ABS(K7)
A19: Tranche conservation B | B19: =ABS(K8)
A20: Tranche conservation C | B20: =ABS(K9)
A21: Months with a trigger breach | B21: =SUM(Tests!$M$6:$M$101)
A22: Excess spread at month 12 (bps annualized) | B22: =Tests!O17
A23: Cumulative net loss % of pool at horizon | B23: =Tests!P101
A26: Break-even CDR per tranche is solved by bisection in python/ (Excel has no live solver). Set the CDR of a scenario to a Python break-even value here to confirm zero loss just below it.
A27: Scenario table lives on Inputs; change the selected scenario number there to recalculate every sheet.
